Workbook

Sheet 00_README
A1: FINAL Master Workbook — LLM-Assisted Threat Modeling Evaluation (CORRECTED)
A2: Single source of truth for quantitative thesis results. All derived values are live Excel formulas; nothing derived is hard-coded.
A4: PURPOSE: This workbook is the audited, corrected version of the master evaluation workbook. It has been rebuilt from the authoritative source artifacts so that every final metric is traceable back through the calculation sheet -> TP/FP/FN -> per-finding mapping -> generated finding -> original source, and every Recall value is traceable to the expert reference baseline.
A5: AUDIT AUTHORITY (important): 1) Expert reference baselines (Scenario{1,2,3}_Expert_Reference_Baseline_FINAL.csv) are treated as the authoritative comparison baseline (NOT as infallible truth). 2) matching.csv is treated as the authoritative per-finding matching decision record (one row per generated finding). 3) The previously-exported PDF workbook displayed a TP/FP/Duplicate set that does NOT match matching.csv; this discrepancy is flagged in 15_DATA_QUALITY and Section A/C of the audit report.
A6: AUDIT ASSUMPTIONS: (a) One-to-one rule implemented: within each Approach x Scenario a reference threat contributes exactly one Primary TP; additional equivalent findings are Duplicates. (b) Recall = Primary TP / Reference threats; Duplicates do NOT add recall. (c) Precision follows the stated formula TP/(TP+FP) using Primary TP; a supplementary "per-finding precision incl. duplicates" is also shown. (d) Metrics that the source data cannot support are reported as N/A and FLAGGED, never fabricated.
A7: MISSING DATA (flagged N/A): (1) Per-finding GROUNDING annotation - not provided -> 08_GROUNDING = N/A. (2) Approach FEATURE/FUNCTIONALITY matrix - documentation not provided -> all cells "Unknown", feature completeness & MCDM composite = N/A. (3) Per-finding STRIDE classification for False-Positive findings - not provided -> STRIDE precision/FP/Generated = N/A (STRIDE recall computed at reference level). (4) No SUS/usability study - no SUS scores computed.
A8: TERMINOLOGY: OWASP = OWASP Threat Dragon; TMT = Microsoft Threat Modeling Tool; CHATGPT = ChatGPT; OLLAMA = Ollama (local LLM); THREMOLIA = ThreMoLIA.
A9: COLOUR KEY: BLUE = raw generated data (verbatim). GREEN = validated reference baseline. YELLOW = manual matching/mapping coding. RED = failed check. GREY = fixed parameters/metadata.
A10: STATISTICAL CAVEAT: There are only three scenarios (n=3). The 1,025 generated findings are NOT treated as independent statistical observations; scenario-level descriptive statistics are the primary analysis. No inferential tests were performed.
A11: METHODOLOGICAL RULES: See 15_DATA_QUALITY, 16_CHANGE_LOG and this README. Rules: one-to-one rule; semantic (not keyword) matching; Precision=TP/(TP+FP); Recall=TP/Reference; FN=Reference-TP; F1 harmonic; no accuracy/TN; grounding separate from correctness; severity only from baseline; MCDM = decision-support synthesis (30/30/20/20), not a statistical metric.
A12: DISCLAIMER: The workbook is not claimed to be perfect. Unresolved items are listed in 15_DATA_QUALITY and in the accompanying audit report (AUDIT_REPORT.md).

Sheet 01_SCENARIOS
A1: Scenario Architecture and Volume Overview
A2: All counts are formulas over 02_REFERENCE / 03_RAW_FINDINGS / 04_MATCHING.
A4: Scenario | B4: Scenario Name | C4: Reference threats | D4: LLM-specific refs | E4: OWASP | F4: TMT | G4: CHATGPT | H4: OLLAMA | I4: THREMOLIA | J4: Total findings
A5: S1 | B5: S1 - User authentication web app with AI chatbot assistant | C5: =COUNTIFS('02_REFERENCE'!$B$2:$B$99,$A5,'02_REFERENCE'!$S$2:$S$99,"YES") -> 32 | D5: =COUNTIFS('02_REFERENCE'!$B$2:$B$99,$A5,'02_REFERENCE'!$S$2:$S$99,"YES",'02_REFERENCE'!$Q$2:$Q$99,"Yes") -> 13 | E5: =COUNTIFS('04_MATCHING'!$B$2:$B$1026,"OWASP",'04_MATCHING'!$C$2:$C$1026,$A5) -> 38 | F5: =COUNTIFS('04_MATCHING'!$B$2:$B$1026,"TMT",'04_MATCHING'!$C$2:$C$1026,$A5) -> 95 | G5: =COUNTIFS('04_MATCHING'!$B$2:$B$1026,"CHATGPT",'04_MATCHING'!$C$2:$C$1026,$A5) -> 72 | H5: =COUNTIFS('04_MATCHING'!$B$2:$B$1026,"OLLAMA",'04_MATCHING'!$C$2:$C$1026,$A5) -> 40 | I5: =COUNTIFS('04_MATCHING'!$B$2:$B$1026,"THREMOLIA",'04_MATCHING'!$C$2:$C$1026,$A5) -> 106 | J5: =SUM(E5:I5) -> 351
A6: S2 | B6: S2 - Secure file management platform with AI file assistant (external LLM) | C6: =COUNTIFS('02_REFERENCE'!$B$2:$B$99,$A6,'02_REFERENCE'!$S$2:$S$99,"YES") -> 33 | D6: =COUNTIFS('02_REFERENCE'!$B$2:$B$99,$A6,'02_REFERENCE'!$S$2:$S$99,"YES",'02_REFERENCE'!$Q$2:$Q$99,"Yes") -> 13 | E6: =COUNTIFS('04_MATCHING'!$B$2:$B$1026,"OWASP",'04_MATCHING'!$C$2:$C$1026,$A6) -> 39 | F6: =COUNTIFS('04_MATCHING'!$B$2:$B$1026,"TMT",'04_MATCHING'!$C$2:$C$1026,$A6) -> 89 | G6: =COUNTIFS('04_MATCHING'!$B$2:$B$1026,"CHATGPT",'04_MATCHING'!$C$2:$C$1026,$A6) -> 60 | H6: =COUNTIFS('04_MATCHING'!$B$2:$B$1026,"OLLAMA",'04_MATCHING'!$C$2:$C$1026,$A6) -> 28 | I6: =COUNTIFS('04_MATCHING'!$B$2:$B$1026,"THREMOLIA",'04_MATCHING'!$C$2:$C$1026,$A6) -> 105 | J6: =SUM(E6:I6) -> 321
A7: S3 | B7: S3 - Account recovery & profile management with AI support assistant (external LLM) | C7: =COUNTIFS('02_REFERENCE'!$B$2:$B$99,$A7,'02_REFERENCE'!$S$2:$S$99,"YES") -> 33 | D7: =COUNTIFS('02_REFERENCE'!$B$2:$B$99,$A7,'02_REFERENCE'!$S$2:$S$99,"YES",'02_REFERENCE'!$Q$2:$Q$99,"Yes") -> 12 | E7: =COUNTIFS('04_MATCHING'!$B$2:$B$1026,"OWASP",'04_MATCHING'!$C$2:$C$1026,$A7) -> 46 | F7: =COUNTIFS('04_MATCHING'!$B$2:$B$1026,"TMT",'04_MATCHING'!$C$2:$C$1026,$A7) -> 117 | G7: =COUNTIFS('04_MATCHING'!$B$2:$B$1026,"CHATGPT",'04_MATCHING'!$C$2:$C$1026,$A7) -> 49 | H7: =COUNTIFS('04_MATCHING'!$B$2:$B$1026,"OLLAMA",'04_MATCHING'!$C$2:$C$1026,$A7) -> 24 | I7: =COUNTIFS('04_MATCHING'!$B$2:$B$1026,"THREMOLIA",'04_MATCHING'!$C$2:$C$1026,$A7) -> 117 | J7: =SUM(E7:I7) -> 353
A8: TOTAL | B8: Grand total (three scenarios, five approaches) | C8: =SUM(C5:C7) -> 98 | D8: =SUM(D5:D7) -> 38 | E8: =SUM(E5:E7) -> 123 | F8: =SUM(F5:F7) -> 301 | G8: =SUM(G5:G7) -> 181 | H8: =SUM(H5:H7) -> 92 | I8: =SUM(I5:I7) -> 328 | J8: =SUM(J5:J7) -> 1025
A10: Architecture note
A11: TMT and ThreMoLIA model the architectures with different element/flow identifiers (TMT decomposes services; ThreMoLIA uses its own DF/SF numbering). Matching (04) is semantic, never identifier-based. Each scenario's reference baseline is frozen as provided.

Sheet 02_REFERENCE
A1: Expert Reference Baseline (98 threats)
A2: S1-RT-001 | B2: S1 | C2: Online brute-force password guessing | D2: Spoofing | E2: Authentication | F2: P2 Authentication Service (reached via P1 Web Frontend) | G2: DF1, DF2, DF3 | H2: TB1 | I2: User credentials; authentication decision | J2: Unbounded automated password guessing against the credential verification path: the attacker iterates candidate passwords for a known username until the verification result on DF4 indicates success; anti-automation is not specified by the architecture anywhere between the DF1 entry point and the DF3 verification cycle. | K2: An attacker obtains a valid username through enumeration (S1-RT-003), then scripts repeated login submissions on DF1, each carrying the same username with the next candidate password. P1 forwards every attempt on DF2, P2 executes a DF3 verification against DS1 for each, and no element in the drawn architecture limits attempt count or frequency. On the first successful verification the attacker receives a session token via DF6 and holds the account. | L2: Account takeover: one guessed password yields a valid session token on DF6, because the architecture specifies credential verification as the sole authentication factor and no second factor or step-up mechanism is drawn anywhere. | M2: P2 is the sole authentication decision authority (stated assumption A1) and is anonymously reachable because DF1 crosses TB1 from the untrusted End User environment. The DF2 to DF3 verification cycle is unbounded in the drawn architecture: no anti-automation or attempt-limiting element is specified on any flow. OWASP A07 places anti-automation at exactly this point. | N2: Final audit: retained. Architecture-grounded (DF1, DF2, DF3, TB1, A1); distinct from S1-RT-002, which is breadth-first replay of breached pairs rather than depth-first guessing; objectively matchable by attack pattern. Primary STRIDE is Spoofing: the attacker presents a credential they do not own in order to be recognised as the account owner. Control-gap phrasing applied per rule 7: anti-automation is described as not specified, not as definitely absent. Evaluation note: if lockout-style anti-automation is implemented, it admits its own denial-of-access abuse vector, which is documented in the audit summary rather than retained as a separate architecture-level threat. | O2: High | P2: High | Q2: No | R2: High | S2: YES
A3: S1-RT-002 | B3: S1 | C3: Credential stuffing using breached credential corpora | D3: Spoofing | E3: Authentication | F3: P2 Authentication Service | G3: DF1, DF2 | H3: TB1 | I3: User credentials; user accounts | J3: Distributed low-rate replay of externally breached username and password pairs across many accounts and sources, producing a per-account request pattern that per-account anti-automation, where implemented at all, does not detect. | K3: The attacker loads a corpus of breached credential pairs and submits each pair exactly once per account, distributed across many sources. Every account sees at most one failed DF3 verification, so any per-account attempt limit never trips; every password the victim reuses elsewhere yields a session token on DF6 for the attacker. | L3: Mass account takeover proportional to the password-reuse rate in the user population, with a session token issued on DF6 for every successful pair. | M3: Like S1-RT-001 this exploits the anonymous reachability of DF1 across TB1 into P2, but the attack path is breadth-first across accounts rather than depth-first against one, producing a statistically different DF2 request pattern; OWASP treats stuffing and brute force as distinct techniques with distinct controls (breached-password screening versus attempt limiting). | N3: Final audit: retained. Distinct mechanism from S1-RT-001 (request pattern, detection signal and control all differ), so the pair is not merged. Primary STRIDE is Spoofing: valid credentials of the real owner are used to impersonate them. Conditional phrasing applied: the presence of any attempt-limiting control is treated as unspecified, and the mechanism is stated as the pattern such controls fail to catch. | O3: High | P3: High | Q3: No | R3: High | S3: YES
A4: S1-RT-003 | B4: S1 | C4: Username and account enumeration | D4: Information Disclosure | E4: Authentication | F4: P2 Authentication Service; P1 Web Frontend | G4: DF1, DF2, DF4 | H4: TB1 | I4: Account existence metadata (PII) | J4: Differential response content, status or timing between existing and non-existing accounts turns the login and registration functions into an account-existence oracle whose signal crosses TB1 to the untrusted user environment. | K4: The attacker submits login attempts for candidate usernames with a fixed wrong password and compares the returned responses: an account-specific response for existing usernames versus a generic one for non-existing usernames, or a measurable timing difference carried by the DF4 result through P2 and P1, confirms which accounts exist before any guessing begins. | L4: Produces a validated target list that raises the yield of S1-RT-001 and S1-RT-002, and discloses membership information about identifiable persons. | M4: The verification outcome produced on DF4 propagates back through P2 and P1 and crosses TB1 to the untrusted user environment; response uniformity is not specified by the architecture, so differentiating responses are an architecture-level exposure rather than an implementation accident. ASVS V2.2 requires uniform authentication responses at exactly this point. | N4: Final audit: retained. An enabler rather than a direct compromise (Severity Medium) but a distinct mechanism, a design-level response oracle, separable from S1-RT-019 (diagnostic-content disclosure) by inspection method and asset. Primary STRIDE is Information Disclosure: the leaked asset is account existence metadata. No implementation assumption is required: the oracle is defined by response differentiation across a drawn boundary. | O4: Medium | P4: High | Q4: No | R4: High | S4: YES
A5: S1-RT-004 | B5: S1 | C5: Authentication bypass through flawed authentication logic | D5: Spoofing | E5: Authentication | F5: P2 Authentication Service; P3 Session Management Module | G5: DF2, DF5 | H5: TB1; internal P2-to-P3 transition | I5: Authentication decision; session tokens | J5: Request manipulation reaches session creation on DF5 without a successful verification result: forged or mishandled verification state passed from P2 to P3, or direct invocation of the P3 session-creation function where it is independently reachable. | K5: The attacker submits crafted login content that causes P2 to pass an incomplete or mishandled verification result to the session-creation step, or invokes P3's session-creation function directly with a chosen identity; P3 issues a token on DF6 for an arbitrary account whose credentials were never verified against DS1. | L5: Complete authentication bypass: a valid session token is issued on DF6 for an arbitrary identity without any credential ever being verified, defeating the architecture's central property that P2 alone decides authentication. | M5: Nothing in the drawn architecture forces DF5 to be preceded by a successful DF3/DF4 verification; the ordering constraint is an implementation convention rather than an enforced control, and the attacker input that drives the bypass enters across TB1 on DF1 and DF2. Stated assumption A1 makes P2 the sole authentication authority, so any path to DF5 around verification defeats a stated property with no drawn enforcement point. OWASP A04 (insecure design) applies. | N5: Final audit: retained. Primary STRIDE is Spoofing: an unverified identity is accepted as an authenticated subject, which is the essence of spoofing; elevation of privilege is the downstream consequence when privileged accounts are targeted and is retained as a secondary note here only. Implementation-specific payload examples (type-confusion values) were removed; the mechanism is stated at the level of the unenforced DF3/DF4-before-DF5 ordering, which the drawn architecture fully supports. Severity Critical: the bypass mints sessions for arbitrary identities. | O5: Critical | P5: Medium | Q5: No | R5: High | S5: YES
A6: S1-RT-006 | B6: S1 | C6: Exposure of credentials in transit on the authentication paths | D6: Information Disclosure | E6: Authentication | F6: P1 Web Frontend; P2 Authentication Service | G6: DF1, DF2 | H6: TB1 (external leg); internal P1-to-P2 leg | I6: User credentials | J6: Credentials in plaintext form traverse DF1 across TB1 and the internal DF2 leg, and confidentiality protection for these flows is not specified by the architecture; an actor positioned on either path reads submitted credentials. | K6: An actor positioned on the communication path between the End User and P1, or between P1 and P2, reads the username and password of every login submission traversing DF1 and DF2. Any implementation-side persistence of flow content, which the architecture does not specify, would extend the same exposure to stored artefacts and is treated as conditional. | L6: Direct exposure of plaintext passwords, enabling immediate account takeover and cross-service reuse independent of any guessing. | M6: DF1 and DF2 are the only flows in the model that carry plaintext credentials; DF1 crosses TB1 into the application; no confidentiality control for either flow is specified anywhere in the architecture, and under A6 that unspecified protection is itself the architecture-level finding. OWASP A02 applies. | N6: Final audit: retained with a technology-neutral rewrite. The first-pass wording referenced transport-security mechanisms and logging artefacts that the architecture does not specify; the mechanism is now stated purely as unprotected credential-bearing flows across drawn boundaries, with persistence-based exposure phrased conditionally (rules 1 and 7). Distinct from S1-RT-001 and S1-RT-002: credentials are captured rather than guessed. Primary STRIDE is Information Disclosure. | O6: High | P6: High | Q6: No | R6: High | S6: YES
A7: S1-RT-008 | B7: S1 | C7: Injection into the credential verification exchange | D7: Tampering | E7: Authorization | F7: P2 Authentication Service; DS1 User Database | G7: DF3, DF4 | H7: TB3 | I7: User credentials; password hashes; authentication decision | J7: Untrusted input submitted on DF1 influences the verification request that P2 composes on DF3, altering what DS1 returns on DF4: the store result can be forced positive, or the exchange can be steered to return stored records beyond the intended lookup. | K7: The attacker submits a crafted username whose content changes the semantics of the DF3 verification request so that the DF4 response indicates success without the correct password; the same flaw is then steered to return stored credential records from DS1 instead of a single verification result. | L7: Simultaneous authentication bypass and mass disclosure of usernames and password hashes, the worst combined confidentiality and access-control outcome available in this architecture. | M7: DF3, issued by P2 against DS1, is the only flow in the model where untrusted text that entered P1 across TB1 is transformed into a request interpreted by a higher-authority component across TB3; the taint path DF1 to DF2 to DF3 contains no validation or separation element, a confused-deputy condition at the TB3 crossing. OWASP A03 applies. | N7: Final audit: retained with a technology-neutral rewrite: implementation-specific injection constructs were removed, and the mechanism is stated as untrusted influence over the DF3/DF4 verification exchange, which the drawn architecture fully supports. Matching note: a candidate threat describing injection into the session-validation lookups on SF1/SF3 matches this entry, since the taint pattern and the mitigation class are identical. Primary STRIDE is Tampering: the integrity of the verification request is violated; bypass and extraction are consequences. | O7: Critical | P7: Medium | Q7: No | R7: High | S7: YES
A8: S1-RT-009 | B8: S1 | C8: Excessive database access scope across the application-to-database boundary | D8: Elevation of Privilege | E8: Authorization | F8: Application services and store layer (P2, P3, P4 interacting with DS1, DS2, DS3) | G8: DF3, DF4, SF1, SF2 | H8: TB3 | I8: User credentials; session tokens; LLM context repository | J8: Access scoping at the TB3 crossing is not specified by the architecture: nothing requires that each service's store access be limited to the store it legitimately uses, so a compromised or defective service can read and write stores it never requires. | K8: An attacker who compromises P4 operates with its store access; because no per-service scoping is specified, the attacker reaches DS1 and DS2, password hashes and session tokens, although P4 legitimately requires only DS3. | L8: Compromise of any one application service yields read or write access to stores it does not need, so a defect in a lower-value service exposes authentication credentials in DS1 or session tokens in DS2. | M8: TB3 exists to ensure that access to authentication and session data is subject to controlled authorisation. The model shows three distinct services crossing TB3 towards three distinct stores with disjoint legitimate needs: P2 to DS1 on DF3/DF4, P3 to DS2 on SF1, and P4 to DS3 on SF2; how access is scoped at that crossing is not specified, which is recorded as an architecture-level control gap. | N8: Final audit: retained with control-gap phrasing (rule 7): the entry states that scoping is not specified rather than claiming a specific misconfiguration. The entry makes no claim that the chatbot accesses the authentication databases: the architecture states the opposite, and access scoping is the control that keeps that stated property true under component compromise. Distinct from S1-RT-017, which addresses direct compromise of the session store itself. Primary STRIDE is Elevation of Privilege. | O8: High | P8: Medium | Q8: No | R8: High | S8: YES
A9: S1-RT-010 | B9: S1 | C9: Broken object-level authorisation on account data | D9: Elevation of Privilege | E9: Authorization | F9: P2 Authentication Service; P1 Web Frontend | G9: DF2, DF3, DF4 | H9: TB1; TB3 | I9: Account information (PII); authentication decision | J9: An authenticated user substitutes another user's identifier in an account request, and P2 composes the DF3 request from the client-supplied identifier rather than from the identity bound to the authenticated session. | K9: After logging in normally, the attacker submits an account-information request naming a victim's identifier; P2 queries DS1 on DF3 using the supplied identifier and returns or modifies the victim's account record, because no element binds the DF3 access to the identity established at authentication. | L9: Unauthorised read or modification of other users' account information held in DS1. | M9: Identity is established when DF4 returns a successful verification result, but the drawn architecture contains no enforcement element that binds subsequent DS1 access on DF3 to that established identity; authentication and authorisation are therefore separable in this design, and a request may cross TB1 with a valid session and still address another subject's data across TB3. OWASP A01 applies. | N9: Final audit: retained. Primary STRIDE is Elevation of Privilege: the attacker accesses an object belonging to another subject; information disclosure is the consequence and is noted as secondary here only. The grounding is absence-based (no authorisation-enforcement element is drawn), which is stated as a control gap rather than a definite flaw, hence Confidence Medium. Objectively matchable: any candidate threat describing unauthorised access to another user's account record through identifier substitution matches. | O9: High | P9: High | Q9: No | R9: Medium | S9: YES
A10: S1-RT-011 | B10: S1 | C10: Missing authorisation on the chatbot interface | D10: Elevation of Privilege | E10: Authorization | F10: P4 AI Chatbot Component | G10: DF7, SF3 | H10: TB1 | I10: LLM context; generated responses; provider quota | J10: The chatbot interface is invoked directly rather than through the user interface, without presenting a valid session token, or the SF3 validation step is absent or advisory only, so the LLM pipeline is reachable without authentication. | K10: An unauthenticated client calls the chatbot entry point directly, bypassing the web interface; P4 accepts the question on DF7, retrieves context on SF2, and P5 spends provider quota on DF9, all without a session token ever being presented or validated through SF3. | L10: Anonymous consumption of the downstream LLM pipeline, exposure of approved context and assistant behaviour to unauthenticated parties, and loss of per-user attribution for abuse. | M10: DF7 runs from the untrusted End User directly to P4 and crosses TB1 independently of the DF1-to-DF6 authentication path, so P4 does not inherit any protection established at login; SF3, the session-token validation exchange between P3 and P4, is the only authorisation element on this path, and its enforcement strength is not specified. P4's stated responsibilities include no identity check of its own. | N10: Final audit: retained. Primary STRIDE is Elevation of Privilege: the attacker uses a protected application capability without any entitlement; no identity is forged, so Spoofing is not the primary violation. Classified as not LLM-specific: the defect is a missing access-control check on an application endpoint and would exist identically if P4 served static content. Conditional phrasing applied to the SF3 enforcement strength. Objectively matchable by the unauthenticated-reachability test. | O10: High | P10: Medium | Q10: No | R10: High | S10: YES
A11: S1-RT-012 | B11: S1 | C11: Cross-user context leakage between chatbot sessions | D11: Information Disclosure | E11: Authorization | F11: P4 AI Chatbot Component; P5 LLM Integration Service | G11: DF7, DF8, DF11, DF12 | H11: TB1 | I11: User prompts; LLM context; generated responses | J11: A shared or incorrectly keyed conversation-context buffer causes one user's prior questions or retrieved context to be incorporated into another user's prompt on DF8, or a concurrency defect causes a response on DF11 to be delivered to the wrong requester on DF12. | K11: Two users question the chatbot concurrently; a context buffer keyed incorrectly under load causes user B's assembled prompt on DF8 to include user A's earlier authentication-related questions, and the generated answer is delivered to the wrong requester on DF12 with the application's authority. | L11: Disclosure of one user's authentication-related questions and identifiers to a different user, delivered with the application's authority. | M11: P4 and P5 are single logical processes serving all users, and neither DF8 nor DF11 carries an explicit per-user key in the model; conversation context is required for coherent multi-turn answers yet is not represented as a data store in the architecture, so its isolation is not specified, and the leaked material crosses TB1 to the wrong subject on DF12. | N11: Final audit: retained. AI-specific because the leaked asset is accumulated AI context that exists only because prompts are assembled from conversational state. Distinct from S1-RT-026 (authorised aggregate interrogation, components behaving as designed) and from S1-RT-024 (egress to the provider): here the defect is internal keying or concurrency, and the isolation of the unrepresented context store is stated as an architecture-level gap. Confidence Medium for that reason. | O11: Medium | P11: Medium | Q11: Yes | R11: Medium | S11: YES
A12: S1-RT-013 | B12: S1 | C12: Session fixation on the authentication flow | D12: Spoofing | E12: Session Management | F12: P1 Web Frontend Interface; P3 Session Management Module | G12: DF1, DF5, DF6, SF1 | H12: TB1; TB3 | I12: Session tokens; authenticated sessions | J12: Nothing in the architecture requires that the session identifier issued at the authentication transition be freshly derived: if an identifier the attacker already knows is accepted at DF5, P3 binds the victim's authenticated identity to that pre-existing value instead of generating a fresh one for DF6. | K12: The attacker supplies the victim with an authentication entry point that carries an attacker-chosen session identifier (the mechanism by which identifiers travel to the client is not specified by the architecture); the victim authenticates through it; P3 binds the authenticated identity to the known value, and from the moment login completes the attacker uses that identifier as the victim. | L12: The attacker holds a valid token for the victim's authenticated session from the moment login completes, without observing credentials, predicting a generated value, or intercepting any flow. | M12: Token generation is an explicitly stated responsibility of P3, but the drawn flow set shows creation (DF5), issuance (DF6) and persistence (SF1) without any element requiring that the issued identifier be freshly derived at the authentication transition, so acceptance of a client-influenced identifier is an uncontrolled degree of freedom; ASVS V3.2 requires regeneration at every authentication transition. | N12: Final audit: retained with a technology-neutral rewrite: client-transport mechanisms for identifiers were removed, and the acceptance of a client-influenced identifier is phrased conditionally because identifier transport is not specified (rules 1 and 7). Retained separately from S1-RT-014, S1-RT-015 and S1-RT-016 because the attacker never acquires, computes or reuses a token: the victim authenticates onto an identifier the attacker already holds, a distinct control failure with a distinct mitigation. Primary STRIDE is Spoofing. | O12: High | P12: Medium | Q12: No | R12: High | S12: YES
A13: S1-RT-014 | B13: S1 | C13: Session token theft at the delivery and persistence crossings | D13: Spoofing | E13: Session Management | F13: P3 Session Management Module; P1 Web Frontend; DS2 Session Storage | G13: DF6, SF1 | H13: TB1; TB3 | I13: Session tokens | J13: The bearer token is exposed at its two drawn crossings: at delivery to the client environment on DF6 across TB1, where protection of the token within the client context is not specified, and at persistence to DS2 on SF1 across TB3, where store-side protection is not specified; a captured token is presented as the victim. | K13: Script executing in the victim's client environment, delivered for instance through S1-RT-033, reads the session token where it is exposed to client-side code and exfiltrates it; the attacker presents the token from their own client and operates as the victim for the remaining token lifetime. | L13: Full session hijack: the attacker acts as the victim without possessing credentials, defeating password strength and every login-time control. | M13: The session token is a bearer secret exposed at two distinct boundaries with two distinct control sets: it crosses TB1 on DF6 when delivered to the client, and TB3 on SF1 when persisted to DS2; neither crossing has a specified protection, and no element in the model protects either leg specifically. | N13: Final audit: retained with a technology-neutral rewrite: implementation-specific client-side protections were removed and replaced with the unspecified-protection phrasing for both drawn crossings (rules 1 and 7). Primary STRIDE is Spoofing: the primary violation is unauthorised use of the victim's authenticated session; the capture enabling it is information disclosure, noted as secondary. Both crossings are kept so that a partial mitigation at one boundary is not mistaken for coverage. Severity Critical: terminal node of the injection-to-takeover chain anchored by S1-RT-033. | O13: Critical | P13: Medium | Q13: No | R13: High | S13: YES
... A99: S3-RT-034 | B99: S3 | C99: Profile updates performed without valid recovery authorisation | D99: Elevation of Privilege | E99: Authorization | F99: P3 Profile Management Service; P2 Account Recovery Service | G99: DF8, DF9 (the authorisation precondition's enforcement point is not represented in the model) | H99: TB3 | I99: Profile information; user account information; integrity of the recovery-authorisation precondition | J99: The architecture states that P3 performs updates only after authorised recovery approval, but no flow or element shows how P3 establishes that approval: no P2-to-P3 authorisation flow is drawn, and no consultation of DS2's token state by P3 is represented. If the implementation accepts update requests on DF8 without verifiable proof of a valid recovery authorisation, profile modification is available without the recovery the precondition exists to enforce. | K99: An attacker submits a profile update request on DF8 with no completed recovery behind it — the authorisation precondition absent, forged, or merely asserted in the request; P3 persists the change to DS1 on DF9, and the modification stands although no recovery was ever authorised for the account. | L99: Unauthorised profile modification that bypasses the recovery-authorisation gate entirely, collapsing the stated ordering — recovery first, update after — and arming the downstream paths that manipulated profile data enables, including S3-RT-013 and the recovery arming of S3-RT-008. | M99: A1 makes P2 the only recovery authorisation authority, and the supplied architecture makes authorised recovery approval the stated precondition of every P3 update, yet the model draws neither a flow conveying that approval to P3 nor any P3-side check of it; a stated security property without a represented enforcement point is an architecture-level gap the reference model must record, in the same manner as the token-redemption binding gap of S3-RT-006. | N99: NEW ENTRY added in this review. Reason: the profile-management checklist requires coverage of modification without valid recovery authorisation, and the catalogue's existing profile entries attack record selection (S3-RT-007), field scope (S3-RT-008) and store access (S3-RT-009) but not the precondition itself; the mechanism here is the missing enforcement of the recovery-authorisation gate at P3, which is distinct from all three and admits a distinct mitigation, verifiable authorisation proof bound to the update request. Absence-justified rather than drawn-flow-justified, hence Confidence Medium. Primary STRIDE is Elevation of Privilege: a protected capability is exercised without entitlement. Severity High; Likelihood Medium. Not LLM-specific. | O99: High | P99: Medium | Q99: No | R99: Medium | S99: YES

Sheet 03_RAW_FINDINGS
A1: Raw Generated Findings (1,025, verbatim)
A2: OWASP-S1-F001 | B2: OWASP | C2: S1 | D2: captcha | E2: CAPTCHA defeat | F2: EE1 End User | H2: OWASP/S1
A3: OWASP-S1-F002 | B3: OWASP | C3: S1 | D3: credential_stuffing | E3: Credential stuffing | F3: EE1 End User | H3: OWASP/S1
A4: OWASP-S1-F003 | B4: OWASP | C4: S1 | D4: excessive_db_scope | E4: Least privilege | F4: P1 Web Frontend Interface | H4: OWASP/S1
A5: OWASP-S1-F004 | B5: OWASP | C5: S1 | D5: expedition | E5: Expedition | F5: P1 Web Frontend Interface | H5: OWASP/S1
A6: OWASP-S1-F005 | B6: OWASP | C6: S1 | D6: recon | E6: Vulnerability scanning | F6: P1 Web Frontend Interface | H6: OWASP/S1
A7: OWASP-S1-F006 | B7: OWASP | C7: S1 | D7: dos_service | E7: Denial of Service | F7: P1 Web Frontend Interface | H7: OWASP/S1
A8: OWASP-S1-F007 | B8: OWASP | C8: S1 | D8: recon | E8: Footprinting | F8: P1 Web Frontend Interface | H8: OWASP/S1
A9: OWASP-S1-F008 | B9: OWASP | C9: S1 | D9: excessive_db_scope | E9: Least privilege | F9: P2 Authentication Service | H9: OWASP/S1
A10: OWASP-S1-F009 | B10: OWASP | C10: S1 | D10: expedition | E10: Expedition | F10: P2 Authentication Service | H10: OWASP/S1
A11: OWASP-S1-F010 | B11: OWASP | C11: S1 | D11: recon | E11: Vulnerability scanning | F11: P2 Authentication Service | H11: OWASP/S1
A12: OWASP-S1-F011 | B12: OWASP | C12: S1 | D12: dos_service | E12: Denial of Service | F12: P2 Authentication Service | H12: OWASP/S1
A13: OWASP-S1-F012 | B13: OWASP | C13: S1 | D13: recon | E13: Footprinting | F13: P2 Authentication Service | H13: OWASP/S1
... A39: OWASP-S1-F038 | B39: OWASP | C39: S1 | D39: stored_prompt_injection | E39: Spamming | F39: DS3 Knowledge Base | H39: OWASP/S1
A40: TMT-S1-F001 | B40: TMT | C40: S1 | E40: EE1 End User (Browser) Process Memory Tampered | F40: Diagram 1 | G40: Registration/Login Credentials | H40: TMT/S1
A41: TMT-S1-F002 | B41: TMT | C41: S1 | E41: Cross Site Scripting | F41: Diagram 1 | G41: Registration/Login Credentials | H41: TMT/S1
A42: TMT-S1-F003 | B42: TMT | C42: S1 | E42: Elevation Using Impersonation | F42: Diagram 1 | G42: Registration/Login Credentials | H42: TMT/S1
A43: TMT-S1-F004 | B43: TMT | C43: S1 | E43: P1 Web Frontend Interface Process Memory Tampered | F43: Diagram 1 | G43: Credential Submission | H43: TMT/S1
A44: TMT-S1-F005 | B44: TMT | C44: S1 | E44: Elevation Using Impersonation | F44: Diagram 1 | G44: Credential Submission | H44: TMT/S1
A45: TMT-S1-F006 | B45: TMT | C45: S1 | E45: Spoofing of Destination Data Store DS1 Backend User Database | F45: Diagram 1 | G45: Credential Verification Request | H45: TMT/S1
A46: TMT-S1-F007 | B46: TMT | C46: S1 | D46: injection_verification | E46: Potential SQL Injection Vulnerability for DS1 Backend User Database | F46: Diagram 1 | G46: Credential Verification Request | H46: TMT/S1
A47: TMT-S1-F008 | B47: TMT | C47: S1 | D47: dos_service | E47: Potential Excessive Resource Consumption for P2 Authentication Server or DS1 Backend User Database | F47: Diagram 1 | G47: Credential Verification Request | H47: TMT/S1
A48: TMT-S1-F009 | B48: TMT | C48: S1 | E48: P2 Authentication Server Process Memory Tampered | F48: Diagram 1 | G48: Session Token Generation | H48: TMT/S1
A49: TMT-S1-F010 | B49: TMT | C49: S1 | E49: Elevation Using Impersonation | F49: Diagram 1 | G49: Session Token Generation | H49: TMT/S1
A50: TMT-S1-F011 | B50: TMT | C50: S1 | E50: P2 Authentication Server Process Memory Tampered | F50: Diagram 1 | G50: Authentication Result | H50: TMT/S1
A51: TMT-S1-F012 | B51: TMT | C51: S1 | E51: Cross Site Scripting | F51: Diagram 1 | G51: Authentication Result | H51: TMT/S1
A52: TMT-S1-F013 | B52: TMT | C52: S1 | E52: Elevation Using Impersonation | F52: Diagram 1 | G52: Authentication Result | H52: TMT/S1
A53: TMT-S1-F014 | B53: TMT | C53: S1 | E53: Spoofing of Source Data Store DS1 Backend User Database | F53: Diagram 1 | G53: Credential Verification Result | H53: TMT/S1
A54: TMT-S1-F015 | B54: TMT | C54: S1 | D54: mass_disclosure | E54: Weak Access Control for a Resource | F54: Diagram 1 | G54: Credential Verification Result | H54: TMT/S1
A55: TMT-S1-F016 | B55: TMT | C55: S1 | E55: P3 Session Management Module Process Memory Tampered | F55: Diagram 1 | G55: Session Token | H55: TMT/S1
A56: TMT-S1-F017 | B56: TMT | C56: S1 | D56: transit_token | E56: Cross Site Scripting | F56: Diagram 1 | G56: Session Token | H56: TMT/S1
A57: TMT-S1-F018 | B57: TMT | C57: S1 | E57: Elevation Using Impersonation | F57: Diagram 1 | G57: Session Token | H57: TMT/S1
A58: TMT-S1-F019 | B58: TMT | C58: S1 | E58: P1 Web Frontend Interface Process Memory Tampered | F58: Diagram 1 | G58: Authenticated Session Response | H58: TMT/S1
A59: TMT-S1-F020 | B59: TMT | C59: S1 | E59: Elevation Using Impersonation | F59: Diagram 1 | G59: Authenticated Session Response | H59: TMT/S1
A60: TMT-S1-F021 | B60: TMT | C60: S1 | E60: Elevation Using Impersonation | F60: Diagram 1 | G60: Chatbot Question | H60: TMT/S1
A61: TMT-S1-F022 | B61: TMT | C61: S1 | E61: EE1 End User (Browser) Process Memory Tampered | F61: Diagram 1 | G61: Chatbot Question | H61: TMT/S1
A62: TMT-S1-F023 | B62: TMT | C62: S1 | E62: Potential Process Crash or Stop for EE1 End User (Browser) | F62: Diagram 1 | G62: Chatbot Answer | H62: TMT/S1
A63: TMT-S1-F024 | B63: TMT | C63: S1 | E63: Data Flow Sniffing | F63: Diagram 1 | G63: Chatbot Answer | H63: TMT/S1
A64: TMT-S1-F025 | B64: TMT | C64: S1 | D64: repudiation | E64: Potential Data Repudiation by EE1 End User (Browser) | F64: Diagram 1 | G64: Chatbot Answer | H64: TMT/S1
A65: TMT-S1-F026 | B65: TMT | C65: S1 | E65: P4 AI Authentication Assistant Process Memory Tampered | F65: Diagram 1 | G65: Chatbot Answer | H65: TMT/S1
A66: TMT-S1-F027 | B66: TMT | C66: S1 | E66: Potential Lack of Input Validation for EE1 End User (Browser) | F66: Diagram 1 | G66: Chatbot Answer | H66: TMT/S1
A67: TMT-S1-F028 | B67: TMT | C67: S1 | E67: Spoofing the EE1 End User (Browser) Process | F67: Diagram 1 | G67: Chatbot Answer | H67: TMT/S1
A68: TMT-S1-F029 | B68: TMT | C68: S1 | E68: Spoofing the P4 AI Authentication Assistant Process | F68: Diagram 1 | G68: Chatbot Answer | H68: TMT/S1
A69: TMT-S1-F030 | B69: TMT | C69: S1 | E69: Data Flow Chatbot Answer Is Potentially Interrupted | F69: Diagram 1 | G69: Chatbot Answer | H69: TMT/S1
A70: TMT-S1-F031 | B70: TMT | C70: S1 | E70: Elevation Using Impersonation | F70: Diagram 1 | G70: Chatbot Answer | H70: TMT/S1
A71: TMT-S1-F032 | B71: TMT | C71: S1 | E71: EE1 End User (Browser) May be Subject to Elevation of Privilege Using Remote Code Execution | F71: Diagram 1 | G71: Chatbot Answer | H71: TMT/S1
A72: TMT-S1-F033 | B72: TMT | C72: S1 | E72: Elevation by Changing the Execution Flow in EE1 End User (Browser) | F72: Diagram 1 | G72: Chatbot Answer | H72: TMT/S1
A73: TMT-S1-F034 | B73: TMT | C73: S1 | E73: P4 AI Authentication Assistant Process Memory Tampered | F73: Diagram 1 | G73: Prompt Request | H73: TMT/S1
A74: TMT-S1-F035 | B74: TMT | C74: S1 | E74: Elevation Using Impersonation | F74: Diagram 1 | G74: Prompt Request | H74: TMT/S1
A75: TMT-S1-F036 | B75: TMT | C75: S1 | E75: P5 LLM Integration Service Process Memory Tampered | F75: Diagram 1 | G75: Processed AI Response | H75: TMT/S1
A76: TMT-S1-F037 | B76: TMT | C76: S1 | E76: Elevation Using Impersonation | F76: Diagram 1 | G76: Processed AI Response | H76: TMT/S1
A77: TMT-S1-F038 | B77: TMT | C77: S1 | D77: model_substitution | E77: Spoofing the EE2 External LLM Provider External Entity | F77: Diagram 1 | G77: Generated LLM Response | H77: TMT/S1
A78: TMT-S1-F039 | B78: TMT | C78: S1 | E78: Elevation Using Impersonation | F78: Diagram 1 | G78: Generated LLM Response | H78: TMT/S1
A79: TMT-S1-F040 | B79: TMT | C79: S1 | E79: Spoofing the EE1 End User (Browser) Process | F79: Diagram 1 | G79: Chatbot Question | H79: TMT/S1
A80: TMT-S1-F041 | B80: TMT | C80: S1 | E80: Spoofing the P4 AI Authentication Assistant Process | F80: Diagram 1 | G80: Chatbot Question | H80: TMT/S1
A81: TMT-S1-F042 | B81: TMT | C81: S1 | D81: prompt_injection_direct | E81: Potential Lack of Input Validation for P4 AI Authentication Assistant | F81: Diagram 1 | G81: Chatbot Question | H81: TMT/S1
A82: TMT-S1-F043 | B82: TMT | C82: S1 | D82: repudiation | E82: Potential Data Repudiation by P4 AI Authentication Assistant | F82: Diagram 1 | G82: Chatbot Question | H82: TMT/S1
A83: TMT-S1-F044 | B83: TMT | C83: S1 | E83: Data Flow Sniffing | F83: Diagram 1 | G83: Chatbot Question | H83: TMT/S1
A84: TMT-S1-F045 | B84: TMT | C84: S1 | E84: Potential Process Crash or Stop for P4 AI Authentication Assistant | F84: Diagram 1 | G84: Chatbot Question | H84: TMT/S1
A85: TMT-S1-F046 | B85: TMT | C85: S1 | E85: Data Flow Chatbot Question Is Potentially Interrupted | F85: Diagram 1 | G85: Chatbot Question | H85: TMT/S1
A86: TMT-S1-F047 | B86: TMT | C86: S1 | E86: P4 AI Authentication Assistant May be Subject to Elevation of Privilege Using Remote Code Execution | F86: Diagram 1 | G86: Chatbot Question | H86: TMT/S1
A87: TMT-S1-F048 | B87: TMT | C87: S1 | E87: Elevation by Changing the Execution Flow in P4 AI Authentication Assistant | F87: Diagram 1 | G87: Chatbot Question | H87: TMT/S1
A88: TMT-S1-F049 | B88: TMT | C88: S1 | E88: Cross Site Request Forgery | F88: Diagram 1 | G88: Chatbot Question | H88: TMT/S1
A89: TMT-S1-F050 | B89: TMT | C89: S1 | E89: Spoofing the P5 LLM Integration Service Process | F89: Diagram 1 | G89: Generated LLM Response | H89: TMT/S1
A90: TMT-S1-F051 | B90: TMT | C90: S1 | D90: unsafe_output | E90: Potential Lack of Input Validation for P5 LLM Integration Service | F90: Diagram 1 | G90: Generated LLM Response | H90: TMT/S1
A91: TMT-S1-F052 | B91: TMT | C91: S1 | D91: repudiation | E91: Potential Data Repudiation by P5 LLM Integration Service | F91: Diagram 1 | G91: Generated LLM Response | H91: TMT/S1
A92: TMT-S1-F053 | B92: TMT | C92: S1 | E92: Data Flow Sniffing | F92: Diagram 1 | G92: Generated LLM Response | H92: TMT/S1
A93: TMT-S1-F054 | B93: TMT | C93: S1 | E93: Potential Process Crash or Stop for P5 LLM Integration Service | F93: Diagram 1 | G93: Generated LLM Response | H93: TMT/S1
A94: TMT-S1-F055 | B94: TMT | C94: S1 | D94: llm_unavailable | E94: Data Flow Generated LLM Response Is Potentially Interrupted | F94: Diagram 1 | G94: Generated LLM Response | H94: TMT/S1
A95: TMT-S1-F056 | B95: TMT | C95: S1 | E95: P5 LLM Integration Service May be Subject to Elevation of Privilege Using Remote Code Execution | F95: Diagram 1 | G95: Generated LLM Response | H95: TMT/S1
A96: TMT-S1-F057 | B96: TMT | C96: S1 | E96: Elevation by Changing the Execution Flow in P5 LLM Integration Service | F96: Diagram 1 | G96: Generated LLM Response | H96: TMT/S1
A97: TMT-S1-F058 | B97: TMT | C97: S1 | E97: Cross Site Request Forgery | F97: Diagram 1 | G97: Generated LLM Response | H97: TMT/S1
A98: TMT-S1-F059 | B98: TMT | C98: S1 | D98: llm_unavailable | E98: Data Flow Prompt + Approved Context Is Potentially Interrupted | F98: Diagram 1 | G98: Prompt + Approved Context | H98: TMT/S1
A99: TMT-S1-F060 | B99: TMT | C99: S1 | E99: External Entity EE2 External LLM Provider Potentially Denies Receiving Data | F99: Diagram 1 | G99: Prompt + Approved Context | H99: TMT/S1
A100: TMT-S1-F061 | B100: TMT | C100: S1 | D100: model_substitution | E100: Spoofing of the EE2 External LLM Provider External Destination Entity | F100: Diagram 1 | G100: Prompt + Approved Context | H100: TMT/S1
A101: TMT-S1-F062 | B101: TMT | C101: S1 | E101: Potential Process Crash or Stop for EE1 End User (Browser) | F101: Diagram 1 | G101: Authenticated Session Response | H101: TMT/S1
A102: TMT-S1-F063 | B102: TMT | C102: S1 | D102: transit_token | E102: Data Flow Sniffing | F102: Diagram 1 | G102: Authenticated Session Response | H102: TMT/S1
A103: TMT-S1-F064 | B103: TMT | C103: S1 | D103: repudiation | E103: Potential Data Repudiation by EE1 End User (Browser) | F103: Diagram 1 | G103: Authenticated Session Response | H103: TMT/S1
A104: TMT-S1-F065 | B104: TMT | C104: S1 | E104: Potential Lack of Input Validation for EE1 End User (Browser) | F104: Diagram 1 | G104: Authenticated Session Response | H104: TMT/S1
A105: TMT-S1-F066 | B105: TMT | C105: S1 | E105: Spoofing the EE1 End User (Browser) Process | F105: Diagram 1 | G105: Authenticated Session Response | H105: TMT/S1
A106: TMT-S1-F067 | B106: TMT | C106: S1 | E106: Spoofing the P1 Web Frontend Interface Process | F106: Diagram 1 | G106: Authenticated Session Response | H106: TMT/S1
A107: TMT-S1-F068 | B107: TMT | C107: S1 | E107: Cross Site Request Forgery | F107: Diagram 1 | G107: Registration/Login Credentials | H107: TMT/S1
A108: TMT-S1-F069 | B108: TMT | C108: S1 | E108: Elevation by Changing the Execution Flow in P1 Web Frontend Interface | F108: Diagram 1 | G108: Registration/Login Credentials | H108: TMT/S1
A109: TMT-S1-F070 | B109: TMT | C109: S1 | E109: P1 Web Frontend Interface May be Subject to Elevation of Privilege Using Remote Code Execution | F109: Diagram 1 | G109: Registration/Login Credentials | H109: TMT/S1
A110: TMT-S1-F071 | B110: TMT | C110: S1 | D110: dos_service | E110: Data Flow Registration/Login Credentials Is Potentially Interrupted | F110: Diagram 1 | G110: Registration/Login Credentials | H110: TMT/S1
A111: TMT-S1-F072 | B111: TMT | C111: S1 | E111: Potential Process Crash or Stop for P1 Web Frontend Interface | F111: Diagram 1 | G111: Registration/Login Credentials | H111: TMT/S1
A112: TMT-S1-F073 | B112: TMT | C112: S1 | D112: repudiation | E112: Potential Data Repudiation by P1 Web Frontend Interface | F112: Diagram 1 | G112: Registration/Login Credentials | H112: TMT/S1
A113: TMT-S1-F074 | B113: TMT | C113: S1 | E113: Spoofing the EE1 End User (Browser) Process | F113: Diagram 1 | G113: Registration/Login Credentials | H113: TMT/S1
A114: TMT-S1-F075 | B114: TMT | C114: S1 | E114: Data Flow Authenticated Session Response Is Potentially Interrupted | F114: Diagram 1 | G114: Authenticated Session Response | H114: TMT/S1
A115: TMT-S1-F076 | B115: TMT | C115: S1 | E115: EE1 End User (Browser) May be Subject to Elevation of Privilege Using Remote Code Execution | F115: Diagram 1 | G115: Authenticated Session Response | H115: TMT/S1
A116: TMT-S1-F077 | B116: TMT | C116: S1 | E116: Elevation by Changing the Execution Flow in EE1 End User (Browser) | F116: Diagram 1 | G116: Authenticated Session Response | H116: TMT/S1
A117: TMT-S1-F078 | B117: TMT | C117: S1 | E117: Data Flow Sniffing | F117: Diagram 1 | G117: Prompt Request | H117: TMT/S1
A118: TMT-S1-F079 | B118: TMT | C118: S1 | D118: repudiation | E118: Potential Data Repudiation by P5 LLM Integration Service | F118: Diagram 1 | G118: Prompt Request | H118: TMT/S1
A119: TMT-S1-F080 | B119: TMT | C119: S1 | E119: Potential Lack of Input Validation for P5 LLM Integration Service | F119: Diagram 1 | G119: Prompt Request | H119: TMT/S1
A120: TMT-S1-F081 | B120: TMT | C120: S1 | E120: Spoofing the P5 LLM Integration Service Process | F120: Diagram 1 | G120: Prompt Request | H120: TMT/S1
A121: TMT-S1-F082 | B121: TMT | C121: S1 | E121: Spoofing the P4 AI Authentication Assistant Process | F121: Diagram 1 | G121: Prompt Request | H121: TMT/S1
A122: TMT-S1-F083 | B122: TMT | C122: S1 | E122: Potential Process Crash or Stop for P5 LLM Integration Service | F122: Diagram 1 | G122: Prompt Request | H122: TMT/S1
A123: TMT-S1-F084 | B123: TMT | C123: S1 | D123: llm_unavailable | E123: Data Flow Prompt Request Is Potentially Interrupted | F123: Diagram 1 | G123: Prompt Request | H123: TMT/S1
A124: TMT-S1-F085 | B124: TMT | C124: S1 | E124: P5 LLM Integration Service May be Subject to Elevation of Privilege Using Remote Code Execution | F124: Diagram 1 | G124: Prompt Request | H124: TMT/S1
A125: TMT-S1-F086 | B125: TMT | C125: S1 | E125: Elevation by Changing the Execution Flow in P5 LLM Integration Service | F125: Diagram 1 | G125: Prompt Request | H125: TMT/S1
...

Sheet 04_MATCHING
A1: Semantic Matching Decisions (1,025 findings)
A2: OWASP-S1-F001 | B2: OWASP | C2: S1 | D2: =IFERROR(VLOOKUP($G2,'02_REFERENCE'!$A$2:$S$99,4,FALSE),"N/A") -> N/A | E2: =IFERROR(VLOOKUP($G2,'02_REFERENCE'!$A$2:$S$99,15,FALSE),"N/A") -> N/A | F2: =IFERROR(VLOOKUP($G2,'02_REFERENCE'!$A$2:$S$99,17,FALSE),"N/A") -> N/A | H2: False Positive | I2: FP | J2: M | K2: N | L2: No | N2: OWASP Automated Threat #9 (CAPTCHA defeat): the drawn architecture contains no CAPTCHA control; threat depends on absent functionality. | O2: captcha | P2: CAPTCHA defeat | Q2: EE1 End User | S2: Confirmed
A3: OWASP-S1-F002 | B3: OWASP | C3: S1 | D3: =IFERROR(VLOOKUP($G3,'02_REFERENCE'!$A$2:$S$99,4,FALSE),"N/A") -> Spoofing | E3: =IFERROR(VLOOKUP($G3,'02_REFERENCE'!$A$2:$S$99,15,FALSE),"N/A") -> High | F3: =IFERROR(VLOOKUP($G3,'02_REFERENCE'!$A$2:$S$99,17,FALSE),"N/A") -> No | G3: S1-RT-002 | H3: Primary TP | I3: TP | J3: H | K3: Y | L3: No | N3: Mechanism: replayed stolen credentials against login (OWASP Automated Threat #8) -> reference S1-RT-002. | O3: credential_stuffing | P3: Credential stuffing | Q3: EE1 End User | S3: Confirmed
A4: OWASP-S1-F003 | B4: OWASP | C4: S1 | D4: =IFERROR(VLOOKUP($G4,'02_REFERENCE'!$A$2:$S$99,4,FALSE),"N/A") -> N/A | E4: =IFERROR(VLOOKUP($G4,'02_REFERENCE'!$A$2:$S$99,15,FALSE),"N/A") -> N/A | F4: =IFERROR(VLOOKUP($G4,'02_REFERENCE'!$A$2:$S$99,17,FALSE),"N/A") -> N/A | H4: False Positive | I4: FP | J4: M | K4: N | L4: No | N4: Generic least-privilege hardening template (horizontal/lateral EoP after compromise); no reference threat specifies this mechanism for this element. | O4: excessive_db_scope | P4: Least privilege | Q4: P1 Web Frontend Interface | S4: Confirmed
A5: OWASP-S1-F004 | B5: OWASP | C5: S1 | D5: =IFERROR(VLOOKUP($G5,'02_REFERENCE'!$A$2:$S$99,4,FALSE),"N/A") -> N/A | E5: =IFERROR(VLOOKUP($G5,'02_REFERENCE'!$A$2:$S$99,15,FALSE),"N/A") -> N/A | F5: =IFERROR(VLOOKUP($G5,'02_REFERENCE'!$A$2:$S$99,17,FALSE),"N/A") -> N/A | H5: False Positive | I5: FP | J5: M | K5: N | L5: No | N5: Expedition (OWASP Automated Threat #6): generic automation/abuse-agility template; no single reference mechanism matches (brute force / stuffing are distinct specialist mechanisms). | O5: expedition | P5: Expedition | Q5: P1 Web Frontend Interface | S5: Confirmed
A6: OWASP-S1-F005 | B6: OWASP | C6: S1 | D6: =IFERROR(VLOOKUP($G6,'02_REFERENCE'!$A$2:$S$99,4,FALSE),"N/A") -> N/A | E6: =IFERROR(VLOOKUP($G6,'02_REFERENCE'!$A$2:$S$99,15,FALSE),"N/A") -> N/A | F6: =IFERROR(VLOOKUP($G6,'02_REFERENCE'!$A$2:$S$99,17,FALSE),"N/A") -> N/A | H6: False Positive | I6: FP | J6: M | K6: N | L6: No | N6: Vulnerability scanning (OWASP Automated Threat #14): reconnaissance; not a security-failure mechanism present in the baseline. | O6: recon | P6: Vulnerability scanning | Q6: P1 Web Frontend Interface | S6: Confirmed
A7: OWASP-S1-F006 | B7: OWASP | C7: S1 | D7: =IFERROR(VLOOKUP($G7,'02_REFERENCE'!$A$2:$S$99,4,FALSE),"N/A") -> Denial of Service | E7: =IFERROR(VLOOKUP($G7,'02_REFERENCE'!$A$2:$S$99,15,FALSE),"N/A") -> Medium | F7: =IFERROR(VLOOKUP($G7,'02_REFERENCE'!$A$2:$S$99,17,FALSE),"N/A") -> No | G7: S1-RT-028 | H7: Primary TP | I7: TP | J7: M | K7: Y | L7: No | N7: Resource-exhaustion template on the primary service path -> reference S1-RT-028. | O7: dos_service | P7: Denial of Service | Q7: P1 Web Frontend Interface | S7: Confirmed
A8: OWASP-S1-F007 | B8: OWASP | C8: S1 | D8: =IFERROR(VLOOKUP($G8,'02_REFERENCE'!$A$2:$S$99,4,FALSE),"N/A") -> N/A | E8: =IFERROR(VLOOKUP($G8,'02_REFERENCE'!$A$2:$S$99,15,FALSE),"N/A") -> N/A | F8: =IFERROR(VLOOKUP($G8,'02_REFERENCE'!$A$2:$S$99,17,FALSE),"N/A") -> N/A | H8: False Positive | I8: FP | J8: M | K8: N | L8: No | N8: Footprinting/Fingerprinting (OWASP Automated Threat #18/#4): reconnaissance; no reference mechanism. | O8: recon | P8: Footprinting | Q8: P1 Web Frontend Interface | S8: Confirmed
A9: OWASP-S1-F008 | B9: OWASP | C9: S1 | D9: =IFERROR(VLOOKUP($G9,'02_REFERENCE'!$A$2:$S$99,4,FALSE),"N/A") -> N/A | E9: =IFERROR(VLOOKUP($G9,'02_REFERENCE'!$A$2:$S$99,15,FALSE),"N/A") -> N/A | F9: =IFERROR(VLOOKUP($G9,'02_REFERENCE'!$A$2:$S$99,17,FALSE),"N/A") -> N/A | H9: False Positive | I9: FP | J9: M | K9: N | L9: No | N9: Generic least-privilege hardening template (horizontal/lateral EoP after compromise); no reference threat specifies this mechanism for this element. | O9: excessive_db_scope | P9: Least privilege | Q9: P2 Authentication Service | S9: Confirmed
A10: OWASP-S1-F009 | B10: OWASP | C10: S1 | D10: =IFERROR(VLOOKUP($G10,'02_REFERENCE'!$A$2:$S$99,4,FALSE),"N/A") -> N/A | E10: =IFERROR(VLOOKUP($G10,'02_REFERENCE'!$A$2:$S$99,15,FALSE),"N/A") -> N/A | F10: =IFERROR(VLOOKUP($G10,'02_REFERENCE'!$A$2:$S$99,17,FALSE),"N/A") -> N/A | H10: False Positive | I10: FP | J10: M | K10: N | L10: No | N10: Expedition (OWASP Automated Threat #6): generic automation/abuse-agility template; no single reference mechanism matches (brute force / stuffing are distinct specialist mechanisms). | O10: expedition | P10: Expedition | Q10: P2 Authentication Service | S10: Confirmed
A11: OWASP-S1-F010 | B11: OWASP | C11: S1 | D11: =IFERROR(VLOOKUP($G11,'02_REFERENCE'!$A$2:$S$99,4,FALSE),"N/A") -> N/A | E11: =IFERROR(VLOOKUP($G11,'02_REFERENCE'!$A$2:$S$99,15,FALSE),"N/A") -> N/A | F11: =IFERROR(VLOOKUP($G11,'02_REFERENCE'!$A$2:$S$99,17,FALSE),"N/A") -> N/A | H11: False Positive | I11: FP | J11: M | K11: N | L11: No | N11: Vulnerability scanning (OWASP Automated Threat #14): reconnaissance; not a security-failure mechanism present in the baseline. | O11: recon | P11: Vulnerability scanning | Q11: P2 Authentication Service | S11: Confirmed
A12: OWASP-S1-F011 | B12: OWASP | C12: S1 | D12: =IFERROR(VLOOKUP($G12,'02_REFERENCE'!$A$2:$S$99,4,FALSE),"N/A") -> Denial of Service | E12: =IFERROR(VLOOKUP($G12,'02_REFERENCE'!$A$2:$S$99,15,FALSE),"N/A") -> Medium | F12: =IFERROR(VLOOKUP($G12,'02_REFERENCE'!$A$2:$S$99,17,FALSE),"N/A") -> No | G12: S1-RT-028 | H12: Duplicate | I12: TP | J12: M | K12: N | L12: Yes | M12: OWASP-S1-F006 | N12: Resource-exhaustion template on the primary service path -> reference S1-RT-028. [Equivalence: restates OWASP-S1-F006 — one-to-one rule applied.] | O12: dos_service | P12: Denial of Service | Q12: P2 Authentication Service | S12: Confirmed
A13: OWASP-S1-F012 | B13: OWASP | C13: S1 | D13: =IFERROR(VLOOKUP($G13,'02_REFERENCE'!$A$2:$S$99,4,FALSE),"N/A") -> N/A | E13: =IFERROR(VLOOKUP($G13,'02_REFERENCE'!$A$2:$S$99,15,FALSE),"N/A") -> N/A | F13: =IFERROR(VLOOKUP($G13,'02_REFERENCE'!$A$2:$S$99,17,FALSE),"N/A") -> N/A | H13: False Positive | I13: FP | J13: M | K13: N | L13: No | N13: Footprinting/Fingerprinting (OWASP Automated Threat #18/#4): reconnaissance; no reference mechanism. | O13: recon | P13: Footprinting | Q13: P2 Authentication Service | S13: Confirmed
A14: OWASP-S1-F013 | B14: OWASP | C14: S1 | D14: =IFERROR(VLOOKUP($G14,'02_REFERENCE'!$A$2:$S$99,4,FALSE),"N/A") -> N/A | E14: =IFERROR(VLOOKUP($G14,'02_REFERENCE'!$A$2:$S$99,15,FALSE),"N/A") -> N/A | F14: =IFERROR(VLOOKUP($G14,'02_REFERENCE'!$A$2:$S$99,17,FALSE),"N/A") -> N/A | H14: False Positive | I14: FP | J14: M | K14: N | L14: No | N14: Generic least-privilege hardening template (horizontal/lateral EoP after compromise); no reference threat specifies this mechanism for this element. | O14: excessive_db_scope | P14: Least privilege | Q14: P3 Session Management Module | S14: Confirmed
A15: OWASP-S1-F014 | B15: OWASP | C15: S1 | D15: =IFERROR(VLOOKUP($G15,'02_REFERENCE'!$A$2:$S$99,4,FALSE),"N/A") -> N/A | E15: =IFERROR(VLOOKUP($G15,'02_REFERENCE'!$A$2:$S$99,15,FALSE),"N/A") -> N/A | F15: =IFERROR(VLOOKUP($G15,'02_REFERENCE'!$A$2:$S$99,17,FALSE),"N/A") -> N/A | H15: False Positive | I15: FP | J15: M | K15: N | L15: No | N15: Expedition (OWASP Automated Threat #6): generic automation/abuse-agility template; no single reference mechanism matches (brute force / stuffing are distinct specialist mechanisms). | O15: expedition | P15: Expedition | Q15: P3 Session Management Module | S15: Confirmed
A16: OWASP-S1-F015 | B16: OWASP | C16: S1 | D16: =IFERROR(VLOOKUP($G16,'02_REFERENCE'!$A$2:$S$99,4,FALSE),"N/A") -> N/A | E16: =IFERROR(VLOOKUP($G16,'02_REFERENCE'!$A$2:$S$99,15,FALSE),"N/A") -> N/A | F16: =IFERROR(VLOOKUP($G16,'02_REFERENCE'!$A$2:$S$99,17,FALSE),"N/A") -> N/A | H16: False Positive | I16: FP | J16: M | K16: N | L16: No | N16: Vulnerability scanning (OWASP Automated Threat #14): reconnaissance; not a security-failure mechanism present in the baseline. | O16: recon | P16: Vulnerability scanning | Q16: P3 Session Management Module | S16: Confirmed
A17: OWASP-S1-F016 | B17: OWASP | C17: S1 | D17: =IFERROR(VLOOKUP($G17,'02_REFERENCE'!$A$2:$S$99,4,FALSE),"N/A") -> Denial of Service | E17: =IFERROR(VLOOKUP($G17,'02_REFERENCE'!$A$2:$S$99,15,FALSE),"N/A") -> Medium | F17: =IFERROR(VLOOKUP($G17,'02_REFERENCE'!$A$2:$S$99,17,FALSE),"N/A") -> No | G17: S1-RT-028 | H17: Duplicate | I17: TP | J17: M | K17: N | L17: Yes | M17: OWASP-S1-F006 | N17: Resource-exhaustion template on the primary service path -> reference S1-RT-028. [Equivalence: restates OWASP-S1-F006 — one-to-one rule applied.] | O17: dos_service | P17: Denial of Service | Q17: P3 Session Management Module | S17: Confirmed
A18: OWASP-S1-F017 | B18: OWASP | C18: S1 | D18: =IFERROR(VLOOKUP($G18,'02_REFERENCE'!$A$2:$S$99,4,FALSE),"N/A") -> N/A | E18: =IFERROR(VLOOKUP($G18,'02_REFERENCE'!$A$2:$S$99,15,FALSE),"N/A") -> N/A | F18: =IFERROR(VLOOKUP($G18,'02_REFERENCE'!$A$2:$S$99,17,FALSE),"N/A") -> N/A | H18: False Positive | I18: FP | J18: M | K18: N | L18: No | N18: Footprinting/Fingerprinting (OWASP Automated Threat #18/#4): reconnaissance; no reference mechanism. | O18: recon | P18: Footprinting | Q18: P3 Session Management Module | S18: Confirmed
A19: OWASP-S1-F018 | B19: OWASP | C19: S1 | D19: =IFERROR(VLOOKUP($G19,'02_REFERENCE'!$A$2:$S$99,4,FALSE),"N/A") -> Spoofing | E19: =IFERROR(VLOOKUP($G19,'02_REFERENCE'!$A$2:$S$99,15,FALSE),"N/A") -> Critical | F19: =IFERROR(VLOOKUP($G19,'02_REFERENCE'!$A$2:$S$99,17,FALSE),"N/A") -> No | G19: S1-RT-014 | H19: Primary TP | I19: TP | J19: M | K19: Y | L19: No | N19: Weak transport on session-management flows exposes issued session tokens at the delivery crossing -> reference S1-RT-014. | O19: transit_token | P19: Vulnerable transport protocol | Q19: P3 Session Management Module | S19: Confirmed
A20: OWASP-S1-F019 | B20: OWASP | C20: S1 | D20: =IFERROR(VLOOKUP($G20,'02_REFERENCE'!$A$2:$S$99,4,FALSE),"N/A") -> N/A | E20: =IFERROR(VLOOKUP($G20,'02_REFERENCE'!$A$2:$S$99,15,FALSE),"N/A") -> N/A | F20: =IFERROR(VLOOKUP($G20,'02_REFERENCE'!$A$2:$S$99,17,FALSE),"N/A") -> N/A | H20: False Positive | I20: FP | J20: M | K20: N | L20: No | N20: Footprinting/Fingerprinting (OWASP Automated Threat #18/#4): reconnaissance; no reference mechanism. | O20: recon | P20: Fingerprinting | Q20: P3 Session Management Module | S20: Confirmed
A21: OWASP-S1-F020 | B21: OWASP | C21: S1 | D21: =IFERROR(VLOOKUP($G21,'02_REFERENCE'!$A$2:$S$99,4,FALSE),"N/A") -> Spoofing | E21: =IFERROR(VLOOKUP($G21,'02_REFERENCE'!$A$2:$S$99,15,FALSE),"N/A") -> Critical | F21: =IFERROR(VLOOKUP($G21,'02_REFERENCE'!$A$2:$S$99,17,FALSE),"N/A") -> No | G21: S1-RT-014 | H21: Duplicate | I21: TP | J21: M | K21: N | L21: Yes | M21: OWASP-S1-F018 | N21: Weak transport on session-management flows exposes issued session tokens at the delivery crossing -> reference S1-RT-014. [Equivalence: restates OWASP-S1-F018 — one-to-one rule applied.] | O21: transit_token | P21: Vulnerable transport protocol | Q21: P3 Session Management Module | S21: Confirmed
A22: OWASP-S1-F021 | B22: OWASP | C22: S1 | D22: =IFERROR(VLOOKUP($G22,'02_REFERENCE'!$A$2:$S$99,4,FALSE),"N/A") -> Spoofing | E22: =IFERROR(VLOOKUP($G22,'02_REFERENCE'!$A$2:$S$99,15,FALSE),"N/A") -> Critical | F22: =IFERROR(VLOOKUP($G22,'02_REFERENCE'!$A$2:$S$99,17,FALSE),"N/A") -> No | G22: S1-RT-014 | H22: Duplicate | I22: TP | J22: M | K22: N | L22: Yes | M22: OWASP-S1-F018 | N22: Weak transport on session-management flows exposes issued session tokens at the delivery crossing -> reference S1-RT-014. [Equivalence: restates OWASP-S1-F018 — one-to-one rule applied.] | O22: transit_token | P22: Vulnerable transport protocol | Q22: P3 Session Management Module | S22: Confirmed
A23: OWASP-S1-F022 | B23: OWASP | C23: S1 | D23: =IFERROR(VLOOKUP($G23,'02_REFERENCE'!$A$2:$S$99,4,FALSE),"N/A") -> Spoofing | E23: =IFERROR(VLOOKUP($G23,'02_REFERENCE'!$A$2:$S$99,15,FALSE),"N/A") -> Critical | F23: =IFERROR(VLOOKUP($G23,'02_REFERENCE'!$A$2:$S$99,17,FALSE),"N/A") -> No | G23: S1-RT-014 | H23: Duplicate | I23: TP | J23: M | K23: N | L23: Yes | M23: OWASP-S1-F018 | N23: Weak transport on session-management flows exposes issued session tokens at the delivery crossing -> reference S1-RT-014. [Equivalence: restates OWASP-S1-F018 — one-to-one rule applied.] | O23: transit_token | P23: Vulnerable transport protocol | Q23: P3 Session Management Module | S23: Confirmed
A24: OWASP-S1-F023 | B24: OWASP | C24: S1 | D24: =IFERROR(VLOOKUP($G24,'02_REFERENCE'!$A$2:$S$99,4,FALSE),"N/A") -> N/A | E24: =IFERROR(VLOOKUP($G24,'02_REFERENCE'!$A$2:$S$99,15,FALSE),"N/A") -> N/A | F24: =IFERROR(VLOOKUP($G24,'02_REFERENCE'!$A$2:$S$99,17,FALSE),"N/A") -> N/A | H24: False Positive | I24: FP | J24: M | K24: N | L24: No | N24: Footprinting/Fingerprinting (OWASP Automated Threat #18/#4): reconnaissance; no reference mechanism. | O24: recon | P24: Fingerprinting | Q24: P3 Session Management Module | S24: Confirmed
A25: OWASP-S1-F024 | B25: OWASP | C25: S1 | D25: =IFERROR(VLOOKUP($G25,'02_REFERENCE'!$A$2:$S$99,4,FALSE),"N/A") -> N/A | E25: =IFERROR(VLOOKUP($G25,'02_REFERENCE'!$A$2:$S$99,15,FALSE),"N/A") -> N/A | F25: =IFERROR(VLOOKUP($G25,'02_REFERENCE'!$A$2:$S$99,17,FALSE),"N/A") -> N/A | H25: False Positive | I25: FP | J25: M | K25: N | L25: No | N25: Expedition (OWASP Automated Threat #6): generic automation/abuse-agility template; no single reference mechanism matches (brute force / stuffing are distinct specialist mechanisms). | O25: expedition | P25: Expedition | Q25: P4 AI chatbot Component | S25: Confirmed
A26: OWASP-S1-F025 | B26: OWASP | C26: S1 | D26: =IFERROR(VLOOKUP($G26,'02_REFERENCE'!$A$2:$S$99,4,FALSE),"N/A") -> N/A | E26: =IFERROR(VLOOKUP($G26,'02_REFERENCE'!$A$2:$S$99,15,FALSE),"N/A") -> N/A | F26: =IFERROR(VLOOKUP($G26,'02_REFERENCE'!$A$2:$S$99,17,FALSE),"N/A") -> N/A | H26: False Positive | I26: FP | J26: M | K26: N | L26: No | N26: Vulnerability scanning (OWASP Automated Threat #14): reconnaissance; not a security-failure mechanism present in the baseline. | O26: recon | P26: Vulnerability scanning | Q26: P4 AI chatbot Component | S26: Confirmed
A27: OWASP-S1-F026 | B27: OWASP | C27: S1 | D27: =IFERROR(VLOOKUP($G27,'02_REFERENCE'!$A$2:$S$99,4,FALSE),"N/A") -> Denial of Service | E27: =IFERROR(VLOOKUP($G27,'02_REFERENCE'!$A$2:$S$99,15,FALSE),"N/A") -> Medium | F27: =IFERROR(VLOOKUP($G27,'02_REFERENCE'!$A$2:$S$99,17,FALSE),"N/A") -> Yes | G27: S1-RT-030 | H27: Primary TP | I27: TP | J27: M | K27: Y | L27: No | N27: Resource-exhaustion template on the LLM pipeline component -> reference S1-RT-030 (unbounded LLM pipeline consumption). | O27: llm_consumption | P27: Denial of Service | Q27: P4 AI chatbot Component | S27: Confirmed
A28: OWASP-S1-F027 | B28: OWASP | C28: S1 | D28: =IFERROR(VLOOKUP($G28,'02_REFERENCE'!$A$2:$S$99,4,FALSE),"N/A") -> N/A | E28: =IFERROR(VLOOKUP($G28,'02_REFERENCE'!$A$2:$S$99,15,FALSE),"N/A") -> N/A | F28: =IFERROR(VLOOKUP($G28,'02_REFERENCE'!$A$2:$S$99,17,FALSE),"N/A") -> N/A | H28: False Positive | I28: FP | J28: M | K28: N | L28: No | N28: Expedition (OWASP Automated Threat #6): generic automation/abuse-agility template; no single reference mechanism matches (brute force / stuffing are distinct specialist mechanisms). | O28: expedition | P28: Expedition | Q28: P5 LLM Integration Service | S28: Confirmed
A29: OWASP-S1-F028 | B29: OWASP | C29: S1 | D29: =IFERROR(VLOOKUP($G29,'02_REFERENCE'!$A$2:$S$99,4,FALSE),"N/A") -> N/A | E29: =IFERROR(VLOOKUP($G29,'02_REFERENCE'!$A$2:$S$99,15,FALSE),"N/A") -> N/A | F29: =IFERROR(VLOOKUP($G29,'02_REFERENCE'!$A$2:$S$99,17,FALSE),"N/A") -> N/A | H29: False Positive | I29: FP | J29: M | K29: N | L29: No | N29: Vulnerability scanning (OWASP Automated Threat #14): reconnaissance; not a security-failure mechanism present in the baseline. | O29: recon | P29: Vulnerability scanning | Q29: P5 LLM Integration Service | S29: Confirmed
A30: OWASP-S1-F029 | B30: OWASP | C30: S1 | D30: =IFERROR(VLOOKUP($G30,'02_REFERENCE'!$A$2:$S$99,4,FALSE),"N/A") -> Denial of Service | E30: =IFERROR(VLOOKUP($G30,'02_REFERENCE'!$A$2:$S$99,15,FALSE),"N/A") -> Medium | F30: =IFERROR(VLOOKUP($G30,'02_REFERENCE'!$A$2:$S$99,17,FALSE),"N/A") -> Yes | G30: S1-RT-030 | H30: Duplicate | I30: TP | J30: M | K30: N | L30: Yes | M30: OWASP-S1-F026 | N30: Resource-exhaustion template on the LLM pipeline component -> reference S1-RT-030 (unbounded LLM pipeline consumption). [Equivalence: restates OWASP-S1-F026 — one-to-one rule applied.] | O30: llm_consumption | P30: Denial of Service | Q30: P5 LLM Integration Service | S30: Confirmed
A31: OWASP-S1-F030 | B31: OWASP | C31: S1 | D31: =IFERROR(VLOOKUP($G31,'02_REFERENCE'!$A$2:$S$99,4,FALSE),"N/A") -> Information Disclosure | E31: =IFERROR(VLOOKUP($G31,'02_REFERENCE'!$A$2:$S$99,15,FALSE),"N/A") -> Critical | F31: =IFERROR(VLOOKUP($G31,'02_REFERENCE'!$A$2:$S$99,17,FALSE),"N/A") -> No | G31: S1-RT-018 | H31: Primary TP | I31: TP | J31: M | K31: Y | L31: No | N31: Scraping (OWASP Automated Threat #11) on the user-data-store element: automated bulk collection of stored user data corresponds to the mass-disclosure mechanism -> reference S1-RT-018. | O31: mass_disclosure | P31: Scraping | Q31: DS1 User Database | S31: Confirmed
A32: OWASP-S1-F031 | B32: OWASP | C32: S1 | D32: =IFERROR(VLOOKUP($G32,'02_REFERENCE'!$A$2:$S$99,4,FALSE),"N/A") -> N/A | E32: =IFERROR(VLOOKUP($G32,'02_REFERENCE'!$A$2:$S$99,15,FALSE),"N/A") -> N/A | F32: =IFERROR(VLOOKUP($G32,'02_REFERENCE'!$A$2:$S$99,17,FALSE),"N/A") -> N/A | H32: False Positive | I32: FP | J32: M | K32: N | L32: No | N32: Skewing (OWASP Automated Threat #16): metric-frequency gaming; no matching reference mechanism. | O32: skew_spam | P32: Skewing | Q32: DS1 User Database | S32: Confirmed
A33: OWASP-S1-F032 | B33: OWASP | C33: S1 | D33: =IFERROR(VLOOKUP($G33,'02_REFERENCE'!$A$2:$S$99,4,FALSE),"N/A") -> N/A | E33: =IFERROR(VLOOKUP($G33,'02_REFERENCE'!$A$2:$S$99,15,FALSE),"N/A") -> N/A | F33: =IFERROR(VLOOKUP($G33,'02_REFERENCE'!$A$2:$S$99,17,FALSE),"N/A") -> N/A | H33: False Positive | I33: FP | J33: M | K33: N | L33: No | N33: Storing malicious content (OWASP Automated Threat #17) on an element without a matching malicious-content reference. | O33: skew_spam | P33: Spamming | Q33: DS1 User Database | S33: Confirmed
A34: OWASP-S1-F033 | B34: OWASP | C34: S1 | D34: =IFERROR(VLOOKUP($G34,'02_REFERENCE'!$A$2:$S$99,4,FALSE),"N/A") -> N/A | E34: =IFERROR(VLOOKUP($G34,'02_REFERENCE'!$A$2:$S$99,15,FALSE),"N/A") -> N/A | F34: =IFERROR(VLOOKUP($G34,'02_REFERENCE'!$A$2:$S$99,17,FALSE),"N/A") -> N/A | H34: False Positive | I34: FP | J34: M | K34: N | L34: No | N34: Scraping (OWASP Automated Threat #11) on a non-user-store element: collection of accessible application output, not the store-layer bulk-read mechanism of the mass-disclosure reference. | O34: mass_disclosure | P34: Scraping | Q34: DS2 Session Storage | S34: Confirmed
A35: OWASP-S1-F034 | B35: OWASP | C35: S1 | D35: =IFERROR(VLOOKUP($G35,'02_REFERENCE'!$A$2:$S$99,4,FALSE),"N/A") -> N/A | E35: =IFERROR(VLOOKUP($G35,'02_REFERENCE'!$A$2:$S$99,15,FALSE),"N/A") -> N/A | F35: =IFERROR(VLOOKUP($G35,'02_REFERENCE'!$A$2:$S$99,17,FALSE),"N/A") -> N/A | H35: False Positive | I35: FP | J35: M | K35: N | L35: No | N35: Skewing (OWASP Automated Threat #16): metric-frequency gaming; no matching reference mechanism. | O35: skew_spam | P35: Skewing | Q35: DS2 Session Storage | S35: Confirmed
A36: OWASP-S1-F035 | B36: OWASP | C36: S1 | D36: =IFERROR(VLOOKUP($G36,'02_REFERENCE'!$A$2:$S$99,4,FALSE),"N/A") -> N/A | E36: =IFERROR(VLOOKUP($G36,'02_REFERENCE'!$A$2:$S$99,15,FALSE),"N/A") -> N/A | F36: =IFERROR(VLOOKUP($G36,'02_REFERENCE'!$A$2:$S$99,17,FALSE),"N/A") -> N/A | H36: False Positive | I36: FP | J36: M | K36: N | L36: No | N36: Storing malicious content (OWASP Automated Threat #17) on an element without a matching malicious-content reference. | O36: skew_spam | P36: Spamming | Q36: DS2 Session Storage | S36: Confirmed
A37: OWASP-S1-F036 | B37: OWASP | C37: S1 | D37: =IFERROR(VLOOKUP($G37,'02_REFERENCE'!$A$2:$S$99,4,FALSE),"N/A") -> N/A | E37: =IFERROR(VLOOKUP($G37,'02_REFERENCE'!$A$2:$S$99,15,FALSE),"N/A") -> N/A | F37: =IFERROR(VLOOKUP($G37,'02_REFERENCE'!$A$2:$S$99,17,FALSE),"N/A") -> N/A | H37: False Positive | I37: FP | J37: M | K37: N | L37: No | N37: Scraping (OWASP Automated Threat #11) on a non-user-store element: collection of accessible application output, not the store-layer bulk-read mechanism of the mass-disclosure reference. | O37: mass_disclosure | P37: Scraping | Q37: DS3 Knowledge Base | S37: Confirmed
A38: OWASP-S1-F037 | B38: OWASP | C38: S1 | D38: =IFERROR(VLOOKUP($G38,'02_REFERENCE'!$A$2:$S$99,4,FALSE),"N/A") -> N/A | E38: =IFERROR(VLOOKUP($G38,'02_REFERENCE'!$A$2:$S$99,15,FALSE),"N/A") -> N/A | F38: =IFERROR(VLOOKUP($G38,'02_REFERENCE'!$A$2:$S$99,17,FALSE),"N/A") -> N/A | H38: False Positive | I38: FP | J38: M | K38: N | L38: No | N38: Skewing (OWASP Automated Threat #16): metric-frequency gaming; no matching reference mechanism. | O38: skew_spam | P38: Skewing | Q38: DS3 Knowledge Base | S38: Confirmed
A39: OWASP-S1-F038 | B39: OWASP | C39: S1 | D39: =IFERROR(VLOOKUP($G39,'02_REFERENCE'!$A$2:$S$99,4,FALSE),"N/A") -> Tampering | E39: =IFERROR(VLOOKUP($G39,'02_REFERENCE'!$A$2:$S$99,15,FALSE),"N/A") -> High | F39: =IFERROR(VLOOKUP($G39,'02_REFERENCE'!$A$2:$S$99,17,FALSE),"N/A") -> Yes | G39: S1-RT-023 | H39: Primary TP | I39: TP | J39: M | K39: Y | L39: No | N39: Storing malicious content (OWASP Automated Threat #17) in the context repository -> attacker-influenced content later enters assistant context -> reference S1-RT-023 (indirect prompt injection through the context repository). | O39: stored_prompt_injection | P39: Spamming | Q39: DS3 Knowledge Base | S39: Confirmed
A40: TMT-S1-F001 | B40: TMT | C40: S1 | D40: =IFERROR(VLOOKUP($G40,'02_REFERENCE'!$A$2:$S$99,4,FALSE),"N/A") -> N/A | E40: =IFERROR(VLOOKUP($G40,'02_REFERENCE'!$A$2:$S$99,15,FALSE),"N/A") -> N/A | F40: =IFERROR(VLOOKUP($G40,'02_REFERENCE'!$A$2:$S$99,17,FALSE),"N/A") -> N/A | H40: False Positive | I40: FP | J40: M | K40: N | L40: No | N40: Process-identity spoofing / memory-integrity template; no reference mechanism (authentication bypass RT-004 is logic-based, not process-spoofing). | P40: EE1 End User (Browser) Process Memory Tampered | Q40: Diagram 1 | R40: Registration/Login Credentials | S40: Confirmed
A41: TMT-S1-F002 | B41: TMT | C41: S1 | D41: =IFERROR(VLOOKUP($G41,'02_REFERENCE'!$A$2:$S$99,4,FALSE),"N/A") -> N/A | E41: =IFERROR(VLOOKUP($G41,'02_REFERENCE'!$A$2:$S$99,15,FALSE),"N/A") -> N/A | F41: =IFERROR(VLOOKUP($G41,'02_REFERENCE'!$A$2:$S$99,17,FALSE),"N/A") -> N/A | H41: False Positive | I41: FP | J41: M | K41: N | L41: No | N41: XSS template on a flow without a matching reference mechanism (no generic XSS reference in the baseline). | P41: Cross Site Scripting | Q41: Diagram 1 | R41: Registration/Login Credentials | S41: Confirmed
A42: TMT-S1-F003 | B42: TMT | C42: S1 | D42: =IFERROR(VLOOKUP($G42,'02_REFERENCE'!$A$2:$S$99,4,FALSE),"N/A") -> N/A | E42: =IFERROR(VLOOKUP($G42,'02_REFERENCE'!$A$2:$S$99,15,FALSE),"N/A") -> N/A | F42: =IFERROR(VLOOKUP($G42,'02_REFERENCE'!$A$2:$S$99,17,FALSE),"N/A") -> N/A | H42: False Positive | I42: FP | J42: M | K42: N | L42: No | N42: Process-identity spoofing / memory-integrity template; no reference mechanism (authentication bypass RT-004 is logic-based, not process-spoofing). | P42: Elevation Using Impersonation | Q42: Diagram 1 | R42: Registration/Login Credentials | S42: Confirmed
A43: TMT-S1-F004 | B43: TMT | C43: S1 | D43: =IFERROR(VLOOKUP($G43,'02_REFERENCE'!$A$2:$S$99,4,FALSE),"N/A") -> N/A | E43: =IFERROR(VLOOKUP($G43,'02_REFERENCE'!$A$2:$S$99,15,FALSE),"N/A") -> N/A | F43: =IFERROR(VLOOKUP($G43,'02_REFERENCE'!$A$2:$S$99,17,FALSE),"N/A") -> N/A | H43: False Positive | I43: FP | J43: M | K43: N | L43: No | N43: Process-identity spoofing / memory-integrity template; no reference mechanism (authentication bypass RT-004 is logic-based, not process-spoofing). | P43: P1 Web Frontend Interface Process Memory Tampered | Q43: Diagram 1 | R43: Credential Submission | S43: Confirmed
A44: TMT-S1-F005 | B44: TMT | C44: S1 | D44: =IFERROR(VLOOKUP($G44,'02_REFERENCE'!$A$2:$S$99,4,FALSE),"N/A") -> N/A | E44: =IFERROR(VLOOKUP($G44,'02_REFERENCE'!$A$2:$S$99,15,FALSE),"N/A") -> N/A | F44: =IFERROR(VLOOKUP($G44,'02_REFERENCE'!$A$2:$S$99,17,FALSE),"N/A") -> N/A | H44: False Positive | I44: FP | J44: M | K44: N | L44: No | N44: Process-identity spoofing / memory-integrity template; no reference mechanism (authentication bypass RT-004 is logic-based, not process-spoofing). | P44: Elevation Using Impersonation | Q44: Diagram 1 | R44: Credential Submission | S44: Confirmed
A45: TMT-S1-F006 | B45: TMT | C45: S1 | D45: =IFERROR(VLOOKUP($G45,'02_REFERENCE'!$A$2:$S$99,4,FALSE),"N/A") -> N/A | E45: =IFERROR(VLOOKUP($G45,'02_REFERENCE'!$A$2:$S$99,15,FALSE),"N/A") -> N/A | F45: =IFERROR(VLOOKUP($G45,'02_REFERENCE'!$A$2:$S$99,17,FALSE),"N/A") -> N/A | H45: False Positive | I45: FP | J45: M | K45: N | L45: No | N45: Process-identity spoofing / memory-integrity template; no reference mechanism (authentication bypass RT-004 is logic-based, not process-spoofing). | P45: Spoofing of Destination Data Store DS1 Backend User Database | Q45: Diagram 1 | R45: Credential Verification Request | S45: Confirmed
A46: TMT-S1-F007 | B46: TMT | C46: S1 | D46: =IFERROR(VLOOKUP($G46,'02_REFERENCE'!$A$2:$S$99,4,FALSE),"N/A") -> Tampering | E46: =IFERROR(VLOOKUP($G46,'02_REFERENCE'!$A$2:$S$99,15,FALSE),"N/A") -> Critical | F46: =IFERROR(VLOOKUP($G46,'02_REFERENCE'!$A$2:$S$99,17,FALSE),"N/A") -> No | G46: S1-RT-008 | H46: Primary TP | I46: TP | J46: M | K46: Y | L46: No | N46: SQL-injection template on the verification/lookup exchange -> reference S1-RT-008. | O46: injection_verification | P46: Potential SQL Injection Vulnerability for DS1 Backend User Database | Q46: Diagram 1 | R46: Credential Verification Request | S46: Confirmed
A47: TMT-S1-F008 | B47: TMT | C47: S1 | D47: =IFERROR(VLOOKUP($G47,'02_REFERENCE'!$A$2:$S$99,4,FALSE),"N/A") -> Denial of Service | E47: =IFERROR(VLOOKUP($G47,'02_REFERENCE'!$A$2:$S$99,15,FALSE),"N/A") -> Medium | F47: =IFERROR(VLOOKUP($G47,'02_REFERENCE'!$A$2:$S$99,17,FALSE),"N/A") -> No | G47: S1-RT-028 | H47: Primary TP | I47: TP | J47: M | K47: Y | L47: No | N47: Excessive resource consumption of the primary service -> reference S1-RT-028. | O47: dos_service | P47: Potential Excessive Resource Consumption for P2 Authentication Server or DS1 Backend User Database | Q47: Diagram 1 | R47: Credential Verification Request | S47: Confirmed
A48: TMT-S1-F009 | B48: TMT | C48: S1 | D48: =IFERROR(VLOOKUP($G48,'02_REFERENCE'!$A$2:$S$99,4,FALSE),"N/A") -> N/A | E48: =IFERROR(VLOOKUP($G48,'02_REFERENCE'!$A$2:$S$99,15,FALSE),"N/A") -> N/A | F48: =IFERROR(VLOOKUP($G48,'02_REFERENCE'!$A$2:$S$99,17,FALSE),"N/A") -> N/A | H48: False Positive | I48: FP | J48: M | K48: N | L48: No | N48: Process-identity spoofing / memory-integrity template; no reference mechanism (authentication bypass RT-004 is logic-based, not process-spoofing). | P48: P2 Authentication Server Process Memory Tampered | Q48: Diagram 1 | R48: Session Token Generation | S48: Confirmed
A49: TMT-S1-F010 | B49: TMT | C49: S1 | D49: =IFERROR(VLOOKUP($G49,'02_REFERENCE'!$A$2:$S$99,4,FALSE),"N/A") -> N/A | E49: =IFERROR(VLOOKUP($G49,'02_REFERENCE'!$A$2:$S$99,15,FALSE),"N/A") -> N/A | F49: =IFERROR(VLOOKUP($G49,'02_REFERENCE'!$A$2:$S$99,17,FALSE),"N/A") -> N/A | H49: False Positive | I49: FP | J49: M | K49: N | L49: No | N49: Process-identity spoofing / memory-integrity template; no reference mechanism (authentication bypass RT-004 is logic-based, not process-spoofing). | P49: Elevation Using Impersonation | Q49: Diagram 1 | R49: Session Token Generation | S49: Confirmed
A50: TMT-S1-F011 | B50: TMT | C50: S1 | D50: =IFERROR(VLOOKUP($G50,'02_REFERENCE'!$A$2:$S$99,4,FALSE),"N/A") -> N/A | E50: =IFERROR(VLOOKUP($G50,'02_REFERENCE'!$A$2:$S$99,15,FALSE),"N/A") -> N/A | F50: =IFERROR(VLOOKUP($G50,'02_REFERENCE'!$A$2:$S$99,17,FALSE),"N/A") -> N/A | H50: False Positive | I50: FP | J50: M | K50: N | L50: No | N50: Process-identity spoofing / memory-integrity template; no reference mechanism (authentication bypass RT-004 is logic-based, not process-spoofing). | P50: P2 Authentication Server Process Memory Tampered | Q50: Diagram 1 | R50: Authentication Result | S50: Confirmed
A51: TMT-S1-F012 | B51: TMT | C51: S1 | D51: =IFERROR(VLOOKUP($G51,'02_REFERENCE'!$A$2:$S$99,4,FALSE),"N/A") -> N/A | E51: =IFERROR(VLOOKUP($G51,'02_REFERENCE'!$A$2:$S$99,15,FALSE),"N/A") -> N/A | F51: =IFERROR(VLOOKUP($G51,'02_REFERENCE'!$A$2:$S$99,17,FALSE),"N/A") -> N/A | H51: False Positive | I51: FP | J51: M | K51: N | L51: No | N51: XSS template on a flow without a matching reference mechanism (no generic XSS reference in the baseline). | P51: Cross Site Scripting | Q51: Diagram 1 | R51: Authentication Result | S51: Confirmed
A52: TMT-S1-F013 | B52: TMT | C52: S1 | D52: =IFERROR(VLOOKUP($G52,'02_REFERENCE'!$A$2:$S$99,4,FALSE),"N/A") -> N/A | E52: =IFERROR(VLOOKUP($G52,'02_REFERENCE'!$A$2:$S$99,15,FALSE),"N/A") -> N/A | F52: =IFERROR(VLOOKUP($G52,'02_REFERENCE'!$A$2:$S$99,17,FALSE),"N/A") -> N/A | H52: False Positive | I52: FP | J52: M | K52: N | L52: No | N52: Process-identity spoofing / memory-integrity template; no reference mechanism (authentication bypass RT-004 is logic-based, not process-spoofing). | P52: Elevation Using Impersonation | Q52: Diagram 1 | R52: Authentication Result | S52: Confirmed
A53: TMT-S1-F014 | B53: TMT | C53: S1 | D53: =IFERROR(VLOOKUP($G53,'02_REFERENCE'!$A$2:$S$99,4,FALSE),"N/A") -> N/A | E53: =IFERROR(VLOOKUP($G53,'02_REFERENCE'!$A$2:$S$99,15,FALSE),"N/A") -> N/A | F53: =IFERROR(VLOOKUP($G53,'02_REFERENCE'!$A$2:$S$99,17,FALSE),"N/A") -> N/A | H53: False Positive | I53: FP | J53: M | K53: N | L53: No | N53: Process-identity spoofing / memory-integrity template; no reference mechanism (authentication bypass RT-004 is logic-based, not process-spoofing). | P53: Spoofing of Source Data Store DS1 Backend User Database | Q53: Diagram 1 | R53: Credential Verification Result | S53: Confirmed
A54: TMT-S1-F015 | B54: TMT | C54: S1 | D54: =IFERROR(VLOOKUP($G54,'02_REFERENCE'!$A$2:$S$99,4,FALSE),"N/A") -> Information Disclosure | E54: =IFERROR(VLOOKUP($G54,'02_REFERENCE'!$A$2:$S$99,15,FALSE),"N/A") -> Critical | F54: =IFERROR(VLOOKUP($G54,'02_REFERENCE'!$A$2:$S$99,17,FALSE),"N/A") -> No | G54: S1-RT-018 | H54: Primary TP | I54: TP | J54: M | K54: Y | L54: No | N54: Weak access control on a data-store resource -> unauthorized read of store contents -> reference S1-RT-018. | O54: mass_disclosure | P54: Weak Access Control for a Resource | Q54: Diagram 1 | R54: Credential Verification Result | S54: Confirmed
A55: TMT-S1-F016 | B55: TMT | C55: S1 | D55: =IFERROR(VLOOKUP($G55,'02_REFERENCE'!$A$2:$S$99,4,FALSE),"N/A") -> N/A | E55: =IFERROR(VLOOKUP($G55,'02_REFERENCE'!$A$2:$S$99,15,FALSE),"N/A") -> N/A | F55: =IFERROR(VLOOKUP($G55,'02_REFERENCE'!$A$2:$S$99,17,FALSE),"N/A") -> N/A | H55: False Positive | I55: FP | J55: M | K55: N | L55: No | N55: Process-identity spoofing / memory-integrity template; no reference mechanism (authentication bypass RT-004 is logic-based, not process-spoofing). | P55: P3 Session Management Module Process Memory Tampered | Q55: Diagram 1 | R55: Session Token | S55: Confirmed
A56: TMT-S1-F017 | B56: TMT | C56: S1 | D56: =IFERROR(VLOOKUP($G56,'02_REFERENCE'!$A$2:$S$99,4,FALSE),"N/A") -> Spoofing | E56: =IFERROR(VLOOKUP($G56,'02_REFERENCE'!$A$2:$S$99,15,FALSE),"N/A") -> Critical | F56: =IFERROR(VLOOKUP($G56,'02_REFERENCE'!$A$2:$S$99,17,FALSE),"N/A") -> No | G56: S1-RT-014 | H56: Primary TP | I56: TP | J56: M | K56: Y | L56: No | N56: XSS on a session/token flow -> client-side token theft at the delivery crossing -> reference S1-RT-014. | O56: transit_token | P56: Cross Site Scripting | Q56: Diagram 1 | R56: Session Token | S56: Confirmed
A57: TMT-S1-F018 | B57: TMT | C57: S1 | D57: =IFERROR(VLOOKUP($G57,'02_REFERENCE'!$A$2:$S$99,4,FALSE),"N/A") -> N/A | E57: =IFERROR(VLOOKUP($G57,'02_REFERENCE'!$A$2:$S$99,15,FALSE),"N/A") -> N/A | F57: =IFERROR(VLOOKUP($G57,'02_REFERENCE'!$A$2:$S$99,17,FALSE),"N/A") -> N/A | H57: False Positive | I57: FP | J57: M | K57: N | L57: No | N57: Process-identity spoofing / memory-integrity template; no reference mechanism (authentication bypass RT-004 is logic-based, not process-spoofing). | P57: Elevation Using Impersonation | Q57: Diagram 1 | R57: Session Token | S57: Confirmed
A58: TMT-S1-F019 | B58: TMT | C58: S1 | D58: =IFERROR(VLOOKUP($G58,'02_REFERENCE'!$A$2:$S$99,4,FALSE),"N/A") -> N/A | E58: =IFERROR(VLOOKUP($G58,'02_REFERENCE'!$A$2:$S$99,15,FALSE),"N/A") -> N/A | F58: =IFERROR(VLOOKUP($G58,'02_REFERENCE'!$A$2:$S$99,17,FALSE),"N/A") -> N/A | H58: False Positive | I58: FP | J58: M | K58: N | L58: No | N58: Process-identity spoofing / memory-integrity template; no reference mechanism (authentication bypass RT-004 is logic-based, not process-spoofing). | P58: P1 Web Frontend Interface Process Memory Tampered | Q58: Diagram 1 | R58: Authenticated Session Response | S58: Confirmed
A59: TMT-S1-F020 | B59: TMT | C59: S1 | D59: =IFERROR(VLOOKUP($G59,'02_REFERENCE'!$A$2:$S$99,4,FALSE),"N/A") -> N/A | E59: =IFERROR(VLOOKUP($G59,'02_REFERENCE'!$A$2:$S$99,15,FALSE),"N/A") -> N/A | F59: =IFERROR(VLOOKUP($G59,'02_REFERENCE'!$A$2:$S$99,17,FALSE),"N/A") -> N/A | H59: False Positive | I59: FP | J59: M | K59: N | L59: No | N59: Process-identity spoofing / memory-integrity template; no reference mechanism (authentication bypass RT-004 is logic-based, not process-spoofing). | P59: Elevation Using Impersonation | Q59: Diagram 1 | R59: Authenticated Session Response | S59: Confirmed
A60: TMT-S1-F021 | B60: TMT | C60: S1 | D60: =IFERROR(VLOOKUP($G60,'02_REFERENCE'!$A$2:$S$99,4,FALSE),"N/A") -> N/A | E60: =IFERROR(VLOOKUP($G60,'02_REFERENCE'!$A$2:$S$99,15,FALSE),"N/A") -> N/A | F60: =IFERROR(VLOOKUP($G60,'02_REFERENCE'!$A$2:$S$99,17,FALSE),"N/A") -> N/A | H60: False Positive | I60: FP | J60: M | K60: N | L60: No | N60: Process-identity spoofing / memory-integrity template; no reference mechanism (authentication bypass RT-004 is logic-based, not process-spoofing). | P60: Elevation Using Impersonation | Q60: Diagram 1 | R60: Chatbot Question | S60: Confirmed
A61: TMT-S1-F022 | B61: TMT | C61: S1 | D61: =IFERROR(VLOOKUP($G61,'02_REFERENCE'!$A$2:$S$99,4,FALSE),"N/A") -> N/A | E61: =IFERROR(VLOOKUP($G61,'02_REFERENCE'!$A$2:$S$99,15,FALSE),"N/A") -> N/A | F61: =IFERROR(VLOOKUP($G61,'02_REFERENCE'!$A$2:$S$99,17,FALSE),"N/A") -> N/A | H61: False Positive | I61: FP | J61: M | K61: N | L61: No | N61: Process-identity spoofing / memory-integrity template; no reference mechanism (authentication bypass RT-004 is logic-based, not process-spoofing). | P61: EE1 End User (Browser) Process Memory Tampered | Q61: Diagram 1 | R61: Chatbot Question | S61: Confirmed
A62: TMT-S1-F023 | B62: TMT | C62: S1 | D62: =IFERROR(VLOOKUP($G62,'02_REFERENCE'!$A$2:$S$99,4,FALSE),"N/A") -> N/A | E62: =IFERROR(VLOOKUP($G62,'02_REFERENCE'!$A$2:$S$99,15,FALSE),"N/A") -> N/A | F62: =IFERROR(VLOOKUP($G62,'02_REFERENCE'!$A$2:$S$99,17,FALSE),"N/A") -> N/A | H62: False Positive | I62: FP | J62: M | K62: N | L62: No | N62: Process-crash template (internal availability); no reference mechanism (provider-unavailability refs concern the external service; DoS refs concern attacker-driven flooding). | P62: Potential Process Crash or Stop for EE1 End User (Browser) | Q62: Diagram 1 | R62: Chatbot Answer | S62: Confirmed
A63: TMT-S1-F024 | B63: TMT | C63: S1 | D63: =IFERROR(VLOOKUP($G63,'02_REFERENCE'!$A$2:$S$99,4,FALSE),"N/A") -> N/A | E63: =IFERROR(VLOOKUP($G63,'02_REFERENCE'!$A$2:$S$99,15,FALSE),"N/A") -> N/A | F63: =IFERROR(VLOOKUP($G63,'02_REFERENCE'!$A$2:$S$99,17,FALSE),"N/A") -> N/A | H63: False Positive | I63: FP | J63: M | K63: N | L63: No | N63: Sniffing of chatbot answer/question traffic in S1: the S1 baseline contains no reference for interception of chat content (RT-006 is credential-specific and RT-014 is session-token-specific). | P63: Data Flow Sniffing | Q63: Diagram 1 | R63: Chatbot Answer | S63: Confirmed
A64: TMT-S1-F025 | B64: TMT | C64: S1 | D64: =IFERROR(VLOOKUP($G64,'02_REFERENCE'!$A$2:$S$99,4,FALSE),"N/A") -> Repudiation | E64: =IFERROR(VLOOKUP($G64,'02_REFERENCE'!$A$2:$S$99,15,FALSE),"N/A") -> Medium | F64: =IFERROR(VLOOKUP($G64,'02_REFERENCE'!$A$2:$S$99,17,FALSE),"N/A") -> No | G64: S1-RT-021 | H64: Primary TP | I64: TP | J64: M | K64: Y | L64: No | N64: Attribution template -> reference S1-RT-021 (unspecified attribution of security-relevant actions). | O64: repudiation | P64: Potential Data Repudiation by EE1 End User (Browser) | Q64: Diagram 1 | R64: Chatbot Answer | S64: Confirmed
A65: TMT-S1-F026 | B65: TMT | C65: S1 | D65: =IFERROR(VLOOKUP($G65,'02_REFERENCE'!$A$2:$S$99,4,FALSE),"N/A") -> N/A | E65: =IFERROR(VLOOKUP($G65,'02_REFERENCE'!$A$2:$S$99,15,FALSE),"N/A") -> N/A | F65: =IFERROR(VLOOKUP($G65,'02_REFERENCE'!$A$2:$S$99,17,FALSE),"N/A") -> N/A | H65: False Positive | I65: FP | J65: M | K65: N | L65: No | N65: Process-identity spoofing / memory-integrity template; no reference mechanism (authentication bypass RT-004 is logic-based, not process-spoofing). | P65: P4 AI Authentication Assistant Process Memory Tampered | Q65: Diagram 1 | R65: Chatbot Answer | S65: Confirmed
A66: TMT-S1-F027 | B66: TMT | C66: S1 | D66: =IFERROR(VLOOKUP($G66,'02_REFERENCE'!$A$2:$S$99,4,FALSE),"N/A") -> N/A | E66: =IFERROR(VLOOKUP($G66,'02_REFERENCE'!$A$2:$S$99,15,FALSE),"N/A") -> N/A | F66: =IFERROR(VLOOKUP($G66,'02_REFERENCE'!$A$2:$S$99,17,FALSE),"N/A") -> N/A | H66: False Positive | I66: FP | J66: M | K66: N | L66: No | N66: Generic input-validation template; flow-specific reference mapping not supported (no matching mechanism). | P66: Potential Lack of Input Validation for EE1 End User (Browser) | Q66: Diagram 1 | R66: Chatbot Answer | S66: Confirmed
A67: TMT-S1-F028 | B67: TMT | C67: S1 | D67: =IFERROR(VLOOKUP($G67,'02_REFERENCE'!$A$2:$S$99,4,FALSE),"N/A") -> N/A | E67: =IFERROR(VLOOKUP($G67,'02_REFERENCE'!$A$2:$S$99,15,FALSE),"N/A") -> N/A | F67: =IFERROR(VLOOKUP($G67,'02_REFERENCE'!$A$2:$S$99,17,FALSE),"N/A") -> N/A | H67: False Positive | I67: FP | J67: M | K67: N | L67: No | N67: Process-identity spoofing / memory-integrity template; no reference mechanism (authentication bypass RT-004 is logic-based, not process-spoofing). | P67: Spoofing the EE1 End User (Browser) Process | Q67: Diagram 1 | R67: Chatbot Answer | S67: Confirmed
A68: TMT-S1-F029 | B68: TMT | C68: S1 | D68: =IFERROR(VLOOKUP($G68,'02_REFERENCE'!$A$2:$S$99,4,FALSE),"N/A") -> N/A | E68: =IFERROR(VLOOKUP($G68,'02_REFERENCE'!$A$2:$S$99,15,FALSE),"N/A") -> N/A | F68: =IFERROR(VLOOKUP($G68,'02_REFERENCE'!$A$2:$S$99,17,FALSE),"N/A") -> N/A | H68: False Positive | I68: FP | J68: M | K68: N | L68: No | N68: Process-identity spoofing / memory-integrity template; no reference mechanism (authentication bypass RT-004 is logic-based, not process-spoofing). | P68: Spoofing the P4 AI Authentication Assistant Process | Q68: Diagram 1 | R68: Chatbot Answer | S68: Confirmed
A69: TMT-S1-F030 | B69: TMT | C69: S1 | D69: =IFERROR(VLOOKUP($G69,'02_REFERENCE'!$A$2:$S$99,4,FALSE),"N/A") -> N/A | E69: =IFERROR(VLOOKUP($G69,'02_REFERENCE'!$A$2:$S$99,15,FALSE),"N/A") -> N/A | F69: =IFERROR(VLOOKUP($G69,'02_REFERENCE'!$A$2:$S$99,17,FALSE),"N/A") -> N/A | H69: False Positive | I69: FP | J69: M | K69: N | L69: No | N69: Flow-interruption template on a flow without a matching availability reference. | P69: Data Flow Chatbot Answer Is Potentially Interrupted | Q69: Diagram 1 | R69: Chatbot Answer | S69: Confirmed
A70: TMT-S1-F031 | B70: TMT | C70: S1 | D70: =IFERROR(VLOOKUP($G70,'02_REFERENCE'!$A$2:$S$99,4,FALSE),"N/A") -> N/A | E70: =IFERROR(VLOOKUP($G70,'02_REFERENCE'!$A$2:$S$99,15,FALSE),"N/A") -> N/A | F70: =IFERROR(VLOOKUP($G70,'02_REFERENCE'!$A$2:$S$99,17,FALSE),"N/A") -> N/A | H70: False Positive | I70: FP | J70: M | K70: N | L70: No | N70: Process-identity spoofing / memory-integrity template; no reference mechanism (authentication bypass RT-004 is logic-based, not process-spoofing). | P70: Elevation Using Impersonation | Q70: Diagram 1 | R70: Chatbot Answer | S70: Confirmed
A71: TMT-S1-F032 | B71: TMT | C71: S1 | D71: =IFERROR(VLOOKUP($G71,'02_REFERENCE'!$A$2:$S$99,4,FALSE),"N/A") -> N/A | E71: =IFERROR(VLOOKUP($G71,'02_REFERENCE'!$A$2:$S$99,15,FALSE),"N/A") -> N/A | F71: =IFERROR(VLOOKUP($G71,'02_REFERENCE'!$A$2:$S$99,17,FALSE),"N/A") -> N/A | H71: False Positive | I71: FP | J71: M | K71: N | L71: No | N71: Process-identity spoofing / memory-integrity template; no reference mechanism (authentication bypass RT-004 is logic-based, not process-spoofing). | P71: EE1 End User (Browser) May be Subject to Elevation of Privilege Using Remote Code Execution | Q71: Diagram 1 | R71: Chatbot Answer | S71: Confirmed
A72: TMT-S1-F033 | B72: TMT | C72: S1 | D72: =IFERROR(VLOOKUP($G72,'02_REFERENCE'!$A$2:$S$99,4,FALSE),"N/A") -> N/A | E72: =IFERROR(VLOOKUP($G72,'02_REFERENCE'!$A$2:$S$99,15,FALSE),"N/A") -> N/A | F72: =IFERROR(VLOOKUP($G72,'02_REFERENCE'!$A$2:$S$99,17,FALSE),"N/A") -> N/A | H72: False Positive | I72: FP | J72: M | K72: N | L72: No | N72: Process-identity spoofing / memory-integrity template; no reference mechanism (authentication bypass RT-004 is logic-based, not process-spoofing). | P72: Elevation by Changing the Execution Flow in EE1 End User (Browser) | Q72: Diagram 1 | R72: Chatbot Answer | S72: Confirmed
A73: TMT-S1-F034 | B73: TMT | C73: S1 | D73: =IFERROR(VLOOKUP($G73,'02_REFERENCE'!$A$2:$S$99,4,FALSE),"N/A") -> N/A | E73: =IFERROR(VLOOKUP($G73,'02_REFERENCE'!$A$2:$S$99,15,FALSE),"N/A") -> N/A | F73: =IFERROR(VLOOKUP($G73,'02_REFERENCE'!$A$2:$S$99,17,FALSE),"N/A") -> N/A | H73: False Positive | I73: FP | J73: M | K73: N | L73: No | N73: Process-identity spoofing / memory-integrity template; no reference mechanism (authentication bypass RT-004 is logic-based, not process-spoofing). | P73: P4 AI Authentication Assistant Process Memory Tampered | Q73: Diagram 1 | R73: Prompt Request | S73: Confirmed
A74: TMT-S1-F035 | B74: TMT | C74: S1 | D74: =IFERROR(VLOOKUP($G74,'02_REFERENCE'!$A$2:$S$99,4,FALSE),"N/A") -> N/A | E74: =IFERROR(VLOOKUP($G74,'02_REFERENCE'!$A$2:$S$99,15,FALSE),"N/A") -> N/A | F74: =IFERROR(VLOOKUP($G74,'02_REFERENCE'!$A$2:$S$99,17,FALSE),"N/A") -> N/A | H74: False Positive | I74: FP | J74: M | K74: N | L74: No | N74: Process-identity spoofing / memory-integrity template; no reference mechanism (authentication bypass RT-004 is logic-based, not process-spoofing). | P74: Elevation Using Impersonation | Q74: Diagram 1 | R74: Prompt Request | S74: Confirmed
A75: TMT-S1-F036 | B75: TMT | C75: S1 | D75: =IFERROR(VLOOKUP($G75,'02_REFERENCE'!$A$2:$S$99,4,FALSE),"N/A") -> N/A | E75: =IFERROR(VLOOKUP($G75,'02_REFERENCE'!$A$2:$S$99,15,FALSE),"N/A") -> N/A | F75: =IFERROR(VLOOKUP($G75,'02_REFERENCE'!$A$2:$S$99,17,FALSE),"N/A") -> N/A | H75: False Positive | I75: FP | J75: M | K75: N | L75: No | N75: Process-identity spoofing / memory-integrity template; no reference mechanism (authentication bypass RT-004 is logic-based, not process-spoofing). | P75: P5 LLM Integration Service Process Memory Tampered | Q75: Diagram 1 | R75: Processed AI Response | S75: Confirmed
A76: TMT-S1-F037 | B76: TMT | C76: S1 | D76: =IFERROR(VLOOKUP($G76,'02_REFERENCE'!$A$2:$S$99,4,FALSE),"N/A") -> N/A | E76: =IFERROR(VLOOKUP($G76,'02_REFERENCE'!$A$2:$S$99,15,FALSE),"N/A") -> N/A | F76: =IFERROR(VLOOKUP($G76,'02_REFERENCE'!$A$2:$S$99,17,FALSE),"N/A") -> N/A | H76: False Positive | I76: FP | J76: M | K76: N | L76: No | N76: Process-identity spoofing / memory-integrity template; no reference mechanism (authentication bypass RT-004 is logic-based, not process-spoofing). | P76: Elevation Using Impersonation | Q76: Diagram 1 | R76: Processed AI Response | S76: Confirmed
A77: TMT-S1-F038 | B77: TMT | C77: S1 | D77: =IFERROR(VLOOKUP($G77,'02_REFERENCE'!$A$2:$S$99,4,FALSE),"N/A") -> Spoofing | E77: =IFERROR(VLOOKUP($G77,'02_REFERENCE'!$A$2:$S$99,15,FALSE),"N/A") -> High | F77: =IFERROR(VLOOKUP($G77,'02_REFERENCE'!$A$2:$S$99,17,FALSE),"N/A") -> Yes | G77: S1-RT-036 | H77: Primary TP | I77: TP | J77: M | K77: Y | L77: No | N77: Spoofing/impersonation of the external LLM provider -> reference S1-RT-036 (compromise or substitution of the external model service). | O77: model_substitution | P77: Spoofing the EE2 External LLM Provider External Entity | Q77: Diagram 1 | R77: Generated LLM Response | S77: Confirmed
A78: TMT-S1-F039 | B78: TMT | C78: S1 | D78: =IFERROR(VLOOKUP($G78,'02_REFERENCE'!$A$2:$S$99,4,FALSE),"N/A") -> N/A | E78: =IFERROR(VLOOKUP($G78,'02_REFERENCE'!$A$2:$S$99,15,FALSE),"N/A") -> N/A | F78: =IFERROR(VLOOKUP($G78,'02_REFERENCE'!$A$2:$S$99,17,FALSE),"N/A") -> N/A | H78: False Positive | I78: FP | J78: M | K78: N | L78: No | N78: Process-identity spoofing / memory-integrity template; no reference mechanism (authentication bypass RT-004 is logic-based, not process-spoofing). | P78: Elevation Using Impersonation | Q78: Diagram 1 | R78: Generated LLM Response | S78: Confirmed
A79: TMT-S1-F040 | B79: TMT | C79: S1 | D79: =IFERROR(VLOOKUP($G79,'02_REFERENCE'!$A$2:$S$99,4,FALSE),"N/A") -> N/A | E79: =IFERROR(VLOOKUP($G79,'02_REFERENCE'!$A$2:$S$99,15,FALSE),"N/A") -> N/A | F79: =IFERROR(VLOOKUP($G79,'02_REFERENCE'!$A$2:$S$99,17,FALSE),"N/A") -> N/A | H79: False Positive | I79: FP | J79: M | K79: N | L79: No | N79: Process-identity spoofing / memory-integrity template; no reference mechanism (authentication bypass RT-004 is logic-based, not process-spoofing). | P79: Spoofing the EE1 End User (Browser) Process | Q79: Diagram 1 | R79: Chatbot Question | S79: Confirmed
A80: TMT-S1-F041 | B80: TMT | C80: S1 | D80: =IFERROR(VLOOKUP($G80,'02_REFERENCE'!$A$2:$S$99,4,FALSE),"N/A") -> N/A | E80: =IFERROR(VLOOKUP($G80,'02_REFERENCE'!$A$2:$S$99,15,FALSE),"N/A") -> N/A | F80: =IFERROR(VLOOKUP($G80,'02_REFERENCE'!$A$2:$S$99,17,FALSE),"N/A") -> N/A | H80: False Positive | I80: FP | J80: M | K80: N | L80: No | N80: Process-identity spoofing / memory-integrity template; no reference mechanism (authentication bypass RT-004 is logic-based, not process-spoofing). | P80: Spoofing the P4 AI Authentication Assistant Process | Q80: Diagram 1 | R80: Chatbot Question | S80: Confirmed
A81: TMT-S1-F042 | B81: TMT | C81: S1 | D81: =IFERROR(VLOOKUP($G81,'02_REFERENCE'!$A$2:$S$99,4,FALSE),"N/A") -> Tampering | E81: =IFERROR(VLOOKUP($G81,'02_REFERENCE'!$A$2:$S$99,15,FALSE),"N/A") -> High | F81: =IFERROR(VLOOKUP($G81,'02_REFERENCE'!$A$2:$S$99,17,FALSE),"N/A") -> Yes | G81: S1-RT-022 | H81: Primary TP | I81: TP | J81: M | K81: Y | L81: No | N81: Unvalidated user input on the assistant question path -> direct prompt injection -> reference S1-RT-022. | O81: prompt_injection_direct | P81: Potential Lack of Input Validation for P4 AI Authentication Assistant | Q81: Diagram 1 | R81: Chatbot Question | S81: Confirmed
A82: TMT-S1-F043 | B82: TMT | C82: S1 | D82: =IFERROR(VLOOKUP($G82,'02_REFERENCE'!$A$2:$S$99,4,FALSE),"N/A") -> Repudiation | E82: =IFERROR(VLOOKUP($G82,'02_REFERENCE'!$A$2:$S$99,15,FALSE),"N/A") -> Medium | F82: =IFERROR(VLOOKUP($G82,'02_REFERENCE'!$A$2:$S$99,17,FALSE),"N/A") -> No | G82: S1-RT-021 | H82: Duplicate | I82: TP | J82: M | K82: N | L82: Yes | M82: TMT-S1-F025 | N82: Attribution template -> reference S1-RT-021 (unspecified attribution of security-relevant actions). [Equivalence: restates TMT-S1-F025 — one-to-one rule applied.] | O82: repudiation | P82: Potential Data Repudiation by P4 AI Authentication Assistant | Q82: Diagram 1 | R82: Chatbot Question | S82: Confirmed
A83: TMT-S1-F044 | B83: TMT | C83: S1 | D83: =IFERROR(VLOOKUP($G83,'02_REFERENCE'!$A$2:$S$99,4,FALSE),"N/A") -> N/A | E83: =IFERROR(VLOOKUP($G83,'02_REFERENCE'!$A$2:$S$99,15,FALSE),"N/A") -> N/A | F83: =IFERROR(VLOOKUP($G83,'02_REFERENCE'!$A$2:$S$99,17,FALSE),"N/A") -> N/A | H83: False Positive | I83: FP | J83: M | K83: N | L83: No | N83: Sniffing of chatbot answer/question traffic in S1: the S1 baseline contains no reference for interception of chat content (RT-006 is credential-specific and RT-014 is session-token-specific). | P83: Data Flow Sniffing | Q83: Diagram 1 | R83: Chatbot Question | S83: Confirmed
A84: TMT-S1-F045 | B84: TMT | C84: S1 | D84: =IFERROR(VLOOKUP($G84,'02_REFERENCE'!$A$2:$S$99,4,FALSE),"N/A") -> N/A | E84: =IFERROR(VLOOKUP($G84,'02_REFERENCE'!$A$2:$S$99,15,FALSE),"N/A") -> N/A | F84: =IFERROR(VLOOKUP($G84,'02_REFERENCE'!$A$2:$S$99,17,FALSE),"N/A") -> N/A | H84: False Positive | I84: FP | J84: M | K84: N | L84: No | N84: Process-crash template (internal availability); no reference mechanism (provider-unavailability refs concern the external service; DoS refs concern attacker-driven flooding). | P84: Potential Process Crash or Stop for P4 AI Authentication Assistant | Q84: Diagram 1 | R84: Chatbot Question | S84: Confirmed
A85: TMT-S1-F046 | B85: TMT | C85: S1 | D85: =IFERROR(VLOOKUP($G85,'02_REFERENCE'!$A$2:$S$99,4,FALSE),"N/A") -> N/A | E85: =IFERROR(VLOOKUP($G85,'02_REFERENCE'!$A$2:$S$99,15,FALSE),"N/A") -> N/A | F85: =IFERROR(VLOOKUP($G85,'02_REFERENCE'!$A$2:$S$99,17,FALSE),"N/A") -> N/A | H85: False Positive | I85: FP | J85: M | K85: N | L85: No | N85: Flow-interruption template on a flow without a matching availability reference. | P85: Data Flow Chatbot Question Is Potentially Interrupted | Q85: Diagram 1 | R85: Chatbot Question | S85: Confirmed
A86: TMT-S1-F047 | B86: TMT | C86: S1 | D86: =IFERROR(VLOOKUP($G86,'02_REFERENCE'!$A$2:$S$99,4,FALSE),"N/A") -> N/A | E86: =IFERROR(VLOOKUP($G86,'02_REFERENCE'!$A$2:$S$99,15,FALSE),"N/A") -> N/A | F86: =IFERROR(VLOOKUP($G86,'02_REFERENCE'!$A$2:$S$99,17,FALSE),"N/A") -> N/A | H86: False Positive | I86: FP | J86: M | K86: N | L86: No | N86: Process-identity spoofing / memory-integrity template; no reference mechanism (authentication bypass RT-004 is logic-based, not process-spoofing). | P86: P4 AI Authentication Assistant May be Subject to Elevation of Privilege Using Remote Code Execution | Q86: Diagram 1 | R86: Chatbot Question | S86: Confirmed
A87: TMT-S1-F048 | B87: TMT | C87: S1 | D87: =IFERROR(VLOOKUP($G87,'02_REFERENCE'!$A$2:$S$99,4,FALSE),"N/A") -> N/A | E87: =IFERROR(VLOOKUP($G87,'02_REFERENCE'!$A$2:$S$99,15,FALSE),"N/A") -> N/A | F87: =IFERROR(VLOOKUP($G87,'02_REFERENCE'!$A$2:$S$99,17,FALSE),"N/A") -> N/A | H87: False Positive | I87: FP | J87: M | K87: N | L87: No | N87: Process-identity spoofing / memory-integrity template; no reference mechanism (authentication bypass RT-004 is logic-based, not process-spoofing). | P87: Elevation by Changing the Execution Flow in P4 AI Authentication Assistant | Q87: Diagram 1 | R87: Chatbot Question | S87: Confirmed
A88: TMT-S1-F049 | B88: TMT | C88: S1 | D88: =IFERROR(VLOOKUP($G88,'02_REFERENCE'!$A$2:$S$99,4,FALSE),"N/A") -> N/A | E88: =IFERROR(VLOOKUP($G88,'02_REFERENCE'!$A$2:$S$99,15,FALSE),"N/A") -> N/A | F88: =IFERROR(VLOOKUP($G88,'02_REFERENCE'!$A$2:$S$99,17,FALSE),"N/A") -> N/A | H88: False Positive | I88: FP | J88: M | K88: N | L88: No | N88: CSRF template; the reference baseline contains no CSRF mechanism (session threats are fixation/theft/replay/prediction/storage). | P88: Cross Site Request Forgery | Q88: Diagram 1 | R88: Chatbot Question | S88: Confirmed
A89: TMT-S1-F050 | B89: TMT | C89: S1 | D89: =IFERROR(VLOOKUP($G89,'02_REFERENCE'!$A$2:$S$99,4,FALSE),"N/A") -> N/A | E89: =IFERROR(VLOOKUP($G89,'02_REFERENCE'!$A$2:$S$99,15,FALSE),"N/A") -> N/A | F89: =IFERROR(VLOOKUP($G89,'02_REFERENCE'!$A$2:$S$99,17,FALSE),"N/A") -> N/A | H89: False Positive | I89: FP | J89: M | K89: N | L89: No | N89: Process-identity spoofing / memory-integrity template; no reference mechanism (authentication bypass RT-004 is logic-based, not process-spoofing). | P89: Spoofing the P5 LLM Integration Service Process | Q89: Diagram 1 | R89: Generated LLM Response | S89: Confirmed
A90: TMT-S1-F051 | B90: TMT | C90: S1 | D90: =IFERROR(VLOOKUP($G90,'02_REFERENCE'!$A$2:$S$99,4,FALSE),"N/A") -> Tampering | E90: =IFERROR(VLOOKUP($G90,'02_REFERENCE'!$A$2:$S$99,15,FALSE),"N/A") -> Critical | F90: =IFERROR(VLOOKUP($G90,'02_REFERENCE'!$A$2:$S$99,17,FALSE),"N/A") -> Yes | G90: S1-RT-033 | H90: Primary TP | I90: TP | J90: M | K90: Y | L90: No | N90: Unvalidated input on the generated-response path -> insecure handling of generated output -> reference S1-RT-033. | O90: unsafe_output | P90: Potential Lack of Input Validation for P5 LLM Integration Service | Q90: Diagram 1 | R90: Generated LLM Response | S90: Confirmed
A91: TMT-S1-F052 | B91: TMT | C91: S1 | D91: =IFERROR(VLOOKUP($G91,'02_REFERENCE'!$A$2:$S$99,4,FALSE),"N/A") -> Repudiation | E91: =IFERROR(VLOOKUP($G91,'02_REFERENCE'!$A$2:$S$99,15,FALSE),"N/A") -> Medium | F91: =IFERROR(VLOOKUP($G91,'02_REFERENCE'!$A$2:$S$99,17,FALSE),"N/A") -> No | G91: S1-RT-021 | H91: Duplicate | I91: TP | J91: M | K91: N | L91: Yes | M91: TMT-S1-F025 | N91: Attribution template -> reference S1-RT-021 (unspecified attribution of security-relevant actions). [Equivalence: restates TMT-S1-F025 — one-to-one rule applied.] | O91: repudiation | P91: Potential Data Repudiation by P5 LLM Integration Service | Q91: Diagram 1 | R91: Generated LLM Response | S91: Confirmed
A92: TMT-S1-F053 | B92: TMT | C92: S1 | D92: =IFERROR(VLOOKUP($G92,'02_REFERENCE'!$A$2:$S$99,4,FALSE),"N/A") -> N/A | E92: =IFERROR(VLOOKUP($G92,'02_REFERENCE'!$A$2:$S$99,15,FALSE),"N/A") -> N/A | F92: =IFERROR(VLOOKUP($G92,'02_REFERENCE'!$A$2:$S$99,17,FALSE),"N/A") -> N/A | H92: False Positive | I92: FP | J92: M | K92: N | L92: No | N92: Sniffing of prompt/provider traffic: the baseline contains no reference for interception of prompt traffic (credential-token sniffing and file-interception refs are asset-specific; RT-024 covers application-side over-inclusion, not interception). | P92: Data Flow Sniffing | Q92: Diagram 1 | R92: Generated LLM Response | S92: Confirmed
A93: TMT-S1-F054 | B93: TMT | C93: S1 | D93: =IFERROR(VLOOKUP($G93,'02_REFERENCE'!$A$2:$S$99,4,FALSE),"N/A") -> N/A | E93: =IFERROR(VLOOKUP($G93,'02_REFERENCE'!$A$2:$S$99,15,FALSE),"N/A") -> N/A | F93: =IFERROR(VLOOKUP($G93,'02_REFERENCE'!$A$2:$S$99,17,FALSE),"N/A") -> N/A | H93: False Positive | I93: FP | J93: M | K93: N | L93: No | N93: Process-crash template (internal availability); no reference mechanism (provider-unavailability refs concern the external service; DoS refs concern attacker-driven flooding). | P93: Potential Process Crash or Stop for P5 LLM Integration Service | Q93: Diagram 1 | R93: Generated LLM Response | S93: Confirmed
A94: TMT-S1-F055 | B94: TMT | C94: S1 | D94: =IFERROR(VLOOKUP($G94,'02_REFERENCE'!$A$2:$S$99,4,FALSE),"N/A") -> Denial of Service | E94: =IFERROR(VLOOKUP($G94,'02_REFERENCE'!$A$2:$S$99,15,FALSE),"N/A") -> Medium | F94: =IFERROR(VLOOKUP($G94,'02_REFERENCE'!$A$2:$S$99,17,FALSE),"N/A") -> Yes | G94: S1-RT-029 | H94: Primary TP | I94: TP | J94: M | K94: Y | L94: No | N94: Interruption of the provider exchange -> reference S1-RT-029 (provider unavailability). | O94: llm_unavailable | P94: Data Flow Generated LLM Response Is Potentially Interrupted | Q94: Diagram 1 | R94: Generated LLM Response | S94: Confirmed
A95: TMT-S1-F056 | B95: TMT | C95: S1 | D95: =IFERROR(VLOOKUP($G95,'02_REFERENCE'!$A$2:$S$99,4,FALSE),"N/A") -> N/A | E95: =IFERROR(VLOOKUP($G95,'02_REFERENCE'!$A$2:$S$99,15,FALSE),"N/A") -> N/A | F95: =IFERROR(VLOOKUP($G95,'02_REFERENCE'!$A$2:$S$99,17,FALSE),"N/A") -> N/A | H95: False Positive | I95: FP | J95: M | K95: N | L95: No | N95: Process-identity spoofing / memory-integrity template; no reference mechanism (authentication bypass RT-004 is logic-based, not process-spoofing). | P95: P5 LLM Integration Service May be Subject to Elevation of Privilege Using Remote Code Execution | Q95: Diagram 1 | R95: Generated LLM Response | S95: Confirmed
A96: TMT-S1-F057 | B96: TMT | C96: S1 | D96: =IFERROR(VLOOKUP($G96,'02_REFERENCE'!$A$2:$S$99,4,FALSE),"N/A") -> N/A | E96: =IFERROR(VLOOKUP($G96,'02_REFERENCE'!$A$2:$S$99,15,FALSE),"N/A") -> N/A | F96: =IFERROR(VLOOKUP($G96,'02_REFERENCE'!$A$2:$S$99,17,FALSE),"N/A") -> N/A | H96: False Positive | I96: FP | J96: M | K96: N | L96: No | N96: Process-identity spoofing / memory-integrity template; no reference mechanism (authentication bypass RT-004 is logic-based, not process-spoofing). | P96: Elevation by Changing the Execution Flow in P5 LLM Integration Service | Q96: Diagram 1 | R96: Generated LLM Response | S96: Confirmed
A97: TMT-S1-F058 | B97: TMT | C97: S1 | D97: =IFERROR(VLOOKUP($G97,'02_REFERENCE'!$A$2:$S$99,4,FALSE),"N/A") -> N/A | E97: =IFERROR(VLOOKUP($G97,'02_REFERENCE'!$A$2:$S$99,15,FALSE),"N/A") -> N/A | F97: =IFERROR(VLOOKUP($G97,'02_REFERENCE'!$A$2:$S$99,17,FALSE),"N/A") -> N/A | H97: False Positive | I97: FP | J97: M | K97: N | L97: No | N97: CSRF template; the reference baseline contains no CSRF mechanism (session threats are fixation/theft/replay/prediction/storage). | P97: Cross Site Request Forgery | Q97: Diagram 1 | R97: Generated LLM Response | S97: Confirmed
A98: TMT-S1-F059 | B98: TMT | C98: S1 | D98: =IFERROR(VLOOKUP($G98,'02_REFERENCE'!$A$2:$S$99,4,FALSE),"N/A") -> Denial of Service | E98: =IFERROR(VLOOKUP($G98,'02_REFERENCE'!$A$2:$S$99,15,FALSE),"N/A") -> Medium | F98: =IFERROR(VLOOKUP($G98,'02_REFERENCE'!$A$2:$S$99,17,FALSE),"N/A") -> Yes | G98: S1-RT-029 | H98: Duplicate | I98: TP | J98: M | K98: N | L98: Yes | M98: TMT-S1-F055 | N98: Interruption of the provider exchange -> reference S1-RT-029 (provider unavailability). [Equivalence: restates TMT-S1-F055 — one-to-one rule applied.] | O98: llm_unavailable | P98: Data Flow Prompt + Approved Context Is Potentially Interrupted | Q98: Diagram 1 | R98: Prompt + Approved Context | S98: Confirmed
A99: TMT-S1-F060 | B99: TMT | C99: S1 | D99: =IFERROR(VLOOKUP($G99,'02_REFERENCE'!$A$2:$S$99,4,FALSE),"N/A") -> N/A | E99: =IFERROR(VLOOKUP($G99,'02_REFERENCE'!$A$2:$S$99,15,FALSE),"N/A") -> N/A | F99: =IFERROR(VLOOKUP($G99,'02_REFERENCE'!$A$2:$S$99,17,FALSE),"N/A") -> N/A | H99: False Positive | I99: FP | J99: M | K99: N | L99: No | N99: No reference threat corresponds to this finding's mechanism (scoring found no class with sufficient evidence). | P99: External Entity EE2 External LLM Provider Potentially Denies Receiving Data | Q99: Diagram 1 | R99: Prompt + Approved Context | S99: Confirmed
A100: TMT-S1-F061 | B100: TMT | C100: S1 | D100: =IFERROR(VLOOKUP($G100,'02_REFERENCE'!$A$2:$S$99,4,FALSE),"N/A") -> Spoofing | E100: =IFERROR(VLOOKUP($G100,'02_REFERENCE'!$A$2:$S$99,15,FALSE),"N/A") -> High | F100: =IFERROR(VLOOKUP($G100,'02_REFERENCE'!$A$2:$S$99,17,FALSE),"N/A") -> Yes | G100: S1-RT-036 | H100: Duplicate | I100: TP | J100: M | K100: N | L100: Yes | M100: TMT-S1-F038 | N100: Spoofing/impersonation of the external LLM provider -> reference S1-RT-036 (compromise or substitution of the external model service). [Equivalence: restates TMT-S1-F038 — one-to-one rule applied.] | O100: model_substitution | P100: Spoofing of the EE2 External LLM Provider External Destination Entity | Q100: Diagram 1 | R100: Prompt + Approved Context | S100: Confirmed
...

Sheet 05_TP_FP_FN
A1: TP / FP / FN per Approach x Scenario
A2: TP counts PRIMARY TPs only (one-to-one rule), so TP = number of distinct covered references. FN = reference threats with no primary TP. All cells are formulas over 03/04.
A4: Approach | B4: Scenario | C4: Generated | D4: Reference | E4: TP (Primary) | F4: FP | G4: Duplicates | H4: FN | I4: Precision | J4: Recall/Coverage | K4: F1 | L4: Check TP<=Ref | M4: Check TP+FN=Ref | N4: Check Gen=TP+FP+Dup
A5: OWASP | B5: S1 | C5: =COUNTIFS('04_MATCHING'!$B$2:$B$1026,$A5,'04_MATCHING'!$C$2:$C$1026,$B5) -> 38 | D5: =COUNTIFS('02_REFERENCE'!$B$2:$B$99,$B5,'02_REFERENCE'!$S$2:$S$99,"YES") -> 32 | E5: =COUNTIFS('04_MATCHING'!$B$2:$B$1026,$A5,'04_MATCHING'!$C$2:$C$1026,$B5,'04_MATCHING'!$H$2:$H$1026,"Primary TP") -> 6 | F5: =COUNTIFS('04_MATCHING'!$B$2:$B$1026,$A5,'04_MATCHING'!$C$2:$C$1026,$B5,'04_MATCHING'!$H$2:$H$1026,"False Positive") -> 26 | G5: =COUNTIFS('04_MATCHING'!$B$2:$B$1026,$A5,'04_MATCHING'!$C$2:$C$1026,$B5,'04_MATCHING'!$H$2:$H$1026,"Duplicate") -> 6 | H5: =D5-E5 -> 26 | I5: =IFERROR(E5/(E5+F5),"") -> 0.1875 | J5: =IFERROR(E5/D5,"") -> 0.1875 | K5: =IFERROR(2*I5*J5/(I5+J5),"") -> 0.1875 | L5: =IF(E5<=D5,"PASS","FAIL") -> PASS | M5: =IF(E5+H5=D5,"PASS","FAIL") -> PASS | N5: =IF(C5=E5+F5+G5,"PASS","FAIL") -> PASS
A6: OWASP | B6: S2 | C6: =COUNTIFS('04_MATCHING'!$B$2:$B$1026,$A6,'04_MATCHING'!$C$2:$C$1026,$B6) -> 39 | D6: =COUNTIFS('02_REFERENCE'!$B$2:$B$99,$B6,'02_REFERENCE'!$S$2:$S$99,"YES") -> 33 | E6: =COUNTIFS('04_MATCHING'!$B$2:$B$1026,$A6,'04_MATCHING'!$C$2:$C$1026,$B6,'04_MATCHING'!$H$2:$H$1026,"Primary TP") -> 6 | F6: =COUNTIFS('04_MATCHING'!$B$2:$B$1026,$A6,'04_MATCHING'!$C$2:$C$1026,$B6,'04_MATCHING'!$H$2:$H$1026,"False Positive") -> 27 | G6: =COUNTIFS('04_MATCHING'!$B$2:$B$1026,$A6,'04_MATCHING'!$C$2:$C$1026,$B6,'04_MATCHING'!$H$2:$H$1026,"Duplicate") -> 6 | H6: =D6-E6 -> 27 | I6: =IFERROR(E6/(E6+F6),"") -> 0.18181818 | J6: =IFERROR(E6/D6,"") -> 0.18181818 | K6: =IFERROR(2*I6*J6/(I6+J6),"") -> 0.18181818 | L6: =IF(E6<=D6,"PASS","FAIL") -> PASS | M6: =IF(E6+H6=D6,"PASS","FAIL") -> PASS | N6: =IF(C6=E6+F6+G6,"PASS","FAIL") -> PASS
A7: OWASP | B7: S3 | C7: =COUNTIFS('04_MATCHING'!$B$2:$B$1026,$A7,'04_MATCHING'!$C$2:$C$1026,$B7) -> 46 | D7: =COUNTIFS('02_REFERENCE'!$B$2:$B$99,$B7,'02_REFERENCE'!$S$2:$S$99,"YES") -> 33 | E7: =COUNTIFS('04_MATCHING'!$B$2:$B$1026,$A7,'04_MATCHING'!$C$2:$C$1026,$B7,'04_MATCHING'!$H$2:$H$1026,"Primary TP") -> 7 | F7: =COUNTIFS('04_MATCHING'!$B$2:$B$1026,$A7,'04_MATCHING'!$C$2:$C$1026,$B7,'04_MATCHING'!$H$2:$H$1026,"False Positive") -> 26 | G7: =COUNTIFS('04_MATCHING'!$B$2:$B$1026,$A7,'04_MATCHING'!$C$2:$C$1026,$B7,'04_MATCHING'!$H$2:$H$1026,"Duplicate") -> 13 | H7: =D7-E7 -> 26 | I7: =IFERROR(E7/(E7+F7),"") -> 0.21212121 | J7: =IFERROR(E7/D7,"") -> 0.21212121 | K7: =IFERROR(2*I7*J7/(I7+J7),"") -> 0.21212121 | L7: =IF(E7<=D7,"PASS","FAIL") -> PASS | M7: =IF(E7+H7=D7,"PASS","FAIL") -> PASS | N7: =IF(C7=E7+F7+G7,"PASS","FAIL") -> PASS
A8: TMT | B8: S1 | C8: =COUNTIFS('04_MATCHING'!$B$2:$B$1026,$A8,'04_MATCHING'!$C$2:$C$1026,$B8) -> 95 | D8: =COUNTIFS('02_REFERENCE'!$B$2:$B$99,$B8,'02_REFERENCE'!$S$2:$S$99,"YES") -> 32 | E8: =COUNTIFS('04_MATCHING'!$B$2:$B$1026,$A8,'04_MATCHING'!$C$2:$C$1026,$B8,'04_MATCHING'!$H$2:$H$1026,"Primary TP") -> 9 | F8: =COUNTIFS('04_MATCHING'!$B$2:$B$1026,$A8,'04_MATCHING'!$C$2:$C$1026,$B8,'04_MATCHING'!$H$2:$H$1026,"False Positive") -> 73 | G8: =COUNTIFS('04_MATCHING'!$B$2:$B$1026,$A8,'04_MATCHING'!$C$2:$C$1026,$B8,'04_MATCHING'!$H$2:$H$1026,"Duplicate") -> 13 | H8: =D8-E8 -> 23 | I8: =IFERROR(E8/(E8+F8),"") -> 0.1097561 | J8: =IFERROR(E8/D8,"") -> 0.28125 | K8: =IFERROR(2*I8*J8/(I8+J8),"") -> 0.15789474 | L8: =IF(E8<=D8,"PASS","FAIL") -> PASS | M8: =IF(E8+H8=D8,"PASS","FAIL") -> PASS | N8: =IF(C8=E8+F8+G8,"PASS","FAIL") -> PASS
A9: TMT | B9: S2 | C9: =COUNTIFS('04_MATCHING'!$B$2:$B$1026,$A9,'04_MATCHING'!$C$2:$C$1026,$B9) -> 89 | D9: =COUNTIFS('02_REFERENCE'!$B$2:$B$99,$B9,'02_REFERENCE'!$S$2:$S$99,"YES") -> 33 | E9: =COUNTIFS('04_MATCHING'!$B$2:$B$1026,$A9,'04_MATCHING'!$C$2:$C$1026,$B9,'04_MATCHING'!$H$2:$H$1026,"Primary TP") -> 10 | F9: =COUNTIFS('04_MATCHING'!$B$2:$B$1026,$A9,'04_MATCHING'!$C$2:$C$1026,$B9,'04_MATCHING'!$H$2:$H$1026,"False Positive") -> 65 | G9: =COUNTIFS('04_MATCHING'!$B$2:$B$1026,$A9,'04_MATCHING'!$C$2:$C$1026,$B9,'04_MATCHING'!$H$2:$H$1026,"Duplicate") -> 14 | H9: =D9-E9 -> 23 | I9: =IFERROR(E9/(E9+F9),"") -> 0.13333333 | J9: =IFERROR(E9/D9,"") -> 0.3030303 | K9: =IFERROR(2*I9*J9/(I9+J9),"") -> 0.18518519 | L9: =IF(E9<=D9,"PASS","FAIL") -> PASS | M9: =IF(E9+H9=D9,"PASS","FAIL") -> PASS | N9: =IF(C9=E9+F9+G9,"PASS","FAIL") -> PASS
A10: TMT | B10: S3 | C10: =COUNTIFS('04_MATCHING'!$B$2:$B$1026,$A10,'04_MATCHING'!$C$2:$C$1026,$B10) -> 117 | D10: =COUNTIFS('02_REFERENCE'!$B$2:$B$99,$B10,'02_REFERENCE'!$S$2:$S$99,"YES") -> 33 | E10: =COUNTIFS('04_MATCHING'!$B$2:$B$1026,$A10,'04_MATCHING'!$C$2:$C$1026,$B10,'04_MATCHING'!$H$2:$H$1026,"Primary TP") -> 9 | F10: =COUNTIFS('04_MATCHING'!$B$2:$B$1026,$A10,'04_MATCHING'!$C$2:$C$1026,$B10,'04_MATCHING'!$H$2:$H$1026,"False Positive") -> 83 | G10: =COUNTIFS('04_MATCHING'!$B$2:$B$1026,$A10,'04_MATCHING'!$C$2:$C$1026,$B10,'04_MATCHING'!$H$2:$H$1026,"Duplicate") -> 25 | H10: =D10-E10 -> 24 | I10: =IFERROR(E10/(E10+F10),"") -> 0.097826087 | J10: =IFERROR(E10/D10,"") -> 0.27272727 | K10: =IFERROR(2*I10*J10/(I10+J10),"") -> 0.144 | L10: =IF(E10<=D10,"PASS","FAIL") -> PASS | M10: =IF(E10+H10=D10,"PASS","FAIL") -> PASS | N10: =IF(C10=E10+F10+G10,"PASS","FAIL") -> PASS
A11: CHATGPT | B11: S1 | C11: =COUNTIFS('04_MATCHING'!$B$2:$B$1026,$A11,'04_MATCHING'!$C$2:$C$1026,$B11) -> 72 | D11: =COUNTIFS('02_REFERENCE'!$B$2:$B$99,$B11,'02_REFERENCE'!$S$2:$S$99,"YES") -> 32 | E11: =COUNTIFS('04_MATCHING'!$B$2:$B$1026,$A11,'04_MATCHING'!$C$2:$C$1026,$B11,'04_MATCHING'!$H$2:$H$1026,"Primary TP") -> 18 | F11: =COUNTIFS('04_MATCHING'!$B$2:$B$1026,$A11,'04_MATCHING'!$C$2:$C$1026,$B11,'04_MATCHING'!$H$2:$H$1026,"False Positive") -> 17 | G11: =COUNTIFS('04_MATCHING'!$B$2:$B$1026,$A11,'04_MATCHING'!$C$2:$C$1026,$B11,'04_MATCHING'!$H$2:$H$1026,"Duplicate") -> 37 | H11: =D11-E11 -> 14 | I11: =IFERROR(E11/(E11+F11),"") -> 0.51428571 | J11: =IFERROR(E11/D11,"") -> 0.5625 | K11: =IFERROR(2*I11*J11/(I11+J11),"") -> 0.53731343 | L11: =IF(E11<=D11,"PASS","FAIL") -> PASS | M11: =IF(E11+H11=D11,"PASS","FAIL") -> PASS | N11: =IF(C11=E11+F11+G11,"PASS","FAIL") -> PASS
A12: CHATGPT | B12: S2 | C12: =COUNTIFS('04_MATCHING'!$B$2:$B$1026,$A12,'04_MATCHING'!$C$2:$C$1026,$B12) -> 60 | D12: =COUNTIFS('02_REFERENCE'!$B$2:$B$99,$B12,'02_REFERENCE'!$S$2:$S$99,"YES") -> 33 | E12: =COUNTIFS('04_MATCHING'!$B$2:$B$1026,$A12,'04_MATCHING'!$C$2:$C$1026,$B12,'04_MATCHING'!$H$2:$H$1026,"Primary TP") -> 18 | F12: =COUNTIFS('04_MATCHING'!$B$2:$B$1026,$A12,'04_MATCHING'!$C$2:$C$1026,$B12,'04_MATCHING'!$H$2:$H$1026,"False Positive") -> 18 | G12: =COUNTIFS('04_MATCHING'!$B$2:$B$1026,$A12,'04_MATCHING'!$C$2:$C$1026,$B12,'04_MATCHING'!$H$2:$H$1026,"Duplicate") -> 24 | H12: =D12-E12 -> 15 | I12: =IFERROR(E12/(E12+F12),"") -> 0.5 | J12: =IFERROR(E12/D12,"") -> 0.54545455 | K12: =IFERROR(2*I12*J12/(I12+J12),"") -> 0.52173913 | L12: =IF(E12<=D12,"PASS","FAIL") -> PASS | M12: =IF(E12+H12=D12,"PASS","FAIL") -> PASS | N12: =IF(C12=E12+F12+G12,"PASS","FAIL") -> PASS
A13: CHATGPT | B13: S3 | C13: =COUNTIFS('04_MATCHING'!$B$2:$B$1026,$A13,'04_MATCHING'!$C$2:$C$1026,$B13) -> 49 | D13: =COUNTIFS('02_REFERENCE'!$B$2:$B$99,$B13,'02_REFERENCE'!$S$2:$S$99,"YES") -> 33 | E13: =COUNTIFS('04_MATCHING'!$B$2:$B$1026,$A13,'04_MATCHING'!$C$2:$C$1026,$B13,'04_MATCHING'!$H$2:$H$1026,"Primary TP") -> 16 | F13: =COUNTIFS('04_MATCHING'!$B$2:$B$1026,$A13,'04_MATCHING'!$C$2:$C$1026,$B13,'04_MATCHING'!$H$2:$H$1026,"False Positive") -> 22 | G13: =COUNTIFS('04_MATCHING'!$B$2:$B$1026,$A13,'04_MATCHING'!$C$2:$C$1026,$B13,'04_MATCHING'!$H$2:$H$1026,"Duplicate") -> 11 | H13: =D13-E13 -> 17 | I13: =IFERROR(E13/(E13+F13),"") -> 0.42105263 | J13: =IFERROR(E13/D13,"") -> 0.48484848 | K13: =IFERROR(2*I13*J13/(I13+J13),"") -> 0.45070423 | L13: =IF(E13<=D13,"PASS","FAIL") -> PASS | M13: =IF(E13+H13=D13,"PASS","FAIL") -> PASS | N13: =IF(C13=E13+F13+G13,"PASS","FAIL") -> PASS
A14: OLLAMA | B14: S1 | C14: =COUNTIFS('04_MATCHING'!$B$2:$B$1026,$A14,'04_MATCHING'!$C$2:$C$1026,$B14) -> 40 | D14: =COUNTIFS('02_REFERENCE'!$B$2:$B$99,$B14,'02_REFERENCE'!$S$2:$S$99,"YES") -> 32 | E14: =COUNTIFS('04_MATCHING'!$B$2:$B$1026,$A14,'04_MATCHING'!$C$2:$C$1026,$B14,'04_MATCHING'!$H$2:$H$1026,"Primary TP") -> 6 | F14: =COUNTIFS('04_MATCHING'!$B$2:$B$1026,$A14,'04_MATCHING'!$C$2:$C$1026,$B14,'04_MATCHING'!$H$2:$H$1026,"False Positive") -> 19 | G14: =COUNTIFS('04_MATCHING'!$B$2:$B$1026,$A14,'04_MATCHING'!$C$2:$C$1026,$B14,'04_MATCHING'!$H$2:$H$1026,"Duplicate") -> 15 | H14: =D14-E14 -> 26 | I14: =IFERROR(E14/(E14+F14),"") -> 0.24 | J14: =IFERROR(E14/D14,"") -> 0.1875 | K14: =IFERROR(2*I14*J14/(I14+J14),"") -> 0.21052632 | L14: =IF(E14<=D14,"PASS","FAIL") -> PASS | M14: =IF(E14+H14=D14,"PASS","FAIL") -> PASS | N14: =IF(C14=E14+F14+G14,"PASS","FAIL") -> PASS
A15: OLLAMA | B15: S2 | C15: =COUNTIFS('04_MATCHING'!$B$2:$B$1026,$A15,'04_MATCHING'!$C$2:$C$1026,$B15) -> 28 | D15: =COUNTIFS('02_REFERENCE'!$B$2:$B$99,$B15,'02_REFERENCE'!$S$2:$S$99,"YES") -> 33 | E15: =COUNTIFS('04_MATCHING'!$B$2:$B$1026,$A15,'04_MATCHING'!$C$2:$C$1026,$B15,'04_MATCHING'!$H$2:$H$1026,"Primary TP") -> 7 | F15: =COUNTIFS('04_MATCHING'!$B$2:$B$1026,$A15,'04_MATCHING'!$C$2:$C$1026,$B15,'04_MATCHING'!$H$2:$H$1026,"False Positive") -> 15 | G15: =COUNTIFS('04_MATCHING'!$B$2:$B$1026,$A15,'04_MATCHING'!$C$2:$C$1026,$B15,'04_MATCHING'!$H$2:$H$1026,"Duplicate") -> 6 | H15: =D15-E15 -> 26 | I15: =IFERROR(E15/(E15+F15),"") -> 0.31818182 | J15: =IFERROR(E15/D15,"") -> 0.21212121 | K15: =IFERROR(2*I15*J15/(I15+J15),"") -> 0.25454545 | L15: =IF(E15<=D15,"PASS","FAIL") -> PASS | M15: =IF(E15+H15=D15,"PASS","FAIL") -> PASS | N15: =IF(C15=E15+F15+G15,"PASS","FAIL") -> PASS
A16: OLLAMA | B16: S3 | C16: =COUNTIFS('04_MATCHING'!$B$2:$B$1026,$A16,'04_MATCHING'!$C$2:$C$1026,$B16) -> 24 | D16: =COUNTIFS('02_REFERENCE'!$B$2:$B$99,$B16,'02_REFERENCE'!$S$2:$S$99,"YES") -> 33 | E16: =COUNTIFS('04_MATCHING'!$B$2:$B$1026,$A16,'04_MATCHING'!$C$2:$C$1026,$B16,'04_MATCHING'!$H$2:$H$1026,"Primary TP") -> 7 | F16: =COUNTIFS('04_MATCHING'!$B$2:$B$1026,$A16,'04_MATCHING'!$C$2:$C$1026,$B16,'04_MATCHING'!$H$2:$H$1026,"False Positive") -> 12 | G16: =COUNTIFS('04_MATCHING'!$B$2:$B$1026,$A16,'04_MATCHING'!$C$2:$C$1026,$B16,'04_MATCHING'!$H$2:$H$1026,"Duplicate") -> 5 | H16: =D16-E16 -> 26 | I16: =IFERROR(E16/(E16+F16),"") -> 0.36842105 | J16: =IFERROR(E16/D16,"") -> 0.21212121 | K16: =IFERROR(2*I16*J16/(I16+J16),"") -> 0.26923077 | L16: =IF(E16<=D16,"PASS","FAIL") -> PASS | M16: =IF(E16+H16=D16,"PASS","FAIL") -> PASS | N16: =IF(C16=E16+F16+G16,"PASS","FAIL") -> PASS
... A19: THREMOLIA | B19: S3 | C19: =COUNTIFS('04_MATCHING'!$B$2:$B$1026,$A19,'04_MATCHING'!$C$2:$C$1026,$B19) -> 117 | D19: =COUNTIFS('02_REFERENCE'!$B$2:$B$99,$B19,'02_REFERENCE'!$S$2:$S$99,"YES") -> 33 | E19: =COUNTIFS('04_MATCHING'!$B$2:$B$1026,$A19,'04_MATCHING'!$C$2:$C$1026,$B19,'04_MATCHING'!$H$2:$H$1026,"Primary TP") -> 20 | F19: =COUNTIFS('04_MATCHING'!$B$2:$B$1026,$A19,'04_MATCHING'!$C$2:$C$1026,$B19,'04_MATCHING'!$H$2:$H$1026,"False Positive") -> 43 | G19: =COUNTIFS('04_MATCHING'!$B$2:$B$1026,$A19,'04_MATCHING'!$C$2:$C$1026,$B19,'04_MATCHING'!$H$2:$H$1026,"Duplicate") -> 54 | H19: =D19-E19 -> 13 | I19: =IFERROR(E19/(E19+F19),"") -> 0.31746032 | J19: =IFERROR(E19/D19,"") -> 0.60606061 | K19: =IFERROR(2*I19*J19/(I19+J19),"") -> 0.41666667 | L19: =IF(E19<=D19,"PASS","FAIL") -> PASS | M19: =IF(E19+H19=D19,"PASS","FAIL") -> PASS | N19: =IF(C19=E19+F19+G19,"PASS","FAIL") -> PASS
A20: TOTAL | B20: All | C20: =SUM(C5:C19) -> 1025 | D20: =SUM(D5:D19) -> 490 | E20: =SUM(E5:E19) -> 188 | F20: =SUM(F5:F19) -> 498 | G20: =SUM(G5:G19) -> 339 | H20: =SUM(H5:H19) -> 302 | I20: =IFERROR(E20/(E20+F20),"") -> 0.27405248 | J20: =IFERROR(E20/D20,"") -> 0.38367347 | K20: =IFERROR(2*I20*J20/(I20+J20),"") -> 0.31972789 | N20: =IF(C20=E20+F20+G20,"PASS","FAIL") -> PASS
A22: Per-reference coverage grid (98 reference threats x 5 approaches). Covered = a Primary TP exists for that approach/scenario; FN = no Primary TP.
A23: Scenario | B23: Reference Threat ID | C23: Threat Name | D23: OWASP | E23: TMT | F23: CHATGPT | G23: OLLAMA | H23: THREMOLIA | I23: Covered by # approaches
A24: S1 | B24: S1-RT-001 | C24: Online brute-force password guessing | D24: =IF(COUNTIFS('04_MATCHING'!$B$2:$B$1026,"OWASP",'04_MATCHING'!$C$2:$C$1026,$A24,'04_MATCHING'!$G$2:$G$1026,$B24,'04_MATCHING'!$H$2:$H$1026,"Primary TP")>0,"Covered","FN") -> FN | E24: =IF(COUNTIFS('04_MATCHING'!$B$2:$B$1026,"TMT",'04_MATCHING'!$C$2:$C$1026,$A24,'04_MATCHING'!$G$2:$G$1026,$B24,'04_MATCHING'!$H$2:$H$1026,"Primary TP")>0,"Covered","FN") -> FN | F24: =IF(COUNTIFS('04_MATCHING'!$B$2:$B$1026,"CHATGPT",'04_MATCHING'!$C$2:$C$1026,$A24,'04_MATCHING'!$G$2:$G$1026,$B24,'04_MATCHING'!$H$2:$H$1026,"Primary TP")>0,"Covered","FN") -> Covered | G24: =IF(COUNTIFS('04_MATCHING'!$B$2:$B$1026,"OLLAMA",'04_MATCHING'!$C$2:$C$1026,$A24,'04_MATCHING'!$G$2:$G$1026,$B24,'04_MATCHING'!$H$2:$H$1026,"Primary TP")>0,"Covered","FN") -> FN | H24: =IF(COUNTIFS('04_MATCHING'!$B$2:$B$1026,"THREMOLIA",'04_MATCHING'!$C$2:$C$1026,$A24,'04_MATCHING'!$G$2:$G$1026,$B24,'04_MATCHING'!$H$2:$H$1026,"Primary TP")>0,"Covered","FN") -> FN | I24: =COUNTIF($D24:$H24,"Covered") -> 1
A25: S1 | B25: S1-RT-002 | C25: Credential stuffing using breached credential corpora | D25: =IF(COUNTIFS('04_MATCHING'!$B$2:$B$1026,"OWASP",'04_MATCHING'!$C$2:$C$1026,$A25,'04_MATCHING'!$G$2:$G$1026,$B25,'04_MATCHING'!$H$2:$H$1026,"Primary TP")>0,"Covered","FN") -> Covered | E25: =IF(COUNTIFS('04_MATCHING'!$B$2:$B$1026,"TMT",'04_MATCHING'!$C$2:$C$1026,$A25,'04_MATCHING'!$G$2:$G$1026,$B25,'04_MATCHING'!$H$2:$H$1026,"Primary TP")>0,"Covered","FN") -> FN | F25: =IF(COUNTIFS('04_MATCHING'!$B$2:$B$1026,"CHATGPT",'04_MATCHING'!$C$2:$C$1026,$A25,'04_MATCHING'!$G$2:$G$1026,$B25,'04_MATCHING'!$H$2:$H$1026,"Primary TP")>0,"Covered","FN") -> FN | G25: =IF(COUNTIFS('04_MATCHING'!$B$2:$B$1026,"OLLAMA",'04_MATCHING'!$C$2:$C$1026,$A25,'04_MATCHING'!$G$2:$G$1026,$B25,'04_MATCHING'!$H$2:$H$1026,"Primary TP")>0,"Covered","FN") -> FN | H25: =IF(COUNTIFS('04_MATCHING'!$B$2:$B$1026,"THREMOLIA",'04_MATCHING'!$C$2:$C$1026,$A25,'04_MATCHING'!$G$2:$G$1026,$B25,'04_MATCHING'!$H$2:$H$1026,"Primary TP")>0,"Covered","FN") -> Covered | I25: =COUNTIF($D25:$H25,"Covered") -> 2
A26: S1 | B26: S1-RT-003 | C26: Username and account enumeration | D26: =IF(COUNTIFS('04_MATCHING'!$B$2:$B$1026,"OWASP",'04_MATCHING'!$C$2:$C$1026,$A26,'04_MATCHING'!$G$2:$G$1026,$B26,'04_MATCHING'!$H$2:$H$1026,"Primary TP")>0,"Covered","FN") -> FN | E26: =IF(COUNTIFS('04_MATCHING'!$B$2:$B$1026,"TMT",'04_MATCHING'!$C$2:$C$1026,$A26,'04_MATCHING'!$G$2:$G$1026,$B26,'04_MATCHING'!$H$2:$H$1026,"Primary TP")>0,"Covered","FN") -> FN | F26: =IF(COUNTIFS('04_MATCHING'!$B$2:$B$1026,"CHATGPT",'04_MATCHING'!$C$2:$C$1026,$A26,'04_MATCHING'!$G$2:$G$1026,$B26,'04_MATCHING'!$H$2:$H$1026,"Primary TP")>0,"Covered","FN") -> Covered | G26: =IF(COUNTIFS('04_MATCHING'!$B$2:$B$1026,"OLLAMA",'04_MATCHING'!$C$2:$C$1026,$A26,'04_MATCHING'!$G$2:$G$1026,$B26,'04_MATCHING'!$H$2:$H$1026,"Primary TP")>0,"Covered","FN") -> FN | H26: =IF(COUNTIFS('04_MATCHING'!$B$2:$B$1026,"THREMOLIA",'04_MATCHING'!$C$2:$C$1026,$A26,'04_MATCHING'!$G$2:$G$1026,$B26,'04_MATCHING'!$H$2:$H$1026,"Primary TP")>0,"Covered","FN") -> Covered | I26: =COUNTIF($D26:$H26,"Covered") -> 2
A27: S1 | B27: S1-RT-004 | C27: Authentication bypass through flawed authentication logic | D27: =IF(COUNTIFS('04_MATCHING'!$B$2:$B$1026,"OWASP",'04_MATCHING'!$C$2:$C$1026,$A27,'04_MATCHING'!$G$2:$G$1026,$B27,'04_MATCHING'!$H$2:$H$1026,"Primary TP")>0,"Covered","FN") -> FN | E27: =IF(COUNTIFS('04_MATCHING'!$B$2:$B$1026,"TMT",'04_MATCHING'!$C$2:$C$1026,$A27,'04_MATCHING'!$G$2:$G$1026,$B27,'04_MATCHING'!$H$2:$H$1026,"Primary TP")>0,"Covered","FN") -> FN | F27: =IF(COUNTIFS('04_MATCHING'!$B$2:$B$1026,"CHATGPT",'04_MATCHING'!$C$2:$C$1026,$A27,'04_MATCHING'!$G$2:$G$1026,$B27,'04_MATCHING'!$H$2:$H$1026,"Primary TP")>0,"Covered","FN") -> Covered | G27: =IF(COUNTIFS('04_MATCHING'!$B$2:$B$1026,"OLLAMA",'04_MATCHING'!$C$2:$C$1026,$A27,'04_MATCHING'!$G$2:$G$1026,$B27,'04_MATCHING'!$H$2:$H$1026,"Primary TP")>0,"Covered","FN") -> Covered | H27: =IF(COUNTIFS('04_MATCHING'!$B$2:$B$1026,"THREMOLIA",'04_MATCHING'!$C$2:$C$1026,$A27,'04_MATCHING'!$G$2:$G$1026,$B27,'04_MATCHING'!$H$2:$H$1026,"Primary TP")>0,"Covered","FN") -> Covered | I27: =COUNTIF($D27:$H27,"Covered") -> 3
A28: S1 | B28: S1-RT-006 | C28: Exposure of credentials in transit on the authentication paths | D28: =IF(COUNTIFS('04_MATCHING'!$B$2:$B$1026,"OWASP",'04_MATCHING'!$C$2:$C$1026,$A28,'04_MATCHING'!$G$2:$G$1026,$B28,'04_MATCHING'!$H$2:$H$1026,"Primary TP")>0,"Covered","FN") -> FN | E28: =IF(COUNTIFS('04_MATCHING'!$B$2:$B$1026,"TMT",'04_MATCHING'!$C$2:$C$1026,$A28,'04_MATCHING'!$G$2:$G$1026,$B28,'04_MATCHING'!$H$2:$H$1026,"Primary TP")>0,"Covered","FN") -> FN | F28: =IF(COUNTIFS('04_MATCHING'!$B$2:$B$1026,"CHATGPT",'04_MATCHING'!$C$2:$C$1026,$A28,'04_MATCHING'!$G$2:$G$1026,$B28,'04_MATCHING'!$H$2:$H$1026,"Primary TP")>0,"Covered","FN") -> FN | G28: =IF(COUNTIFS('04_MATCHING'!$B$2:$B$1026,"OLLAMA",'04_MATCHING'!$C$2:$C$1026,$A28,'04_MATCHING'!$G$2:$G$1026,$B28,'04_MATCHING'!$H$2:$H$1026,"Primary TP")>0,"Covered","FN") -> FN | H28: =IF(COUNTIFS('04_MATCHING'!$B$2:$B$1026,"THREMOLIA",'04_MATCHING'!$C$2:$C$1026,$A28,'04_MATCHING'!$G$2:$G$1026,$B28,'04_MATCHING'!$H$2:$H$1026,"Primary TP")>0,"Covered","FN") -> Covered | I28: =COUNTIF($D28:$H28,"Covered") -> 1
A29: S1 | B29: S1-RT-008 | C29: Injection into the credential verification exchange | D29: =IF(COUNTIFS('04_MATCHING'!$B$2:$B$1026,"OWASP",'04_MATCHING'!$C$2:$C$1026,$A29,'04_MATCHING'!$G$2:$G$1026,$B29,'04_MATCHING'!$H$2:$H$1026,"Primary TP")>0,"Covered","FN") -> FN | E29: =IF(COUNTIFS('04_MATCHING'!$B$2:$B$1026,"TMT",'04_MATCHING'!$C$2:$C$1026,$A29,'04_MATCHING'!$G$2:$G$1026,$B29,'04_MATCHING'!$H$2:$H$1026,"Primary TP")>0,"Covered","FN") -> Covered | F29: =IF(COUNTIFS('04_MATCHING'!$B$2:$B$1026,"CHATGPT",'04_MATCHING'!$C$2:$C$1026,$A29,'04_MATCHING'!$G$2:$G$1026,$B29,'04_MATCHING'!$H$2:$H$1026,"Primary TP")>0,"Covered","FN") -> FN | G29: =IF(COUNTIFS('04_MATCHING'!$B$2:$B$1026,"OLLAMA",'04_MATCHING'!$C$2:$C$1026,$A29,'04_MATCHING'!$G$2:$G$1026,$B29,'04_MATCHING'!$H$2:$H$1026,"Primary TP")>0,"Covered","FN") -> FN | H29: =IF(COUNTIFS('04_MATCHING'!$B$2:$B$1026,"THREMOLIA",'04_MATCHING'!$C$2:$C$1026,$A29,'04_MATCHING'!$G$2:$G$1026,$B29,'04_MATCHING'!$H$2:$H$1026,"Primary TP")>0,"Covered","FN") -> Covered | I29: =COUNTIF($D29:$H29,"Covered") -> 2
A30: S1 | B30: S1-RT-009 | C30: Excessive database access scope across the application-to-database boundary | D30: =IF(COUNTIFS('04_MATCHING'!$B$2:$B$1026,"OWASP",'04_MATCHING'!$C$2:$C$1026,$A30,'04_MATCHING'!$G$2:$G$1026,$B30,'04_MATCHING'!$H$2:$H$1026,"Primary TP")>0,"Covered","FN") -> FN | E30: =IF(COUNTIFS('04_MATCHING'!$B$2:$B$1026,"TMT",'04_MATCHING'!$C$2:$C$1026,$A30,'04_MATCHING'!$G$2:$G$1026,$B30,'04_MATCHING'!$H$2:$H$1026,"Primary TP")>0,"Covered","FN") -> FN | F30: =IF(COUNTIFS('04_MATCHING'!$B$2:$B$1026,"CHATGPT",'04_MATCHING'!$C$2:$C$1026,$A30,'04_MATCHING'!$G$2:$G$1026,$B30,'04_MATCHING'!$H$2:$H$1026,"Primary TP")>0,"Covered","FN") -> FN | G30: =IF(COUNTIFS('04_MATCHING'!$B$2:$B$1026,"OLLAMA",'04_MATCHING'!$C$2:$C$1026,$A30,'04_MATCHING'!$G$2:$G$1026,$B30,'04_MATCHING'!$H$2:$H$1026,"Primary TP")>0,"Covered","FN") -> FN | H30: =IF(COUNTIFS('04_MATCHING'!$B$2:$B$1026,"THREMOLIA",'04_MATCHING'!$C$2:$C$1026,$A30,'04_MATCHING'!$G$2:$G$1026,$B30,'04_MATCHING'!$H$2:$H$1026,"Primary TP")>0,"Covered","FN") -> FN | I30: =COUNTIF($D30:$H30,"Covered") -> 0
A31: S1 | B31: S1-RT-010 | C31: Broken object-level authorisation on account data | D31: =IF(COUNTIFS('04_MATCHING'!$B$2:$B$1026,"OWASP",'04_MATCHING'!$C$2:$C$1026,$A31,'04_MATCHING'!$G$2:$G$1026,$B31,'04_MATCHING'!$H$2:$H$1026,"Primary TP")>0,"Covered","FN") -> FN | E31: =IF(COUNTIFS('04_MATCHING'!$B$2:$B$1026,"TMT",'04_MATCHING'!$C$2:$C$1026,$A31,'04_MATCHING'!$G$2:$G$1026,$B31,'04_MATCHING'!$H$2:$H$1026,"Primary TP")>0,"Covered","FN") -> FN | F31: =IF(COUNTIFS('04_MATCHING'!$B$2:$B$1026,"CHATGPT",'04_MATCHING'!$C$2:$C$1026,$A31,'04_MATCHING'!$G$2:$G$1026,$B31,'04_MATCHING'!$H$2:$H$1026,"Primary TP")>0,"Covered","FN") -> FN | G31: =IF(COUNTIFS('04_MATCHING'!$B$2:$B$1026,"OLLAMA",'04_MATCHING'!$C$2:$C$1026,$A31,'04_MATCHING'!$G$2:$G$1026,$B31,'04_MATCHING'!$H$2:$H$1026,"Primary TP")>0,"Covered","FN") -> FN | H31: =IF(COUNTIFS('04_MATCHING'!$B$2:$B$1026,"THREMOLIA",'04_MATCHING'!$C$2:$C$1026,$A31,'04_MATCHING'!$G$2:$G$1026,$B31,'04_MATCHING'!$H$2:$H$1026,"Primary TP")>0,"Covered","FN") -> FN | I31: =COUNTIF($D31:$H31,"Covered") -> 0
A32: S1 | B32: S1-RT-011 | C32: Missing authorisation on the chatbot interface | D32: =IF(COUNTIFS('04_MATCHING'!$B$2:$B$1026,"OWASP",'04_MATCHING'!$C$2:$C$1026,$A32,'04_MATCHING'!$G$2:$G$1026,$B32,'04_MATCHING'!$H$2:$H$1026,"Primary TP")>0,"Covered","FN") -> FN | E32: =IF(COUNTIFS('04_MATCHING'!$B$2:$B$1026,"TMT",'04_MATCHING'!$C$2:$C$1026,$A32,'04_MATCHING'!$G$2:$G$1026,$B32,'04_MATCHING'!$H$2:$H$1026,"Primary TP")>0,"Covered","FN") -> FN | F32: =IF(COUNTIFS('04_MATCHING'!$B$2:$B$1026,"CHATGPT",'04_MATCHING'!$C$2:$C$1026,$A32,'04_MATCHING'!$G$2:$G$1026,$B32,'04_MATCHING'!$H$2:$H$1026,"Primary TP")>0,"Covered","FN") -> FN | G32: =IF(COUNTIFS('04_MATCHING'!$B$2:$B$1026,"OLLAMA",'04_MATCHING'!$C$2:$C$1026,$A32,'04_MATCHING'!$G$2:$G$1026,$B32,'04_MATCHING'!$H$2:$H$1026,"Primary TP")>0,"Covered","FN") -> FN | H32: =IF(COUNTIFS('04_MATCHING'!$B$2:$B$1026,"THREMOLIA",'04_MATCHING'!$C$2:$C$1026,$A32,'04_MATCHING'!$G$2:$G$1026,$B32,'04_MATCHING'!$H$2:$H$1026,"Primary TP")>0,"Covered","FN") -> Covered | I32: =COUNTIF($D32:$H32,"Covered") -> 1
A33: S1 | B33: S1-RT-012 | C33: Cross-user context leakage between chatbot sessions | D33: =IF(COUNTIFS('04_MATCHING'!$B$2:$B$1026,"OWASP",'04_MATCHING'!$C$2:$C$1026,$A33,'04_MATCHING'!$G$2:$G$1026,$B33,'04_MATCHING'!$H$2:$H$1026,"Primary TP")>0,"Covered","FN") -> FN | E33: =IF(COUNTIFS('04_MATCHING'!$B$2:$B$1026,"TMT",'04_MATCHING'!$C$2:$C$1026,$A33,'04_MATCHING'!$G$2:$G$1026,$B33,'04_MATCHING'!$H$2:$H$1026,"Primary TP")>0,"Covered","FN") -> FN | F33: =IF(COUNTIFS('04_MATCHING'!$B$2:$B$1026,"CHATGPT",'04_MATCHING'!$C$2:$C$1026,$A33,'04_MATCHING'!$G$2:$G$1026,$B33,'04_MATCHING'!$H$2:$H$1026,"Primary TP")>0,"Covered","FN") -> FN | G33: =IF(COUNTIFS('04_MATCHING'!$B$2:$B$1026,"OLLAMA",'04_MATCHING'!$C$2:$C$1026,$A33,'04_MATCHING'!$G$2:$G$1026,$B33,'04_MATCHING'!$H$2:$H$1026,"Primary TP")>0,"Covered","FN") -> FN | H33: =IF(COUNTIFS('04_MATCHING'!$B$2:$B$1026,"THREMOLIA",'04_MATCHING'!$C$2:$C$1026,$A33,'04_MATCHING'!$G$2:$G$1026,$B33,'04_MATCHING'!$H$2:$H$1026,"Primary TP")>0,"Covered","FN") -> Covered | I33: =COUNTIF($D33:$H33,"Covered") -> 1
A34: S1 | B34: S1-RT-013 | C34: Session fixation on the authentication flow | D34: =IF(COUNTIFS('04_MATCHING'!$B$2:$B$1026,"OWASP",'04_MATCHING'!$C$2:$C$1026,$A34,'04_MATCHING'!$G$2:$G$1026,$B34,'04_MATCHING'!$H$2:$H$1026,"Primary TP")>0,"Covered","FN") -> FN | E34: =IF(COUNTIFS('04_MATCHING'!$B$2:$B$1026,"TMT",'04_MATCHING'!$C$2:$C$1026,$A34,'04_MATCHING'!$G$2:$G$1026,$B34,'04_MATCHING'!$H$2:$H$1026,"Primary TP")>0,"Covered","FN") -> FN | F34: =IF(COUNTIFS('04_MATCHING'!$B$2:$B$1026,"CHATGPT",'04_MATCHING'!$C$2:$C$1026,$A34,'04_MATCHING'!$G$2:$G$1026,$B34,'04_MATCHING'!$H$2:$H$1026,"Primary TP")>0,"Covered","FN") -> FN | G34: =IF(COUNTIFS('04_MATCHING'!$B$2:$B$1026,"OLLAMA",'04_MATCHING'!$C$2:$C$1026,$A34,'04_MATCHING'!$G$2:$G$1026,$B34,'04_MATCHING'!$H$2:$H$1026,"Primary TP")>0,"Covered","FN") -> FN | H34: =IF(COUNTIFS('04_MATCHING'!$B$2:$B$1026,"THREMOLIA",'04_MATCHING'!$C$2:$C$1026,$A34,'04_MATCHING'!$G$2:$G$1026,$B34,'04_MATCHING'!$H$2:$H$1026,"Primary TP")>0,"Covered","FN") -> Covered | I34: =COUNTIF($D34:$H34,"Covered") -> 1
A35: S1 | B35: S1-RT-014 | C35: Session token theft at the delivery and persistence crossings | D35: =IF(COUNTIFS('04_MATCHING'!$B$2:$B$1026,"OWASP",'04_MATCHING'!$C$2:$C$1026,$A35,'04_MATCHING'!$G$2:$G$1026,$B35,'04_MATCHING'!$H$2:$H$1026,"Primary TP")>0,"Covered","FN") -> Covered | E35: =IF(COUNTIFS('04_MATCHING'!$B$2:$B$1026,"TMT",'04_MATCHING'!$C$2:$C$1026,$A35,'04_MATCHING'!$G$2:$G$1026,$B35,'04_MATCHING'!$H$2:$H$1026,"Primary TP")>0,"Covered","FN") -> Covered | F35: =IF(COUNTIFS('04_MATCHING'!$B$2:$B$1026,"CHATGPT",'04_MATCHING'!$C$2:$C$1026,$A35,'04_MATCHING'!$G$2:$G$1026,$B35,'04_MATCHING'!$H$2:$H$1026,"Primary TP")>0,"Covered","FN") -> Covered | G35: =IF(COUNTIFS('04_MATCHING'!$B$2:$B$1026,"OLLAMA",'04_MATCHING'!$C$2:$C$1026,$A35,'04_MATCHING'!$G$2:$G$1026,$B35,'04_MATCHING'!$H$2:$H$1026,"Primary TP")>0,"Covered","FN") -> FN | H35: =IF(COUNTIFS('04_MATCHING'!$B$2:$B$1026,"THREMOLIA",'04_MATCHING'!$C$2:$C$1026,$A35,'04_MATCHING'!$G$2:$G$1026,$B35,'04_MATCHING'!$H$2:$H$1026,"Primary TP")>0,"Covered","FN") -> Covered | I35: =COUNTIF($D35:$H35,"Covered") -> 4
... A121: S3 | B121: S3-RT-034 | C121: Profile updates performed without valid recovery authorisation | D121: =IF(COUNTIFS('04_MATCHING'!$B$2:$B$1026,"OWASP",'04_MATCHING'!$C$2:$C$1026,$A121,'04_MATCHING'!$G$2:$G$1026,$B121,'04_MATCHING'!$H$2:$H$1026,"Primary TP")>0,"Covered","FN") -> FN | E121: =IF(COUNTIFS('04_MATCHING'!$B$2:$B$1026,"TMT",'04_MATCHING'!$C$2:$C$1026,$A121,'04_MATCHING'!$G$2:$G$1026,$B121,'04_MATCHING'!$H$2:$H$1026,"Primary TP")>0,"Covered","FN") -> FN | F121: =IF(COUNTIFS('04_MATCHING'!$B$2:$B$1026,"CHATGPT",'04_MATCHING'!$C$2:$C$1026,$A121,'04_MATCHING'!$G$2:$G$1026,$B121,'04_MATCHING'!$H$2:$H$1026,"Primary TP")>0,"Covered","FN") -> Covered | G121: =IF(COUNTIFS('04_MATCHING'!$B$2:$B$1026,"OLLAMA",'04_MATCHING'!$C$2:$C$1026,$A121,'04_MATCHING'!$G$2:$G$1026,$B121,'04_MATCHING'!$H$2:$H$1026,"Primary TP")>0,"Covered","FN") -> Covered | H121: =IF(COUNTIFS('04_MATCHING'!$B$2:$B$1026,"THREMOLIA",'04_MATCHING'!$C$2:$C$1026,$A121,'04_MATCHING'!$G$2:$G$1026,$B121,'04_MATCHING'!$H$2:$H$1026,"Primary TP")>0,"Covered","FN") -> FN | I121: =COUNTIF($D121:$H121,"Covered") -> 2

Sheet 06_METRICS
A1: Precision / Recall / F1
A2: Precision = TP/(TP+FP) using Primary TP (one-to-one rule, per explicit specification). A supplementary "per-finding precision incl. duplicates" = (PrimaryTP+Duplicates)/Generated is shown for interpretation. 95% Wilson CIs are exploratory (small n).
A4: Approach | B4: Scenario | C4: Generated | D4: Primary TP | E4: Duplicates | F4: FP | G4: Reference | H4: FN | I4: Precision (Primary) | J4: Recall/Coverage | K4: F1 | L4: Per-finding Precision (incl. dup.) | M4: 95%CI Prec (lower) | N4: 95%CI Prec (upper) | O4: 95%CI Rec (lower) | P4: 95%CI Rec (upper)
A5: OWASP | B5: S1 | C5: =COUNTIFS('04_MATCHING'!$B$2:$B$1026,$A5,'04_MATCHING'!$C$2:$C$1026,$B5) -> 38 | D5: =COUNTIFS('04_MATCHING'!$B$2:$B$1026,$A5,'04_MATCHING'!$C$2:$C$1026,$B5,'04_MATCHING'!$H$2:$H$1026,"Primary TP") -> 6 | E5: =COUNTIFS('04_MATCHING'!$B$2:$B$1026,$A5,'04_MATCHING'!$C$2:$C$1026,$B5,'04_MATCHING'!$H$2:$H$1026,"Duplicate") -> 6 | F5: =COUNTIFS('04_MATCHING'!$B$2:$B$1026,$A5,'04_MATCHING'!$C$2:$C$1026,$B5,'04_MATCHING'!$H$2:$H$1026,"False Positive") -> 26 | G5: =COUNTIFS('02_REFERENCE'!$B$2:$B$99,$B5,'02_REFERENCE'!$S$2:$S$99,"YES") -> 32 | H5: =G5-D5 -> 26 | I5: =IFERROR(D5/(D5+F5),"") -> 0.1875 | J5: =IFERROR(D5/G5,"") -> 0.1875 | K5: =IFERROR(2*I5*J5/(I5+J5),"") -> 0.1875 | L5: =IFERROR((D5+E5)/C5,"") -> 0.31578947 | M5: =IFERROR((($D5/($D5+$F5))+1.96^2/(2*($D5+$F5))-1.96*SQRT(($D5/($D5+$F5))*(1-$D5/($D5+$F5))/($D5+$F5)+1.96^2/(4*($D5+$F5)^2)))/(1+1.96^2/($D5+$F5)),"") -> 0.088894239 | N5: =IFERROR((($D5/($D5+$F5))+1.96^2/(2*($D5+$F5))+1.96*SQRT(($D5/($D5+$F5))*(1-$D5/($D5+$F5))/($D5+$F5)+1.96^2/(4*($D5+$F5)^2)))/(1+1.96^2/($D5+$F5)),"") -> 0.35309496 | O5: =IFERROR((($D5/$G5)+1.96^2/(2*$G5)-1.96*SQRT(($D5/$G5)*(1-$D5/$G5)/$G5+1.96^2/(4*$G5^2)))/(1+1.96^2/$G5),"") -> 0.088894239 | P5: =IFERROR((($D5/$G5)+1.96^2/(2*$G5)+1.96*SQRT(($D5/$G5)*(1-$D5/$G5)/$G5+1.96^2/(4*$G5^2)))/(1+1.96^2/$G5),"") -> 0.35309496
A6: OWASP | B6: S2 | C6: =COUNTIFS('04_MATCHING'!$B$2:$B$1026,$A6,'04_MATCHING'!$C$2:$C$1026,$B6) -> 39 | D6: =COUNTIFS('04_MATCHING'!$B$2:$B$1026,$A6,'04_MATCHING'!$C$2:$C$1026,$B6,'04_MATCHING'!$H$2:$H$1026,"Primary TP") -> 6 | E6: =COUNTIFS('04_MATCHING'!$B$2:$B$1026,$A6,'04_MATCHING'!$C$2:$C$1026,$B6,'04_MATCHING'!$H$2:$H$1026,"Duplicate") -> 6 | F6: =COUNTIFS('04_MATCHING'!$B$2:$B$1026,$A6,'04_MATCHING'!$C$2:$C$1026,$B6,'04_MATCHING'!$H$2:$H$1026,"False Positive") -> 27 | G6: =COUNTIFS('02_REFERENCE'!$B$2:$B$99,$B6,'02_REFERENCE'!$S$2:$S$99,"YES") -> 33 | H6: =G6-D6 -> 27 | I6: =IFERROR(D6/(D6+F6),"") -> 0.18181818 | J6: =IFERROR(D6/G6,"") -> 0.18181818 | K6: =IFERROR(2*I6*J6/(I6+J6),"") -> 0.18181818 | L6: =IFERROR((D6+E6)/C6,"") -> 0.30769231 | M6: =IFERROR((($D6/($D6+$F6))+1.96^2/(2*($D6+$F6))-1.96*SQRT(($D6/($D6+$F6))*(1-$D6/($D6+$F6))/($D6+$F6)+1.96^2/(4*($D6+$F6)^2)))/(1+1.96^2/($D6+$F6)),"") -> 0.086106512 | N6: =IFERROR((($D6/($D6+$F6))+1.96^2/(2*($D6+$F6))+1.96*SQRT(($D6/($D6+$F6))*(1-$D6/($D6+$F6))/($D6+$F6)+1.96^2/(4*($D6+$F6)^2)))/(1+1.96^2/($D6+$F6)),"") -> 0.34388567 | O6: =IFERROR((($D6/$G6)+1.96^2/(2*$G6)-1.96*SQRT(($D6/$G6)*(1-$D6/$G6)/$G6+1.96^2/(4*$G6^2)))/(1+1.96^2/$G6),"") -> 0.086106512 | P6: =IFERROR((($D6/$G6)+1.96^2/(2*$G6)+1.96*SQRT(($D6/$G6)*(1-$D6/$G6)/$G6+1.96^2/(4*$G6^2)))/(1+1.96^2/$G6),"") -> 0.34388567
A7: OWASP | B7: S3 | C7: =COUNTIFS('04_MATCHING'!$B$2:$B$1026,$A7,'04_MATCHING'!$C$2:$C$1026,$B7) -> 46 | D7: =COUNTIFS('04_MATCHING'!$B$2:$B$1026,$A7,'04_MATCHING'!$C$2:$C$1026,$B7,'04_MATCHING'!$H$2:$H$1026,"Primary TP") -> 7 | E7: =COUNTIFS('04_MATCHING'!$B$2:$B$1026,$A7,'04_MATCHING'!$C$2:$C$1026,$B7,'04_MATCHING'!$H$2:$H$1026,"Duplicate") -> 13 | F7: =COUNTIFS('04_MATCHING'!$B$2:$B$1026,$A7,'04_MATCHING'!$C$2:$C$1026,$B7,'04_MATCHING'!$H$2:$H$1026,"False Positive") -> 26 | G7: =COUNTIFS('02_REFERENCE'!$B$2:$B$99,$B7,'02_REFERENCE'!$S$2:$S$99,"YES") -> 33 | H7: =G7-D7 -> 26 | I7: =IFERROR(D7/(D7+F7),"") -> 0.21212121 | J7: =IFERROR(D7/G7,"") -> 0.21212121 | K7: =IFERROR(2*I7*J7/(I7+J7),"") -> 0.21212121 | L7: =IFERROR((D7+E7)/C7,"") -> 0.43478261 | M7: =IFERROR((($D7/($D7+$F7))+1.96^2/(2*($D7+$F7))-1.96*SQRT(($D7/($D7+$F7))*(1-$D7/($D7+$F7))/($D7+$F7)+1.96^2/(4*($D7+$F7)^2)))/(1+1.96^2/($D7+$F7)),"") -> 0.10675887 | N7: =IFERROR((($D7/($D7+$F7))+1.96^2/(2*($D7+$F7))+1.96*SQRT(($D7/($D7+$F7))*(1-$D7/($D7+$F7))/($D7+$F7)+1.96^2/(4*($D7+$F7)^2)))/(1+1.96^2/($D7+$F7)),"") -> 0.37751978 | O7: =IFERROR((($D7/$G7)+1.96^2/(2*$G7)-1.96*SQRT(($D7/$G7)*(1-$D7/$G7)/$G7+1.96^2/(4*$G7^2)))/(1+1.96^2/$G7),"") -> 0.10675887 | P7: =IFERROR((($D7/$G7)+1.96^2/(2*$G7)+1.96*SQRT(($D7/$G7)*(1-$D7/$G7)/$G7+1.96^2/(4*$G7^2)))/(1+1.96^2/$G7),"") -> 0.37751978
A8: TMT | B8: S1 | C8: =COUNTIFS('04_MATCHING'!$B$2:$B$1026,$A8,'04_MATCHING'!$C$2:$C$1026,$B8) -> 95 | D8: =COUNTIFS('04_MATCHING'!$B$2:$B$1026,$A8,'04_MATCHING'!$C$2:$C$1026,$B8,'04_MATCHING'!$H$2:$H$1026,"Primary TP") -> 9 | E8: =COUNTIFS('04_MATCHING'!$B$2:$B$1026,$A8,'04_MATCHING'!$C$2:$C$1026,$B8,'04_MATCHING'!$H$2:$H$1026,"Duplicate") -> 13 | F8: =COUNTIFS('04_MATCHING'!$B$2:$B$1026,$A8,'04_MATCHING'!$C$2:$C$1026,$B8,'04_MATCHING'!$H$2:$H$1026,"False Positive") -> 73 | G8: =COUNTIFS('02_REFERENCE'!$B$2:$B$99,$B8,'02_REFERENCE'!$S$2:$S$99,"YES") -> 32 | H8: =G8-D8 -> 23 | I8: =IFERROR(D8/(D8+F8),"") -> 0.1097561 | J8: =IFERROR(D8/G8,"") -> 0.28125 | K8: =IFERROR(2*I8*J8/(I8+J8),"") -> 0.15789474 | L8: =IFERROR((D8+E8)/C8,"") -> 0.23157895 | M8: =IFERROR((($D8/($D8+$F8))+1.96^2/(2*($D8+$F8))-1.96*SQRT(($D8/($D8+$F8))*(1-$D8/($D8+$F8))/($D8+$F8)+1.96^2/(4*($D8+$F8)^2)))/(1+1.96^2/($D8+$F8)),"") -> 0.058826479 | N8: =IFERROR((($D8/($D8+$F8))+1.96^2/(2*($D8+$F8))+1.96*SQRT(($D8/($D8+$F8))*(1-$D8/($D8+$F8))/($D8+$F8)+1.96^2/(4*($D8+$F8)^2)))/(1+1.96^2/($D8+$F8)),"") -> 0.19561426 | O8: =IFERROR((($D8/$G8)+1.96^2/(2*$G8)-1.96*SQRT(($D8/$G8)*(1-$D8/$G8)/$G8+1.96^2/(4*$G8^2)))/(1+1.96^2/$G8),"") -> 0.15564407 | P8: =IFERROR((($D8/$G8)+1.96^2/(2*$G8)+1.96*SQRT(($D8/$G8)*(1-$D8/$G8)/$G8+1.96^2/(4*$G8^2)))/(1+1.96^2/$G8),"") -> 0.45374837
A9: TMT | B9: S2 | C9: =COUNTIFS('04_MATCHING'!$B$2:$B$1026,$A9,'04_MATCHING'!$C$2:$C$1026,$B9) -> 89 | D9: =COUNTIFS('04_MATCHING'!$B$2:$B$1026,$A9,'04_MATCHING'!$C$2:$C$1026,$B9,'04_MATCHING'!$H$2:$H$1026,"Primary TP") -> 10 | E9: =COUNTIFS('04_MATCHING'!$B$2:$B$1026,$A9,'04_MATCHING'!$C$2:$C$1026,$B9,'04_MATCHING'!$H$2:$H$1026,"Duplicate") -> 14 | F9: =COUNTIFS('04_MATCHING'!$B$2:$B$1026,$A9,'04_MATCHING'!$C$2:$C$1026,$B9,'04_MATCHING'!$H$2:$H$1026,"False Positive") -> 65 | G9: =COUNTIFS('02_REFERENCE'!$B$2:$B$99,$B9,'02_REFERENCE'!$S$2:$S$99,"YES") -> 33 | H9: =G9-D9 -> 23 | I9: =IFERROR(D9/(D9+F9),"") -> 0.13333333 | J9: =IFERROR(D9/G9,"") -> 0.3030303 | K9: =IFERROR(2*I9*J9/(I9+J9),"") -> 0.18518519 | L9: =IFERROR((D9+E9)/C9,"") -> 0.26966292 | M9: =IFERROR((($D9/($D9+$F9))+1.96^2/(2*($D9+$F9))-1.96*SQRT(($D9/($D9+$F9))*(1-$D9/($D9+$F9))/($D9+$F9)+1.96^2/(4*($D9+$F9)^2)))/(1+1.96^2/($D9+$F9)),"") -> 0.074065051 | N9: =IFERROR((($D9/($D9+$F9))+1.96^2/(2*($D9+$F9))+1.96*SQRT(($D9/($D9+$F9))*(1-$D9/($D9+$F9))/($D9+$F9)+1.96^2/(4*($D9+$F9)^2)))/(1+1.96^2/($D9+$F9)),"") -> 0.22833368 | O9: =IFERROR((($D9/$G9)+1.96^2/(2*$G9)-1.96*SQRT(($D9/$G9)*(1-$D9/$G9)/$G9+1.96^2/(4*$G9^2)))/(1+1.96^2/$G9),"") -> 0.17375348 | P9: =IFERROR((($D9/$G9)+1.96^2/(2*$G9)+1.96*SQRT(($D9/$G9)*(1-$D9/$G9)/$G9+1.96^2/(4*$G9^2)))/(1+1.96^2/$G9),"") -> 0.47338454
A10: TMT | B10: S3 | C10: =COUNTIFS('04_MATCHING'!$B$2:$B$1026,$A10,'04_MATCHING'!$C$2:$C$1026,$B10) -> 117 | D10: =COUNTIFS('04_MATCHING'!$B$2:$B$1026,$A10,'04_MATCHING'!$C$2:$C$1026,$B10,'04_MATCHING'!$H$2:$H$1026,"Primary TP") -> 9 | E10: =COUNTIFS('04_MATCHING'!$B$2:$B$1026,$A10,'04_MATCHING'!$C$2:$C$1026,$B10,'04_MATCHING'!$H$2:$H$1026,"Duplicate") -> 25 | F10: =COUNTIFS('04_MATCHING'!$B$2:$B$1026,$A10,'04_MATCHING'!$C$2:$C$1026,$B10,'04_MATCHING'!$H$2:$H$1026,"False Positive") -> 83 | G10: =COUNTIFS('02_REFERENCE'!$B$2:$B$99,$B10,'02_REFERENCE'!$S$2:$S$99,"YES") -> 33 | H10: =G10-D10 -> 24 | I10: =IFERROR(D10/(D10+F10),"") -> 0.097826087 | J10: =IFERROR(D10/G10,"") -> 0.27272727 | K10: =IFERROR(2*I10*J10/(I10+J10),"") -> 0.144 | L10: =IFERROR((D10+E10)/C10,"") -> 0.29059829 | M10: =IFERROR((($D10/($D10+$F10))+1.96^2/(2*($D10+$F10))-1.96*SQRT(($D10/($D10+$F10))*(1-$D10/($D10+$F10))/($D10+$F10)+1.96^2/(4*($D10+$F10)^2)))/(1+1.96^2/($D10+$F10)),"") -> 0.052323164 | N10: =IFERROR((($D10/($D10+$F10))+1.96^2/(2*($D10+$F10))+1.96*SQRT(($D10/($D10+$F10))*(1-$D10/($D10+$F10))/($D10+$F10)+1.96^2/(4*($D10+$F10)^2)))/(1+1.96^2/($D10+$F10)),"") -> 0.17556953 | O10: =IFERROR((($D10/$G10)+1.96^2/(2*$G10)-1.96*SQRT(($D10/$G10)*(1-$D10/$G10)/$G10+1.96^2/(4*$G10^2)))/(1+1.96^2/$G10),"") -> 0.15067273 | P10: =IFERROR((($D10/$G10)+1.96^2/(2*$G10)+1.96*SQRT(($D10/$G10)*(1-$D10/$G10)/$G10+1.96^2/(4*$G10^2)))/(1+1.96^2/$G10),"") -> 0.44217883
A11: CHATGPT | B11: S1 | C11: =COUNTIFS('04_MATCHING'!$B$2:$B$1026,$A11,'04_MATCHING'!$C$2:$C$1026,$B11) -> 72 | D11: =COUNTIFS('04_MATCHING'!$B$2:$B$1026,$A11,'04_MATCHING'!$C$2:$C$1026,$B11,'04_MATCHING'!$H$2:$H$1026,"Primary TP") -> 18 | E11: =COUNTIFS('04_MATCHING'!$B$2:$B$1026,$A11,'04_MATCHING'!$C$2:$C$1026,$B11,'04_MATCHING'!$H$2:$H$1026,"Duplicate") -> 37 | F11: =COUNTIFS('04_MATCHING'!$B$2:$B$1026,$A11,'04_MATCHING'!$C$2:$C$1026,$B11,'04_MATCHING'!$H$2:$H$1026,"False Positive") -> 17 | G11: =COUNTIFS('02_REFERENCE'!$B$2:$B$99,$B11,'02_REFERENCE'!$S$2:$S$99,"YES") -> 32 | H11: =G11-D11 -> 14 | I11: =IFERROR(D11/(D11+F11),"") -> 0.51428571 | J11: =IFERROR(D11/G11,"") -> 0.5625 | K11: =IFERROR(2*I11*J11/(I11+J11),"") -> 0.53731343 | L11: =IFERROR((D11+E11)/C11,"") -> 0.76388889 | M11: =IFERROR((($D11/($D11+$F11))+1.96^2/(2*($D11+$F11))-1.96*SQRT(($D11/($D11+$F11))*(1-$D11/($D11+$F11))/($D11+$F11)+1.96^2/(4*($D11+$F11)^2)))/(1+1.96^2/($D11+$F11)),"") -> 0.3556854 | N11: =IFERROR((($D11/($D11+$F11))+1.96^2/(2*($D11+$F11))+1.96*SQRT(($D11/($D11+$F11))*(1-$D11/($D11+$F11))/($D11+$F11)+1.96^2/(4*($D11+$F11)^2)))/(1+1.96^2/($D11+$F11)),"") -> 0.6700602 | O11: =IFERROR((($D11/$G11)+1.96^2/(2*$G11)-1.96*SQRT(($D11/$G11)*(1-$D11/$G11)/$G11+1.96^2/(4*$G11^2)))/(1+1.96^2/$G11),"") -> 0.39325302 | P11: =IFERROR((($D11/$G11)+1.96^2/(2*$G11)+1.96*SQRT(($D11/$G11)*(1-$D11/$G11)/$G11+1.96^2/(4*$G11^2)))/(1+1.96^2/$G11),"") -> 0.71834914
A12: CHATGPT | B12: S2 | C12: =COUNTIFS('04_MATCHING'!$B$2:$B$1026,$A12,'04_MATCHING'!$C$2:$C$1026,$B12) -> 60 | D12: =COUNTIFS('04_MATCHING'!$B$2:$B$1026,$A12,'04_MATCHING'!$C$2:$C$1026,$B12,'04_MATCHING'!$H$2:$H$1026,"Primary TP") -> 18 | E12: =COUNTIFS('04_MATCHING'!$B$2:$B$1026,$A12,'04_MATCHING'!$C$2:$C$1026,$B12,'04_MATCHING'!$H$2:$H$1026,"Duplicate") -> 24 | F12: =COUNTIFS('04_MATCHING'!$B$2:$B$1026,$A12,'04_MATCHING'!$C$2:$C$1026,$B12,'04_MATCHING'!$H$2:$H$1026,"False Positive") -> 18 | G12: =COUNTIFS('02_REFERENCE'!$B$2:$B$99,$B12,'02_REFERENCE'!$S$2:$S$99,"YES") -> 33 | H12: =G12-D12 -> 15 | I12: =IFERROR(D12/(D12+F12),"") -> 0.5 | J12: =IFERROR(D12/G12,"") -> 0.54545455 | K12: =IFERROR(2*I12*J12/(I12+J12),"") -> 0.52173913 | L12: =IFERROR((D12+E12)/C12,"") -> 0.7 | M12: =IFERROR((($D12/($D12+$F12))+1.96^2/(2*($D12+$F12))-1.96*SQRT(($D12/($D12+$F12))*(1-$D12/($D12+$F12))/($D12+$F12)+1.96^2/(4*($D12+$F12)^2)))/(1+1.96^2/($D12+$F12)),"") -> 0.34474068 | N12: =IFERROR((($D12/($D12+$F12))+1.96^2/(2*($D12+$F12))+1.96*SQRT(($D12/($D12+$F12))*(1-$D12/($D12+$F12))/($D12+$F12)+1.96^2/(4*($D12+$F12)^2)))/(1+1.96^2/($D12+$F12)),"") -> 0.65525932 | O12: =IFERROR((($D12/$G12)+1.96^2/(2*$G12)-1.96*SQRT(($D12/$G12)*(1-$D12/$G12)/$G12+1.96^2/(4*$G12^2)))/(1+1.96^2/$G12),"") -> 0.37985658 | P12: =IFERROR((($D12/$G12)+1.96^2/(2*$G12)+1.96*SQRT(($D12/$G12)*(1-$D12/$G12)/$G12+1.96^2/(4*$G12^2)))/(1+1.96^2/$G12),"") -> 0.70157311
A13: CHATGPT | B13: S3 | C13: =COUNTIFS('04_MATCHING'!$B$2:$B$1026,$A13,'04_MATCHING'!$C$2:$C$1026,$B13) -> 49 | D13: =COUNTIFS('04_MATCHING'!$B$2:$B$1026,$A13,'04_MATCHING'!$C$2:$C$1026,$B13,'04_MATCHING'!$H$2:$H$1026,"Primary TP") -> 16 | E13: =COUNTIFS('04_MATCHING'!$B$2:$B$1026,$A13,'04_MATCHING'!$C$2:$C$1026,$B13,'04_MATCHING'!$H$2:$H$1026,"Duplicate") -> 11 | F13: =COUNTIFS('04_MATCHING'!$B$2:$B$1026,$A13,'04_MATCHING'!$C$2:$C$1026,$B13,'04_MATCHING'!$H$2:$H$1026,"False Positive") -> 22 | G13: =COUNTIFS('02_REFERENCE'!$B$2:$B$99,$B13,'02_REFERENCE'!$S$2:$S$99,"YES") -> 33 | H13: =G13-D13 -> 17 | I13: =IFERROR(D13/(D13+F13),"") -> 0.42105263 | J13: =IFERROR(D13/G13,"") -> 0.48484848 | K13: =IFERROR(2*I13*J13/(I13+J13),"") -> 0.45070423 | L13: =IFERROR((D13+E13)/C13,"") -> 0.55102041 | M13: =IFERROR((($D13/($D13+$F13))+1.96^2/(2*($D13+$F13))-1.96*SQRT(($D13/($D13+$F13))*(1-$D13/($D13+$F13))/($D13+$F13)+1.96^2/(4*($D13+$F13)^2)))/(1+1.96^2/($D13+$F13)),"") -> 0.27852275 | N13: =IFERROR((($D13/($D13+$F13))+1.96^2/(2*($D13+$F13))+1.96*SQRT(($D13/($D13+$F13))*(1-$D13/($D13+$F13))/($D13+$F13)+1.96^2/(4*($D13+$F13)^2)))/(1+1.96^2/($D13+$F13)),"") -> 0.57807929 | O13: =IFERROR((($D13/$G13)+1.96^2/(2*$G13)-1.96*SQRT(($D13/$G13)*(1-$D13/$G13)/$G13+1.96^2/(4*$G13^2)))/(1+1.96^2/$G13),"") -> 0.32503782 | P13: =IFERROR((($D13/$G13)+1.96^2/(2*$G13)+1.96*SQRT(($D13/$G13)*(1-$D13/$G13)/$G13+1.96^2/(4*$G13^2)))/(1+1.96^2/$G13),"") -> 0.64781895
A14: OLLAMA | B14: S1 | C14: =COUNTIFS('04_MATCHING'!$B$2:$B$1026,$A14,'04_MATCHING'!$C$2:$C$1026,$B14) -> 40 | D14: =COUNTIFS('04_MATCHING'!$B$2:$B$1026,$A14,'04_MATCHING'!$C$2:$C$1026,$B14,'04_MATCHING'!$H$2:$H$1026,"Primary TP") -> 6 | E14: =COUNTIFS('04_MATCHING'!$B$2:$B$1026,$A14,'04_MATCHING'!$C$2:$C$1026,$B14,'04_MATCHING'!$H$2:$H$1026,"Duplicate") -> 15 | F14: =COUNTIFS('04_MATCHING'!$B$2:$B$1026,$A14,'04_MATCHING'!$C$2:$C$1026,$B14,'04_MATCHING'!$H$2:$H$1026,"False Positive") -> 19 | G14: =COUNTIFS('02_REFERENCE'!$B$2:$B$99,$B14,'02_REFERENCE'!$S$2:$S$99,"YES") -> 32 | H14: =G14-D14 -> 26 | I14: =IFERROR(D14/(D14+F14),"") -> 0.24 | J14: =IFERROR(D14/G14,"") -> 0.1875 | K14: =IFERROR(2*I14*J14/(I14+J14),"") -> 0.21052632 | L14: =IFERROR((D14+E14)/C14,"") -> 0.525 | M14: =IFERROR((($D14/($D14+$F14))+1.96^2/(2*($D14+$F14))-1.96*SQRT(($D14/($D14+$F14))*(1-$D14/($D14+$F14))/($D14+$F14)+1.96^2/(4*($D14+$F14)^2)))/(1+1.96^2/($D14+$F14)),"") -> 0.11496158 | N14: =IFERROR((($D14/($D14+$F14))+1.96^2/(2*($D14+$F14))+1.96*SQRT(($D14/($D14+$F14))*(1-$D14/($D14+$F14))/($D14+$F14)+1.96^2/(4*($D14+$F14)^2)))/(1+1.96^2/($D14+$F14)),"") -> 0.4343006 | O14: =IFERROR((($D14/$G14)+1.96^2/(2*$G14)-1.96*SQRT(($D14/$G14)*(1-$D14/$G14)/$G14+1.96^2/(4*$G14^2)))/(1+1.96^2/$G14),"") -> 0.088894239 | P14: =IFERROR((($D14/$G14)+1.96^2/(2*$G14)+1.96*SQRT(($D14/$G14)*(1-$D14/$G14)/$G14+1.96^2/(4*$G14^2)))/(1+1.96^2/$G14),"") -> 0.35309496
A15: OLLAMA | B15: S2 | C15: =COUNTIFS('04_MATCHING'!$B$2:$B$1026,$A15,'04_MATCHING'!$C$2:$C$1026,$B15) -> 28 | D15: =COUNTIFS('04_MATCHING'!$B$2:$B$1026,$A15,'04_MATCHING'!$C$2:$C$1026,$B15,'04_MATCHING'!$H$2:$H$1026,"Primary TP") -> 7 | E15: =COUNTIFS('04_MATCHING'!$B$2:$B$1026,$A15,'04_MATCHING'!$C$2:$C$1026,$B15,'04_MATCHING'!$H$2:$H$1026,"Duplicate") -> 6 | F15: =COUNTIFS('04_MATCHING'!$B$2:$B$1026,$A15,'04_MATCHING'!$C$2:$C$1026,$B15,'04_MATCHING'!$H$2:$H$1026,"False Positive") -> 15 | G15: =COUNTIFS('02_REFERENCE'!$B$2:$B$99,$B15,'02_REFERENCE'!$S$2:$S$99,"YES") -> 33 | H15: =G15-D15 -> 26 | I15: =IFERROR(D15/(D15+F15),"") -> 0.31818182 | J15: =IFERROR(D15/G15,"") -> 0.21212121 | K15: =IFERROR(2*I15*J15/(I15+J15),"") -> 0.25454545 | L15: =IFERROR((D15+E15)/C15,"") -> 0.46428571 | M15: =IFERROR((($D15/($D15+$F15))+1.96^2/(2*($D15+$F15))-1.96*SQRT(($D15/($D15+$F15))*(1-$D15/($D15+$F15))/($D15+$F15)+1.96^2/(4*($D15+$F15)^2)))/(1+1.96^2/($D15+$F15)),"") -> 0.16360387 | N15: =IFERROR((($D15/($D15+$F15))+1.96^2/(2*($D15+$F15))+1.96*SQRT(($D15/($D15+$F15))*(1-$D15/($D15+$F15))/($D15+$F15)+1.96^2/(4*($D15+$F15)^2)))/(1+1.96^2/($D15+$F15)),"") -> 0.52681777 | O15: =IFERROR((($D15/$G15)+1.96^2/(2*$G15)-1.96*SQRT(($D15/$G15)*(1-$D15/$G15)/$G15+1.96^2/(4*$G15^2)))/(1+1.96^2/$G15),"") -> 0.10675887 | P15: =IFERROR((($D15/$G15)+1.96^2/(2*$G15)+1.96*SQRT(($D15/$G15)*(1-$D15/$G15)/$G15+1.96^2/(4*$G15^2)))/(1+1.96^2/$G15),"") -> 0.37751978
A16: OLLAMA | B16: S3 | C16: =COUNTIFS('04_MATCHING'!$B$2:$B$1026,$A16,'04_MATCHING'!$C$2:$C$1026,$B16) -> 24 | D16: =COUNTIFS('04_MATCHING'!$B$2:$B$1026,$A16,'04_MATCHING'!$C$2:$C$1026,$B16,'04_MATCHING'!$H$2:$H$1026,"Primary TP") -> 7 | E16: =COUNTIFS('04_MATCHING'!$B$2:$B$1026,$A16,'04_MATCHING'!$C$2:$C$1026,$B16,'04_MATCHING'!$H$2:$H$1026,"Duplicate") -> 5 | F16: =COUNTIFS('04_MATCHING'!$B$2:$B$1026,$A16,'04_MATCHING'!$C$2:$C$1026,$B16,'04_MATCHING'!$H$2:$H$1026,"False Positive") -> 12 | G16: =COUNTIFS('02_REFERENCE'!$B$2:$B$99,$B16,'02_REFERENCE'!$S$2:$S$99,"YES") -> 33 | H16: =G16-D16 -> 26 | I16: =IFERROR(D16/(D16+F16),"") -> 0.36842105 | J16: =IFERROR(D16/G16,"") -> 0.21212121 | K16: =IFERROR(2*I16*J16/(I16+J16),"") -> 0.26923077 | L16: =IFERROR((D16+E16)/C16,"") -> 0.5 | M16: =IFERROR((($D16/($D16+$F16))+1.96^2/(2*($D16+$F16))-1.96*SQRT(($D16/($D16+$F16))*(1-$D16/($D16+$F16))/($D16+$F16)+1.96^2/(4*($D16+$F16)^2)))/(1+1.96^2/($D16+$F16)),"") -> 0.19149272 | N16: =IFERROR((($D16/($D16+$F16))+1.96^2/(2*($D16+$F16))+1.96*SQRT(($D16/($D16+$F16))*(1-$D16/($D16+$F16))/($D16+$F16)+1.96^2/(4*($D16+$F16)^2)))/(1+1.96^2/($D16+$F16)),"") -> 0.58960843 | O16: =IFERROR((($D16/$G16)+1.96^2/(2*$G16)-1.96*SQRT(($D16/$G16)*(1-$D16/$G16)/$G16+1.96^2/(4*$G16^2)))/(1+1.96^2/$G16),"") -> 0.10675887 | P16: =IFERROR((($D16/$G16)+1.96^2/(2*$G16)+1.96*SQRT(($D16/$G16)*(1-$D16/$G16)/$G16+1.96^2/(4*$G16^2)))/(1+1.96^2/$G16),"") -> 0.37751978
... A19: THREMOLIA | B19: S3 | C19: =COUNTIFS('04_MATCHING'!$B$2:$B$1026,$A19,'04_MATCHING'!$C$2:$C$1026,$B19) -> 117 | D19: =COUNTIFS('04_MATCHING'!$B$2:$B$1026,$A19,'04_MATCHING'!$C$2:$C$1026,$B19,'04_MATCHING'!$H$2:$H$1026,"Primary TP") -> 20 | E19: =COUNTIFS('04_MATCHING'!$B$2:$B$1026,$A19,'04_MATCHING'!$C$2:$C$1026,$B19,'04_MATCHING'!$H$2:$H$1026,"Duplicate") -> 54 | F19: =COUNTIFS('04_MATCHING'!$B$2:$B$1026,$A19,'04_MATCHING'!$C$2:$C$1026,$B19,'04_MATCHING'!$H$2:$H$1026,"False Positive") -> 43 | G19: =COUNTIFS('02_REFERENCE'!$B$2:$B$99,$B19,'02_REFERENCE'!$S$2:$S$99,"YES") -> 33 | H19: =G19-D19 -> 13 | I19: =IFERROR(D19/(D19+F19),"") -> 0.31746032 | J19: =IFERROR(D19/G19,"") -> 0.60606061 | K19: =IFERROR(2*I19*J19/(I19+J19),"") -> 0.41666667 | L19: =IFERROR((D19+E19)/C19,"") -> 0.63247863 | M19: =IFERROR((($D19/($D19+$F19))+1.96^2/(2*($D19+$F19))-1.96*SQRT(($D19/($D19+$F19))*(1-$D19/($D19+$F19))/($D19+$F19)+1.96^2/(4*($D19+$F19)^2)))/(1+1.96^2/($D19+$F19)),"") -> 0.21586527 | N19: =IFERROR((($D19/($D19+$F19))+1.96^2/(2*($D19+$F19))+1.96*SQRT(($D19/($D19+$F19))*(1-$D19/($D19+$F19))/($D19+$F19)+1.96^2/(4*($D19+$F19)^2)))/(1+1.96^2/($D19+$F19)),"") -> 0.44003764 | O19: =IFERROR((($D19/$G19)+1.96^2/(2*$G19)-1.96*SQRT(($D19/$G19)*(1-$D19/$G19)/$G19+1.96^2/(4*$G19^2)))/(1+1.96^2/$G19),"") -> 0.43683143 | P19: =IFERROR((($D19/$G19)+1.96^2/(2*$G19)+1.96*SQRT(($D19/$G19)*(1-$D19/$G19)/$G19+1.96^2/(4*$G19^2)))/(1+1.96^2/$G19),"") -> 0.75317118
A20: OVERALL | B20: All | C20: =SUM(C5:C19) -> 1025 | D20: =SUM(D5:D19) -> 188 | E20: =SUM(E5:E19) -> 339 | F20: =SUM(F5:F19) -> 498 | G20: =SUM(G5:G19) -> 490 | H20: =SUM(H5:H19) -> 302 | I20: =IFERROR(D20/(D20+F20),"") -> 0.27405248 | J20: =IFERROR(D20/G20,"") -> 0.38367347 | K20: =IFERROR(2*I20*J20/(I20+J20),"") -> 0.31972789 | L20: =IFERROR((D20+E20)/C20,"") -> 0.51414634
A22: STRICT MATCHING (additional analysis #4)
A23: Approach | B23: Primary TP | C23: High-confidence Primary TP (H) | D23: Strict Matching Rate
A24: OWASP | B24: =SUMIF('05_TP_FP_FN'!$A$5:$A$19,"OWASP",'05_TP_FP_FN'!$E$5:$E$19) -> 19 | C24: =COUNTIFS('04_MATCHING'!$B$2:$B$1026,"OWASP",'04_MATCHING'!$H$2:$H$1026,"Primary TP",'04_MATCHING'!$J$2:$J$1026,"H") -> 1 | D24: =IFERROR(C24/B24,"") -> 0.052631579
A25: TMT | B25: =SUMIF('05_TP_FP_FN'!$A$5:$A$19,"TMT",'05_TP_FP_FN'!$E$5:$E$19) -> 28 | C25: =COUNTIFS('04_MATCHING'!$B$2:$B$1026,"TMT",'04_MATCHING'!$H$2:$H$1026,"Primary TP",'04_MATCHING'!$J$2:$J$1026,"H") -> 0 | D25: =IFERROR(C25/B25,"") -> 0
A26: CHATGPT | B26: =SUMIF('05_TP_FP_FN'!$A$5:$A$19,"CHATGPT",'05_TP_FP_FN'!$E$5:$E$19) -> 52 | C26: =COUNTIFS('04_MATCHING'!$B$2:$B$1026,"CHATGPT",'04_MATCHING'!$H$2:$H$1026,"Primary TP",'04_MATCHING'!$J$2:$J$1026,"H") -> 25 | D26: =IFERROR(C26/B26,"") -> 0.48076923
A27: OLLAMA | B27: =SUMIF('05_TP_FP_FN'!$A$5:$A$19,"OLLAMA",'05_TP_FP_FN'!$E$5:$E$19) -> 20 | C27: =COUNTIFS('04_MATCHING'!$B$2:$B$1026,"OLLAMA",'04_MATCHING'!$H$2:$H$1026,"Primary TP",'04_MATCHING'!$J$2:$J$1026,"H") -> 6 | D27: =IFERROR(C27/B27,"") -> 0.3
A28: THREMOLIA | B28: =SUMIF('05_TP_FP_FN'!$A$5:$A$19,"THREMOLIA",'05_TP_FP_FN'!$E$5:$E$19) -> 69 | C28: =COUNTIFS('04_MATCHING'!$B$2:$B$1026,"THREMOLIA",'04_MATCHING'!$H$2:$H$1026,"Primary TP",'04_MATCHING'!$J$2:$J$1026,"H") -> 38 | D28: =IFERROR(C28/B28,"") -> 0.55072464
A29: TOTAL | B29: =SUM(B24:B28) -> 188 | C29: =SUM(C24:C28) -> 70 | D29: =IFERROR(C29/B29,"") -> 0.37234043
A30: Note: "Strict matching" is defined as a Primary TP assigned High matching confidence. The Matching Confidence column (J) carries the analyst confidence (H/M/L). Low- and medium-confidence matches are retained but are candidates for manual review.

Sheet 07_STRIDE
A1: STRIDE Performance
A2: RECALL is computed at the reference level (STRIDE category comes from the expert baseline). Because no per-finding STRIDE classification was provided for False-Positive findings, the Generated/FP/Precision/F1 columns are reported as N/A (data not available) rather than estimated.
A4: Approach | B4: Scenario | C4: STRIDE Category | D4: Reference | E4: TP | F4: FN | G4: Recall | H4: Generated | I4: FP | J4: Precision | K4: F1
A5: OWASP | B5: S1 | C5: Spoofing | D5: =COUNTIFS('02_REFERENCE'!$B$2:$B$99,$B5,'02_REFERENCE'!$D$2:$D$99,$C5,'02_REFERENCE'!$S$2:$S$99,"YES") -> 8 | E5: =COUNTIFS('04_MATCHING'!$B$2:$B$1026,$A5,'04_MATCHING'!$C$2:$C$1026,$B5,'04_MATCHING'!$H$2:$H$1026,"Primary TP",'04_MATCHING'!$D$2:$D$1026,$C5) -> 2 | F5: =D5-E5 -> 6 | G5: =IFERROR(E5/D5,"") -> 0.25 | H5: N/A | I5: N/A | J5: N/A | K5: N/A
A6: OWASP | B6: S1 | C6: Tampering | D6: =COUNTIFS('02_REFERENCE'!$B$2:$B$99,$B6,'02_REFERENCE'!$D$2:$D$99,$C6,'02_REFERENCE'!$S$2:$S$99,"YES") -> 7 | E6: =COUNTIFS('04_MATCHING'!$B$2:$B$1026,$A6,'04_MATCHING'!$C$2:$C$1026,$B6,'04_MATCHING'!$H$2:$H$1026,"Primary TP",'04_MATCHING'!$D$2:$D$1026,$C6) -> 1 | F6: =D6-E6 -> 6 | G6: =IFERROR(E6/D6,"") -> 0.14285714 | H6: N/A | I6: N/A | J6: N/A | K6: N/A
A7: OWASP | B7: S1 | C7: Repudiation | D7: =COUNTIFS('02_REFERENCE'!$B$2:$B$99,$B7,'02_REFERENCE'!$D$2:$D$99,$C7,'02_REFERENCE'!$S$2:$S$99,"YES") -> 1 | E7: =COUNTIFS('04_MATCHING'!$B$2:$B$1026,$A7,'04_MATCHING'!$C$2:$C$1026,$B7,'04_MATCHING'!$H$2:$H$1026,"Primary TP",'04_MATCHING'!$D$2:$D$1026,$C7) -> 0 | F7: =D7-E7 -> 1 | G7: =IFERROR(E7/D7,"") -> 0 | H7: N/A | I7: N/A | J7: N/A | K7: N/A
A8: OWASP | B8: S1 | C8: Information Disclosure | D8: =COUNTIFS('02_REFERENCE'!$B$2:$B$99,$B8,'02_REFERENCE'!$D$2:$D$99,$C8,'02_REFERENCE'!$S$2:$S$99,"YES") -> 10 | E8: =COUNTIFS('04_MATCHING'!$B$2:$B$1026,$A8,'04_MATCHING'!$C$2:$C$1026,$B8,'04_MATCHING'!$H$2:$H$1026,"Primary TP",'04_MATCHING'!$D$2:$D$1026,$C8) -> 1 | F8: =D8-E8 -> 9 | G8: =IFERROR(E8/D8,"") -> 0.1 | H8: N/A | I8: N/A | J8: N/A | K8: N/A
A9: OWASP | B9: S1 | C9: Denial of Service | D9: =COUNTIFS('02_REFERENCE'!$B$2:$B$99,$B9,'02_REFERENCE'!$D$2:$D$99,$C9,'02_REFERENCE'!$S$2:$S$99,"YES") -> 3 | E9: =COUNTIFS('04_MATCHING'!$B$2:$B$1026,$A9,'04_MATCHING'!$C$2:$C$1026,$B9,'04_MATCHING'!$H$2:$H$1026,"Primary TP",'04_MATCHING'!$D$2:$D$1026,$C9) -> 2 | F9: =D9-E9 -> 1 | G9: =IFERROR(E9/D9,"") -> 0.66666667 | H9: N/A | I9: N/A | J9: N/A | K9: N/A
A10: OWASP | B10: S1 | C10: Elevation of Privilege | D10: =COUNTIFS('02_REFERENCE'!$B$2:$B$99,$B10,'02_REFERENCE'!$D$2:$D$99,$C10,'02_REFERENCE'!$S$2:$S$99,"YES") -> 3 | E10: =COUNTIFS('04_MATCHING'!$B$2:$B$1026,$A10,'04_MATCHING'!$C$2:$C$1026,$B10,'04_MATCHING'!$H$2:$H$1026,"Primary TP",'04_MATCHING'!$D$2:$D$1026,$C10) -> 0 | F10: =D10-E10 -> 3 | G10: =IFERROR(E10/D10,"") -> 0 | H10: N/A | I10: N/A | J10: N/A | K10: N/A
A11: OWASP | B11: S2 | C11: Spoofing | D11: =COUNTIFS('02_REFERENCE'!$B$2:$B$99,$B11,'02_REFERENCE'!$D$2:$D$99,$C11,'02_REFERENCE'!$S$2:$S$99,"YES") -> 3 | E11: =COUNTIFS('04_MATCHING'!$B$2:$B$1026,$A11,'04_MATCHING'!$C$2:$C$1026,$B11,'04_MATCHING'!$H$2:$H$1026,"Primary TP",'04_MATCHING'!$D$2:$D$1026,$C11) -> 0 | F11: =D11-E11 -> 3 | G11: =IFERROR(E11/D11,"") -> 0 | H11: N/A | I11: N/A | J11: N/A | K11: N/A
A12: OWASP | B12: S2 | C12: Tampering | D12: =COUNTIFS('02_REFERENCE'!$B$2:$B$99,$B12,'02_REFERENCE'!$D$2:$D$99,$C12,'02_REFERENCE'!$S$2:$S$99,"YES") -> 12 | E12: =COUNTIFS('04_MATCHING'!$B$2:$B$1026,$A12,'04_MATCHING'!$C$2:$C$1026,$B12,'04_MATCHING'!$H$2:$H$1026,"Primary TP",'04_MATCHING'!$D$2:$D$1026,$C12) -> 2 | F12: =D12-E12 -> 10 | G12: =IFERROR(E12/D12,"") -> 0.16666667 | H12: N/A | I12: N/A | J12: N/A | K12: N/A
A13: OWASP | B13: S2 | C13: Repudiation | D13: =COUNTIFS('02_REFERENCE'!$B$2:$B$99,$B13,'02_REFERENCE'!$D$2:$D$99,$C13,'02_REFERENCE'!$S$2:$S$99,"YES") -> 1 | E13: =COUNTIFS('04_MATCHING'!$B$2:$B$1026,$A13,'04_MATCHING'!$C$2:$C$1026,$B13,'04_MATCHING'!$H$2:$H$1026,"Primary TP",'04_MATCHING'!$D$2:$D$1026,$C13) -> 0 | F13: =D13-E13 -> 1 | G13: =IFERROR(E13/D13,"") -> 0 | H13: N/A | I13: N/A | J13: N/A | K13: N/A
A14: OWASP | B14: S2 | C14: Information Disclosure | D14: =COUNTIFS('02_REFERENCE'!$B$2:$B$99,$B14,'02_REFERENCE'!$D$2:$D$99,$C14,'02_REFERENCE'!$S$2:$S$99,"YES") -> 8 | E14: =COUNTIFS('04_MATCHING'!$B$2:$B$1026,$A14,'04_MATCHING'!$C$2:$C$1026,$B14,'04_MATCHING'!$H$2:$H$1026,"Primary TP",'04_MATCHING'!$D$2:$D$1026,$C14) -> 2 | F14: =D14-E14 -> 6 | G14: =IFERROR(E14/D14,"") -> 0.25 | H14: N/A | I14: N/A | J14: N/A | K14: N/A
A15: OWASP | B15: S2 | C15: Denial of Service | D15: =COUNTIFS('02_REFERENCE'!$B$2:$B$99,$B15,'02_REFERENCE'!$D$2:$D$99,$C15,'02_REFERENCE'!$S$2:$S$99,"YES") -> 3 | E15: =COUNTIFS('04_MATCHING'!$B$2:$B$1026,$A15,'04_MATCHING'!$C$2:$C$1026,$B15,'04_MATCHING'!$H$2:$H$1026,"Primary TP",'04_MATCHING'!$D$2:$D$1026,$C15) -> 2 | F15: =D15-E15 -> 1 | G15: =IFERROR(E15/D15,"") -> 0.66666667 | H15: N/A | I15: N/A | J15: N/A | K15: N/A
A16: OWASP | B16: S2 | C16: Elevation of Privilege | D16: =COUNTIFS('02_REFERENCE'!$B$2:$B$99,$B16,'02_REFERENCE'!$D$2:$D$99,$C16,'02_REFERENCE'!$S$2:$S$99,"YES") -> 6 | E16: =COUNTIFS('04_MATCHING'!$B$2:$B$1026,$A16,'04_MATCHING'!$C$2:$C$1026,$B16,'04_MATCHING'!$H$2:$H$1026,"Primary TP",'04_MATCHING'!$D$2:$D$1026,$C16) -> 0 | F16: =D16-E16 -> 6 | G16: =IFERROR(E16/D16,"") -> 0 | H16: N/A | I16: N/A | J16: N/A | K16: N/A
... A94: THREMOLIA | B94: S3 | C94: Elevation of Privilege | D94: =COUNTIFS('02_REFERENCE'!$B$2:$B$99,$B94,'02_REFERENCE'!$D$2:$D$99,$C94,'02_REFERENCE'!$S$2:$S$99,"YES") -> 5 | E94: =COUNTIFS('04_MATCHING'!$B$2:$B$1026,$A94,'04_MATCHING'!$C$2:$C$1026,$B94,'04_MATCHING'!$H$2:$H$1026,"Primary TP",'04_MATCHING'!$D$2:$D$1026,$C94) -> 1 | F94: =D94-E94 -> 4 | G94: =IFERROR(E94/D94,"") -> 0.2 | H94: N/A | I94: N/A | J94: N/A | K94: N/A

Sheet 08_GROUNDING
A1: Grounding Analysis
A2: Grounding is kept logically separate from correctness (grounded != correct). NO per-finding grounding annotation was provided in the authoritative source data. The grounding rate and grounded/ungrounded x TP/FP breakdown therefore CANNOT be computed reliably and are reported as N/A - DATA NOT AVAILABLE.
A4: Grounding Metric | B4: Status | C4: Value | D4: Definition / Required Source | E4: Component | F4: Data Flow | G4: Trust Boundary | H4: Asset | I4: Architectural Evidence
A5: Grounding Rate | B5: N/A - DATA NOT AVAILABLE | C5: = | D5: Grounded Findings / Total Findings. Requires an explicit per-finding grounded/ungrounded verdict.
A6: Grounded TP | B6: N/A | C6: = | D6: TP findings whose attack path is supported by drawn architecture (component/data-flow/trust-boundary/asset evidence).
A7: Ungrounded TP | B7: N/A | C7: = | D7: TP findings lacking architectural support in the model.
A8: Grounded FP | B8: N/A | C8: = | D8: FP findings nevertheless supported by the architecture (false positive in the reference-correspondence sense).
A9: Ungrounded FP | B9: N/A | C9: = | D9: FP findings with no architectural support.
A11: Available per-finding metadata (for reference only; NOT a grounding verdict):
A12: Finding ID | B12: Approach | C12: Scenario | D12: Threat Category | E12: Component | F12: Data Flow | G12: (Trust Boundary / Asset / Arch Evidence not present)
A13: OWASP-S1-F001 | B13: OWASP | C13: S1 | D13: captcha | E13: EE1 End User | G13: N/A
A14: OWASP-S1-F002 | B14: OWASP | C14: S1 | D14: credential_stuffing | E14: EE1 End User | G14: N/A
A15: OWASP-S1-F003 | B15: OWASP | C15: S1 | D15: excessive_db_scope | E15: P1 Web Frontend Interface | G15: N/A
A16: OWASP-S1-F004 | B16: OWASP | C16: S1 | D16: expedition | E16: P1 Web Frontend Interface | G16: N/A
A17: OWASP-S1-F005 | B17: OWASP | C17: S1 | D17: recon | E17: P1 Web Frontend Interface | G17: N/A
A18: OWASP-S1-F006 | B18: OWASP | C18: S1 | D18: dos_service | E18: P1 Web Frontend Interface | G18: N/A
A19: OWASP-S1-F007 | B19: OWASP | C19: S1 | D19: recon | E19: P1 Web Frontend Interface | G19: N/A
A20: OWASP-S1-F008 | B20: OWASP | C20: S1 | D20: excessive_db_scope | E20: P2 Authentication Service | G20: N/A
A21: OWASP-S1-F009 | B21: OWASP | C21: S1 | D21: expedition | E21: P2 Authentication Service | G21: N/A
A22: OWASP-S1-F010 | B22: OWASP | C22: S1 | D22: recon | E22: P2 Authentication Service | G22: N/A
A23: OWASP-S1-F011 | B23: OWASP | C23: S1 | D23: dos_service | E23: P2 Authentication Service | G23: N/A
A24: OWASP-S1-F012 | B24: OWASP | C24: S1 | D24: recon | E24: P2 Authentication Service | G24: N/A
... A37: OWASP-S1-F025 | B37: OWASP | C37: S1 | D37: recon | E37: P4 AI chatbot Component | G37: N/A
A38: ... (n=1025 rows total; see 03/04)
A40: CONCLUSION
A41: Grounding cannot be reported without a grounded/ungrounded annotation per finding. The "component" and "data_flow" fields present in the raw records are evidence candidates, not grounding verdicts. Add a grounding column to 04_MATCHING and this sheet will compute automatically.

Sheet 09_UNIQUENESS_REDUNDANCY
A1: Redundancy / Uniqueness
A2: Duplicate = multiple findings describing the same underlying threat mechanism within the same approach & scenario (per one-to-one rule). Unique Findings = Primary TP + FP (i.e., findings that are not duplicates). Redundancy Rate = Duplicates / Generated. Unique-Find Rate = Unique / Generated. Redundancy among correct = Duplicates / (PrimaryTP + Duplicates).
A4: Approach | B4: Scenario | C4: Generated | D4: Primary TP | E4: Duplicates | F4: FP | G4: Unique Findings (non-dup) | H4: Redundancy Rate | I4: Unique-Find Rate | J4: Redundancy among correct
A5: OWASP | B5: S1 | C5: =COUNTIFS('04_MATCHING'!$B$2:$B$1026,$A5,'04_MATCHING'!$C$2:$C$1026,$B5) -> 38 | D5: =COUNTIFS('04_MATCHING'!$B$2:$B$1026,$A5,'04_MATCHING'!$C$2:$C$1026,$B5,'04_MATCHING'!$H$2:$H$1026,"Primary TP") -> 6 | E5: =COUNTIFS('04_MATCHING'!$B$2:$B$1026,$A5,'04_MATCHING'!$C$2:$C$1026,$B5,'04_MATCHING'!$H$2:$H$1026,"Duplicate") -> 6 | F5: =COUNTIFS('04_MATCHING'!$B$2:$B$1026,$A5,'04_MATCHING'!$C$2:$C$1026,$B5,'04_MATCHING'!$H$2:$H$1026,"False Positive") -> 26 | G5: =D5+F5 -> 32 | H5: =IFERROR(E5/C5,"") -> 0.15789474 | I5: =IFERROR(G5/C5,"") -> 0.84210526 | J5: =IFERROR(E5/(D5+E5),"") -> 0.5
A6: OWASP | B6: S2 | C6: =COUNTIFS('04_MATCHING'!$B$2:$B$1026,$A6,'04_MATCHING'!$C$2:$C$1026,$B6) -> 39 | D6: =COUNTIFS('04_MATCHING'!$B$2:$B$1026,$A6,'04_MATCHING'!$C$2:$C$1026,$B6,'04_MATCHING'!$H$2:$H$1026,"Primary TP") -> 6 | E6: =COUNTIFS('04_MATCHING'!$B$2:$B$1026,$A6,'04_MATCHING'!$C$2:$C$1026,$B6,'04_MATCHING'!$H$2:$H$1026,"Duplicate") -> 6 | F6: =COUNTIFS('04_MATCHING'!$B$2:$B$1026,$A6,'04_MATCHING'!$C$2:$C$1026,$B6,'04_MATCHING'!$H$2:$H$1026,"False Positive") -> 27 | G6: =D6+F6 -> 33 | H6: =IFERROR(E6/C6,"") -> 0.15384615 | I6: =IFERROR(G6/C6,"") -> 0.84615385 | J6: =IFERROR(E6/(D6+E6),"") -> 0.5
A7: OWASP | B7: S3 | C7: =COUNTIFS('04_MATCHING'!$B$2:$B$1026,$A7,'04_MATCHING'!$C$2:$C$1026,$B7) -> 46 | D7: =COUNTIFS('04_MATCHING'!$B$2:$B$1026,$A7,'04_MATCHING'!$C$2:$C$1026,$B7,'04_MATCHING'!$H$2:$H$1026,"Primary TP") -> 7 | E7: =COUNTIFS('04_MATCHING'!$B$2:$B$1026,$A7,'04_MATCHING'!$C$2:$C$1026,$B7,'04_MATCHING'!$H$2:$H$1026,"Duplicate") -> 13 | F7: =COUNTIFS('04_MATCHING'!$B$2:$B$1026,$A7,'04_MATCHING'!$C$2:$C$1026,$B7,'04_MATCHING'!$H$2:$H$1026,"False Positive") -> 26 | G7: =D7+F7 -> 33 | H7: =IFERROR(E7/C7,"") -> 0.2826087 | I7: =IFERROR(G7/C7,"") -> 0.7173913 | J7: =IFERROR(E7/(D7+E7),"") -> 0.65
A8: TMT | B8: S1 | C8: =COUNTIFS('04_MATCHING'!$B$2:$B$1026,$A8,'04_MATCHING'!$C$2:$C$1026,$B8) -> 95 | D8: =COUNTIFS('04_MATCHING'!$B$2:$B$1026,$A8,'04_MATCHING'!$C$2:$C$1026,$B8,'04_MATCHING'!$H$2:$H$1026,"Primary TP") -> 9 | E8: =COUNTIFS('04_MATCHING'!$B$2:$B$1026,$A8,'04_MATCHING'!$C$2:$C$1026,$B8,'04_MATCHING'!$H$2:$H$1026,"Duplicate") -> 13 | F8: =COUNTIFS('04_MATCHING'!$B$2:$B$1026,$A8,'04_MATCHING'!$C$2:$C$1026,$B8,'04_MATCHING'!$H$2:$H$1026,"False Positive") -> 73 | G8: =D8+F8 -> 82 | H8: =IFERROR(E8/C8,"") -> 0.13684211 | I8: =IFERROR(G8/C8,"") -> 0.86315789 | J8: =IFERROR(E8/(D8+E8),"") -> 0.59090909
A9: TMT | B9: S2 | C9: =COUNTIFS('04_MATCHING'!$B$2:$B$1026,$A9,'04_MATCHING'!$C$2:$C$1026,$B9) -> 89 | D9: =COUNTIFS('04_MATCHING'!$B$2:$B$1026,$A9,'04_MATCHING'!$C$2:$C$1026,$B9,'04_MATCHING'!$H$2:$H$1026,"Primary TP") -> 10 | E9: =COUNTIFS('04_MATCHING'!$B$2:$B$1026,$A9,'04_MATCHING'!$C$2:$C$1026,$B9,'04_MATCHING'!$H$2:$H$1026,"Duplicate") -> 14 | F9: =COUNTIFS('04_MATCHING'!$B$2:$B$1026,$A9,'04_MATCHING'!$C$2:$C$1026,$B9,'04_MATCHING'!$H$2:$H$1026,"False Positive") -> 65 | G9: =D9+F9 -> 75 | H9: =IFERROR(E9/C9,"") -> 0.15730337 | I9: =IFERROR(G9/C9,"") -> 0.84269663 | J9: =IFERROR(E9/(D9+E9),"") -> 0.58333333
A10: TMT | B10: S3 | C10: =COUNTIFS('04_MATCHING'!$B$2:$B$1026,$A10,'04_MATCHING'!$C$2:$C$1026,$B10) -> 117 | D10: =COUNTIFS('04_MATCHING'!$B$2:$B$1026,$A10,'04_MATCHING'!$C$2:$C$1026,$B10,'04_MATCHING'!$H$2:$H$1026,"Primary TP") -> 9 | E10: =COUNTIFS('04_MATCHING'!$B$2:$B$1026,$A10,'04_MATCHING'!$C$2:$C$1026,$B10,'04_MATCHING'!$H$2:$H$1026,"Duplicate") -> 25 | F10: =COUNTIFS('04_MATCHING'!$B$2:$B$1026,$A10,'04_MATCHING'!$C$2:$C$1026,$B10,'04_MATCHING'!$H$2:$H$1026,"False Positive") -> 83 | G10: =D10+F10 -> 92 | H10: =IFERROR(E10/C10,"") -> 0.21367521 | I10: =IFERROR(G10/C10,"") -> 0.78632479 | J10: =IFERROR(E10/(D10+E10),"") -> 0.73529412
A11: CHATGPT | B11: S1 | C11: =COUNTIFS('04_MATCHING'!$B$2:$B$1026,$A11,'04_MATCHING'!$C$2:$C$1026,$B11) -> 72 | D11: =COUNTIFS('04_MATCHING'!$B$2:$B$1026,$A11,'04_MATCHING'!$C$2:$C$1026,$B11,'04_MATCHING'!$H$2:$H$1026,"Primary TP") -> 18 | E11: =COUNTIFS('04_MATCHING'!$B$2:$B$1026,$A11,'04_MATCHING'!$C$2:$C$1026,$B11,'04_MATCHING'!$H$2:$H$1026,"Duplicate") -> 37 | F11: =COUNTIFS('04_MATCHING'!$B$2:$B$1026,$A11,'04_MATCHING'!$C$2:$C$1026,$B11,'04_MATCHING'!$H$2:$H$1026,"False Positive") -> 17 | G11: =D11+F11 -> 35 | H11: =IFERROR(E11/C11,"") -> 0.51388889 | I11: =IFERROR(G11/C11,"") -> 0.48611111 | J11: =IFERROR(E11/(D11+E11),"") -> 0.67272727
A12: CHATGPT | B12: S2 | C12: =COUNTIFS('04_MATCHING'!$B$2:$B$1026,$A12,'04_MATCHING'!$C$2:$C$1026,$B12) -> 60 | D12: =COUNTIFS('04_MATCHING'!$B$2:$B$1026,$A12,'04_MATCHING'!$C$2:$C$1026,$B12,'04_MATCHING'!$H$2:$H$1026,"Primary TP") -> 18 | E12: =COUNTIFS('04_MATCHING'!$B$2:$B$1026,$A12,'04_MATCHING'!$C$2:$C$1026,$B12,'04_MATCHING'!$H$2:$H$1026,"Duplicate") -> 24 | F12: =COUNTIFS('04_MATCHING'!$B$2:$B$1026,$A12,'04_MATCHING'!$C$2:$C$1026,$B12,'04_MATCHING'!$H$2:$H$1026,"False Positive") -> 18 | G12: =D12+F12 -> 36 | H12: =IFERROR(E12/C12,"") -> 0.4 | I12: =IFERROR(G12/C12,"") -> 0.6 | J12: =IFERROR(E12/(D12+E12),"") -> 0.57142857
A13: CHATGPT | B13: S3 | C13: =COUNTIFS('04_MATCHING'!$B$2:$B$1026,$A13,'04_MATCHING'!$C$2:$C$1026,$B13) -> 49 | D13: =COUNTIFS('04_MATCHING'!$B$2:$B$1026,$A13,'04_MATCHING'!$C$2:$C$1026,$B13,'04_MATCHING'!$H$2:$H$1026,"Primary TP") -> 16 | E13: =COUNTIFS('04_MATCHING'!$B$2:$B$1026,$A13,'04_MATCHING'!$C$2:$C$1026,$B13,'04_MATCHING'!$H$2:$H$1026,"Duplicate") -> 11 | F13: =COUNTIFS('04_MATCHING'!$B$2:$B$1026,$A13,'04_MATCHING'!$C$2:$C$1026,$B13,'04_MATCHING'!$H$2:$H$1026,"False Positive") -> 22 | G13: =D13+F13 -> 38 | H13: =IFERROR(E13/C13,"") -> 0.2244898 | I13: =IFERROR(G13/C13,"") -> 0.7755102 | J13: =IFERROR(E13/(D13+E13),"") -> 0.40740741
A14: OLLAMA | B14: S1 | C14: =COUNTIFS('04_MATCHING'!$B$2:$B$1026,$A14,'04_MATCHING'!$C$2:$C$1026,$B14) -> 40 | D14: =COUNTIFS('04_MATCHING'!$B$2:$B$1026,$A14,'04_MATCHING'!$C$2:$C$1026,$B14,'04_MATCHING'!$H$2:$H$1026,"Primary TP") -> 6 | E14: =COUNTIFS('04_MATCHING'!$B$2:$B$1026,$A14,'04_MATCHING'!$C$2:$C$1026,$B14,'04_MATCHING'!$H$2:$H$1026,"Duplicate") -> 15 | F14: =COUNTIFS('04_MATCHING'!$B$2:$B$1026,$A14,'04_MATCHING'!$C$2:$C$1026,$B14,'04_MATCHING'!$H$2:$H$1026,"False Positive") -> 19 | G14: =D14+F14 -> 25 | H14: =IFERROR(E14/C14,"") -> 0.375 | I14: =IFERROR(G14/C14,"") -> 0.625 | J14: =IFERROR(E14/(D14+E14),"") -> 0.71428571
A15: OLLAMA | B15: S2 | C15: =COUNTIFS('04_MATCHING'!$B$2:$B$1026,$A15,'04_MATCHING'!$C$2:$C$1026,$B15) -> 28 | D15: =COUNTIFS('04_MATCHING'!$B$2:$B$1026,$A15,'04_MATCHING'!$C$2:$C$1026,$B15,'04_MATCHING'!$H$2:$H$1026,"Primary TP") -> 7 | E15: =COUNTIFS('04_MATCHING'!$B$2:$B$1026,$A15,'04_MATCHING'!$C$2:$C$1026,$B15,'04_MATCHING'!$H$2:$H$1026,"Duplicate") -> 6 | F15: =COUNTIFS('04_MATCHING'!$B$2:$B$1026,$A15,'04_MATCHING'!$C$2:$C$1026,$B15,'04_MATCHING'!$H$2:$H$1026,"False Positive") -> 15 | G15: =D15+F15 -> 22 | H15: =IFERROR(E15/C15,"") -> 0.21428571 | I15: =IFERROR(G15/C15,"") -> 0.78571429 | J15: =IFERROR(E15/(D15+E15),"") -> 0.46153846
A16: OLLAMA | B16: S3 | C16: =COUNTIFS('04_MATCHING'!$B$2:$B$1026,$A16,'04_MATCHING'!$C$2:$C$1026,$B16) -> 24 | D16: =COUNTIFS('04_MATCHING'!$B$2:$B$1026,$A16,'04_MATCHING'!$C$2:$C$1026,$B16,'04_MATCHING'!$H$2:$H$1026,"Primary TP") -> 7 | E16: =COUNTIFS('04_MATCHING'!$B$2:$B$1026,$A16,'04_MATCHING'!$C$2:$C$1026,$B16,'04_MATCHING'!$H$2:$H$1026,"Duplicate") -> 5 | F16: =COUNTIFS('04_MATCHING'!$B$2:$B$1026,$A16,'04_MATCHING'!$C$2:$C$1026,$B16,'04_MATCHING'!$H$2:$H$1026,"False Positive") -> 12 | G16: =D16+F16 -> 19 | H16: =IFERROR(E16/C16,"") -> 0.20833333 | I16: =IFERROR(G16/C16,"") -> 0.79166667 | J16: =IFERROR(E16/(D16+E16),"") -> 0.41666667
... A19: THREMOLIA | B19: S3 | C19: =COUNTIFS('04_MATCHING'!$B$2:$B$1026,$A19,'04_MATCHING'!$C$2:$C$1026,$B19) -> 117 | D19: =COUNTIFS('04_MATCHING'!$B$2:$B$1026,$A19,'04_MATCHING'!$C$2:$C$1026,$B19,'04_MATCHING'!$H$2:$H$1026,"Primary TP") -> 20 | E19: =COUNTIFS('04_MATCHING'!$B$2:$B$1026,$A19,'04_MATCHING'!$C$2:$C$1026,$B19,'04_MATCHING'!$H$2:$H$1026,"Duplicate") -> 54 | F19: =COUNTIFS('04_MATCHING'!$B$2:$B$1026,$A19,'04_MATCHING'!$C$2:$C$1026,$B19,'04_MATCHING'!$H$2:$H$1026,"False Positive") -> 43 | G19: =D19+F19 -> 63 | H19: =IFERROR(E19/C19,"") -> 0.46153846 | I19: =IFERROR(G19/C19,"") -> 0.53846154 | J19: =IFERROR(E19/(D19+E19),"") -> 0.72972973
A20: TOTAL | B20: All | C20: =SUM(C5:C19) -> 1025 | D20: =SUM(D5:D19) -> 188 | E20: =SUM(E5:E19) -> 339 | F20: =SUM(F5:F19) -> 498 | G20: =SUM(G5:G19) -> 686 | H20: =IFERROR(E20/C20,"") -> 0.33073171 | I20: =IFERROR(G20/C20,"") -> 0.66926829 | J20: =IFERROR(E20/(D20+E20),"") -> 0.64326376

Sheet 10_SEVERITY
A1: Severity Analysis
A4: Severity only from the expert baseline. Weights fixed a priori: Critical=3, High=2, Medium=1 (never changed after seeing results).
A5: Approach | B5: Scenario | C5: Severity | D5: Reference | E5: TP | F5: FN | G5: Recall | H5: Weight
A6: OWASP | B6: S1 | C6: Critical | D6: =COUNTIFS('02_REFERENCE'!$B$2:$B$99,$B6,'02_REFERENCE'!$O$2:$O$99,$C6,'02_REFERENCE'!$S$2:$S$99,"YES") -> 5 | E6: =COUNTIFS('04_MATCHING'!$B$2:$B$1026,$A6,'04_MATCHING'!$C$2:$C$1026,$B6,'04_MATCHING'!$H$2:$H$1026,"Primary TP",'04_MATCHING'!$E$2:$E$1026,$C6) -> 2 | F6: =D6-E6 -> 3 | G6: =IFERROR(E6/D6,"") -> 0.4 | H6: 3
A7: OWASP | B7: S1 | C7: High | D7: =COUNTIFS('02_REFERENCE'!$B$2:$B$99,$B7,'02_REFERENCE'!$O$2:$O$99,$C7,'02_REFERENCE'!$S$2:$S$99,"YES") -> 17 | E7: =COUNTIFS('04_MATCHING'!$B$2:$B$1026,$A7,'04_MATCHING'!$C$2:$C$1026,$B7,'04_MATCHING'!$H$2:$H$1026,"Primary TP",'04_MATCHING'!$E$2:$E$1026,$C7) -> 2 | F7: =D7-E7 -> 15 | G7: =IFERROR(E7/D7,"") -> 0.11764706 | H7: 2
A8: OWASP | B8: S1 | C8: Medium | D8: =COUNTIFS('02_REFERENCE'!$B$2:$B$99,$B8,'02_REFERENCE'!$O$2:$O$99,$C8,'02_REFERENCE'!$S$2:$S$99,"YES") -> 10 | E8: =COUNTIFS('04_MATCHING'!$B$2:$B$1026,$A8,'04_MATCHING'!$C$2:$C$1026,$B8,'04_MATCHING'!$H$2:$H$1026,"Primary TP",'04_MATCHING'!$E$2:$E$1026,$C8) -> 2 | F8: =D8-E8 -> 8 | G8: =IFERROR(E8/D8,"") -> 0.2 | H8: 1
A9: OWASP | B9: S2 | C9: Critical | D9: =COUNTIFS('02_REFERENCE'!$B$2:$B$99,$B9,'02_REFERENCE'!$O$2:$O$99,$C9,'02_REFERENCE'!$S$2:$S$99,"YES") -> 9 | E9: =COUNTIFS('04_MATCHING'!$B$2:$B$1026,$A9,'04_MATCHING'!$C$2:$C$1026,$B9,'04_MATCHING'!$H$2:$H$1026,"Primary TP",'04_MATCHING'!$E$2:$E$1026,$C9) -> 2 | F9: =D9-E9 -> 7 | G9: =IFERROR(E9/D9,"") -> 0.22222222 | H9: 3
A10: OWASP | B10: S2 | C10: High | D10: =COUNTIFS('02_REFERENCE'!$B$2:$B$99,$B10,'02_REFERENCE'!$O$2:$O$99,$C10,'02_REFERENCE'!$S$2:$S$99,"YES") -> 16 | E10: =COUNTIFS('04_MATCHING'!$B$2:$B$1026,$A10,'04_MATCHING'!$C$2:$C$1026,$B10,'04_MATCHING'!$H$2:$H$1026,"Primary TP",'04_MATCHING'!$E$2:$E$1026,$C10) -> 3 | F10: =D10-E10 -> 13 | G10: =IFERROR(E10/D10,"") -> 0.1875 | H10: 2
A11: OWASP | B11: S2 | C11: Medium | D11: =COUNTIFS('02_REFERENCE'!$B$2:$B$99,$B11,'02_REFERENCE'!$O$2:$O$99,$C11,'02_REFERENCE'!$S$2:$S$99,"YES") -> 8 | E11: =COUNTIFS('04_MATCHING'!$B$2:$B$1026,$A11,'04_MATCHING'!$C$2:$C$1026,$B11,'04_MATCHING'!$H$2:$H$1026,"Primary TP",'04_MATCHING'!$E$2:$E$1026,$C11) -> 1 | F11: =D11-E11 -> 7 | G11: =IFERROR(E11/D11,"") -> 0.125 | H11: 1
A12: OWASP | B12: S3 | C12: Critical | D12: =COUNTIFS('02_REFERENCE'!$B$2:$B$99,$B12,'02_REFERENCE'!$O$2:$O$99,$C12,'02_REFERENCE'!$S$2:$S$99,"YES") -> 8 | E12: =COUNTIFS('04_MATCHING'!$B$2:$B$1026,$A12,'04_MATCHING'!$C$2:$C$1026,$B12,'04_MATCHING'!$H$2:$H$1026,"Primary TP",'04_MATCHING'!$E$2:$E$1026,$C12) -> 2 | F12: =D12-E12 -> 6 | G12: =IFERROR(E12/D12,"") -> 0.25 | H12: 3
A13: OWASP | B13: S3 | C13: High | D13: =COUNTIFS('02_REFERENCE'!$B$2:$B$99,$B13,'02_REFERENCE'!$O$2:$O$99,$C13,'02_REFERENCE'!$S$2:$S$99,"YES") -> 17 | E13: =COUNTIFS('04_MATCHING'!$B$2:$B$1026,$A13,'04_MATCHING'!$C$2:$C$1026,$B13,'04_MATCHING'!$H$2:$H$1026,"Primary TP",'04_MATCHING'!$E$2:$E$1026,$C13) -> 3 | F13: =D13-E13 -> 14 | G13: =IFERROR(E13/D13,"") -> 0.17647059 | H13: 2
A14: OWASP | B14: S3 | C14: Medium | D14: =COUNTIFS('02_REFERENCE'!$B$2:$B$99,$B14,'02_REFERENCE'!$O$2:$O$99,$C14,'02_REFERENCE'!$S$2:$S$99,"YES") -> 8 | E14: =COUNTIFS('04_MATCHING'!$B$2:$B$1026,$A14,'04_MATCHING'!$C$2:$C$1026,$B14,'04_MATCHING'!$H$2:$H$1026,"Primary TP",'04_MATCHING'!$E$2:$E$1026,$C14) -> 2 | F14: =D14-E14 -> 6 | G14: =IFERROR(E14/D14,"") -> 0.25 | H14: 1
A15: TMT | B15: S1 | C15: Critical | D15: =COUNTIFS('02_REFERENCE'!$B$2:$B$99,$B15,'02_REFERENCE'!$O$2:$O$99,$C15,'02_REFERENCE'!$S$2:$S$99,"YES") -> 5 | E15: =COUNTIFS('04_MATCHING'!$B$2:$B$1026,$A15,'04_MATCHING'!$C$2:$C$1026,$B15,'04_MATCHING'!$H$2:$H$1026,"Primary TP",'04_MATCHING'!$E$2:$E$1026,$C15) -> 4 | F15: =D15-E15 -> 1 | G15: =IFERROR(E15/D15,"") -> 0.8 | H15: 3
A16: TMT | B16: S1 | C16: High | D16: =COUNTIFS('02_REFERENCE'!$B$2:$B$99,$B16,'02_REFERENCE'!$O$2:$O$99,$C16,'02_REFERENCE'!$S$2:$S$99,"YES") -> 17 | E16: =COUNTIFS('04_MATCHING'!$B$2:$B$1026,$A16,'04_MATCHING'!$C$2:$C$1026,$B16,'04_MATCHING'!$H$2:$H$1026,"Primary TP",'04_MATCHING'!$E$2:$E$1026,$C16) -> 2 | F16: =D16-E16 -> 15 | G16: =IFERROR(E16/D16,"") -> 0.11764706 | H16: 2
A17: TMT | B17: S1 | C17: Medium | D17: =COUNTIFS('02_REFERENCE'!$B$2:$B$99,$B17,'02_REFERENCE'!$O$2:$O$99,$C17,'02_REFERENCE'!$S$2:$S$99,"YES") -> 10 | E17: =COUNTIFS('04_MATCHING'!$B$2:$B$1026,$A17,'04_MATCHING'!$C$2:$C$1026,$B17,'04_MATCHING'!$H$2:$H$1026,"Primary TP",'04_MATCHING'!$E$2:$E$1026,$C17) -> 3 | F17: =D17-E17 -> 7 | G17: =IFERROR(E17/D17,"") -> 0.3 | H17: 1
... A50: THREMOLIA | B50: S3 | C50: Medium | D50: =COUNTIFS('02_REFERENCE'!$B$2:$B$99,$B50,'02_REFERENCE'!$O$2:$O$99,$C50,'02_REFERENCE'!$S$2:$S$99,"YES") -> 8 | E50: =COUNTIFS('04_MATCHING'!$B$2:$B$1026,$A50,'04_MATCHING'!$C$2:$C$1026,$B50,'04_MATCHING'!$H$2:$H$1026,"Primary TP",'04_MATCHING'!$E$2:$E$1026,$C50) -> 5 | F50: =D50-E50 -> 3 | G50: =IFERROR(E50/D50,"") -> 0.625 | H50: 1
A52: Severity-weighted recall (Critical=3, High=2, Medium=1)
A53: Approach | B53: Scenario | C53: Weighted TP (sum w*TP) | D53: Weighted Reference (sum w*Ref) | E53: Severity-Weighted Recall
A54: OWASP | B54: S1 | C54: =SUMIFS(E$6:E$51,A$6:A$51,$A54,B$6:B$51,$B54,H$6:H$51,"3")*3 + SUMIFS(E$6:E$51,A$6:A$51,$A54,B$6:B$51,$B54,H$6:H$51,"2")*2 + SUMIFS(E$6:E$51,A$6:A$51,$A54,B$6:B$51,$B54,H$6:H$51,"1")*1 -> 12 | D54: =SUMIFS(D$6:D$51,A$6:A$51,$A54,B$6:B$51,$B54,H$6:H$51,"3")*3 + SUMIFS(D$6:D$51,A$6:A$51,$A54,B$6:B$51,$B54,H$6:H$51,"2")*2 + SUMIFS(D$6:D$51,A$6:A$51,$A54,B$6:B$51,$B54,H$6:H$51,"1")*1 -> 59 | E54: =IFERROR(C54/D54,"") -> 0.20338983
A55: OWASP | B55: S2 | C55: =SUMIFS(E$6:E$51,A$6:A$51,$A55,B$6:B$51,$B55,H$6:H$51,"3")*3 + SUMIFS(E$6:E$51,A$6:A$51,$A55,B$6:B$51,$B55,H$6:H$51,"2")*2 + SUMIFS(E$6:E$51,A$6:A$51,$A55,B$6:B$51,$B55,H$6:H$51,"1")*1 -> 13 | D55: =SUMIFS(D$6:D$51,A$6:A$51,$A55,B$6:B$51,$B55,H$6:H$51,"3")*3 + SUMIFS(D$6:D$51,A$6:A$51,$A55,B$6:B$51,$B55,H$6:H$51,"2")*2 + SUMIFS(D$6:D$51,A$6:A$51,$A55,B$6:B$51,$B55,H$6:H$51,"1")*1 -> 67 | E55: =IFERROR(C55/D55,"") -> 0.19402985
A56: OWASP | B56: S3 | C56: =SUMIFS(E$6:E$51,A$6:A$51,$A56,B$6:B$51,$B56,H$6:H$51,"3")*3 + SUMIFS(E$6:E$51,A$6:A$51,$A56,B$6:B$51,$B56,H$6:H$51,"2")*2 + SUMIFS(E$6:E$51,A$6:A$51,$A56,B$6:B$51,$B56,H$6:H$51,"1")*1 -> 14 | D56: =SUMIFS(D$6:D$51,A$6:A$51,$A56,B$6:B$51,$B56,H$6:H$51,"3")*3 + SUMIFS(D$6:D$51,A$6:A$51,$A56,B$6:B$51,$B56,H$6:H$51,"2")*2 + SUMIFS(D$6:D$51,A$6:A$51,$A56,B$6:B$51,$B56,H$6:H$51,"1")*1 -> 66 | E56: =IFERROR(C56/D56,"") -> 0.21212121
A57: TMT | B57: S1 | C57: =SUMIFS(E$6:E$51,A$6:A$51,$A57,B$6:B$51,$B57,H$6:H$51,"3")*3 + SUMIFS(E$6:E$51,A$6:A$51,$A57,B$6:B$51,$B57,H$6:H$51,"2")*2 + SUMIFS(E$6:E$51,A$6:A$51,$A57,B$6:B$51,$B57,H$6:H$51,"1")*1 -> 19 | D57: =SUMIFS(D$6:D$51,A$6:A$51,$A57,B$6:B$51,$B57,H$6:H$51,"3")*3 + SUMIFS(D$6:D$51,A$6:A$51,$A57,B$6:B$51,$B57,H$6:H$51,"2")*2 + SUMIFS(D$6:D$51,A$6:A$51,$A57,B$6:B$51,$B57,H$6:H$51,"1")*1 -> 59 | E57: =IFERROR(C57/D57,"") -> 0.3220339
A58: TMT | B58: S2 | C58: =SUMIFS(E$6:E$51,A$6:A$51,$A58,B$6:B$51,$B58,H$6:H$51,"3")*3 + SUMIFS(E$6:E$51,A$6:A$51,$A58,B$6:B$51,$B58,H$6:H$51,"2")*2 + SUMIFS(E$6:E$51,A$6:A$51,$A58,B$6:B$51,$B58,H$6:H$51,"1")*1 -> 20 | D58: =SUMIFS(D$6:D$51,A$6:A$51,$A58,B$6:B$51,$B58,H$6:H$51,"3")*3 + SUMIFS(D$6:D$51,A$6:A$51,$A58,B$6:B$51,$B58,H$6:H$51,"2")*2 + SUMIFS(D$6:D$51,A$6:A$51,$A58,B$6:B$51,$B58,H$6:H$51,"1")*1 -> 67 | E58: =IFERROR(C58/D58,"") -> 0.29850746
A59: TMT | B59: S3 | C59: =SUMIFS(E$6:E$51,A$6:A$51,$A59,B$6:B$51,$B59,H$6:H$51,"3")*3 + SUMIFS(E$6:E$51,A$6:A$51,$A59,B$6:B$51,$B59,H$6:H$51,"2")*2 + SUMIFS(E$6:E$51,A$6:A$51,$A59,B$6:B$51,$B59,H$6:H$51,"1")*1 -> 18 | D59: =SUMIFS(D$6:D$51,A$6:A$51,$A59,B$6:B$51,$B59,H$6:H$51,"3")*3 + SUMIFS(D$6:D$51,A$6:A$51,$A59,B$6:B$51,$B59,H$6:H$51,"2")*2 + SUMIFS(D$6:D$51,A$6:A$51,$A59,B$6:B$51,$B59,H$6:H$51,"1")*1 -> 66 | E59: =IFERROR(C59/D59,"") -> 0.27272727
A60: CHATGPT | B60: S1 | C60: =SUMIFS(E$6:E$51,A$6:A$51,$A60,B$6:B$51,$B60,H$6:H$51,"3")*3 + SUMIFS(E$6:E$51,A$6:A$51,$A60,B$6:B$51,$B60,H$6:H$51,"2")*2 + SUMIFS(E$6:E$51,A$6:A$51,$A60,B$6:B$51,$B60,H$6:H$51,"1")*1 -> 32 | D60: =SUMIFS(D$6:D$51,A$6:A$51,$A60,B$6:B$51,$B60,H$6:H$51,"3")*3 + SUMIFS(D$6:D$51,A$6:A$51,$A60,B$6:B$51,$B60,H$6:H$51,"2")*2 + SUMIFS(D$6:D$51,A$6:A$51,$A60,B$6:B$51,$B60,H$6:H$51,"1")*1 -> 59 | E60: =IFERROR(C60/D60,"") -> 0.54237288
A61: CHATGPT | B61: S2 | C61: =SUMIFS(E$6:E$51,A$6:A$51,$A61,B$6:B$51,$B61,H$6:H$51,"3")*3 + SUMIFS(E$6:E$51,A$6:A$51,$A61,B$6:B$51,$B61,H$6:H$51,"2")*2 + SUMIFS(E$6:E$51,A$6:A$51,$A61,B$6:B$51,$B61,H$6:H$51,"1")*1 -> 34 | D61: =SUMIFS(D$6:D$51,A$6:A$51,$A61,B$6:B$51,$B61,H$6:H$51,"3")*3 + SUMIFS(D$6:D$51,A$6:A$51,$A61,B$6:B$51,$B61,H$6:H$51,"2")*2 + SUMIFS(D$6:D$51,A$6:A$51,$A61,B$6:B$51,$B61,H$6:H$51,"1")*1 -> 67 | E61: =IFERROR(C61/D61,"") -> 0.50746269
A62: CHATGPT | B62: S3 | C62: =SUMIFS(E$6:E$51,A$6:A$51,$A62,B$6:B$51,$B62,H$6:H$51,"3")*3 + SUMIFS(E$6:E$51,A$6:A$51,$A62,B$6:B$51,$B62,H$6:H$51,"2")*2 + SUMIFS(E$6:E$51,A$6:A$51,$A62,B$6:B$51,$B62,H$6:H$51,"1")*1 -> 28 | D62: =SUMIFS(D$6:D$51,A$6:A$51,$A62,B$6:B$51,$B62,H$6:H$51,"3")*3 + SUMIFS(D$6:D$51,A$6:A$51,$A62,B$6:B$51,$B62,H$6:H$51,"2")*2 + SUMIFS(D$6:D$51,A$6:A$51,$A62,B$6:B$51,$B62,H$6:H$51,"1")*1 -> 66 | E62: =IFERROR(C62/D62,"") -> 0.42424242
A63: OLLAMA | B63: S1 | C63: =SUMIFS(E$6:E$51,A$6:A$51,$A63,B$6:B$51,$B63,H$6:H$51,"3")*3 + SUMIFS(E$6:E$51,A$6:A$51,$A63,B$6:B$51,$B63,H$6:H$51,"2")*2 + SUMIFS(E$6:E$51,A$6:A$51,$A63,B$6:B$51,$B63,H$6:H$51,"1")*1 -> 15 | D63: =SUMIFS(D$6:D$51,A$6:A$51,$A63,B$6:B$51,$B63,H$6:H$51,"3")*3 + SUMIFS(D$6:D$51,A$6:A$51,$A63,B$6:B$51,$B63,H$6:H$51,"2")*2 + SUMIFS(D$6:D$51,A$6:A$51,$A63,B$6:B$51,$B63,H$6:H$51,"1")*1 -> 59 | E63: =IFERROR(C63/D63,"") -> 0.25423729
A64: OLLAMA | B64: S2 | C64: =SUMIFS(E$6:E$51,A$6:A$51,$A64,B$6:B$51,$B64,H$6:H$51,"3")*3 + SUMIFS(E$6:E$51,A$6:A$51,$A64,B$6:B$51,$B64,H$6:H$51,"2")*2 + SUMIFS(E$6:E$51,A$6:A$51,$A64,B$6:B$51,$B64,H$6:H$51,"1")*1 -> 17 | D64: =SUMIFS(D$6:D$51,A$6:A$51,$A64,B$6:B$51,$B64,H$6:H$51,"3")*3 + SUMIFS(D$6:D$51,A$6:A$51,$A64,B$6:B$51,$B64,H$6:H$51,"2")*2 + SUMIFS(D$6:D$51,A$6:A$51,$A64,B$6:B$51,$B64,H$6:H$51,"1")*1 -> 67 | E64: =IFERROR(C64/D64,"") -> 0.25373134
A65: OLLAMA | B65: S3 | C65: =SUMIFS(E$6:E$51,A$6:A$51,$A65,B$6:B$51,$B65,H$6:H$51,"3")*3 + SUMIFS(E$6:E$51,A$6:A$51,$A65,B$6:B$51,$B65,H$6:H$51,"2")*2 + SUMIFS(E$6:E$51,A$6:A$51,$A65,B$6:B$51,$B65,H$6:H$51,"1")*1 -> 15 | D65: =SUMIFS(D$6:D$51,A$6:A$51,$A65,B$6:B$51,$B65,H$6:H$51,"3")*3 + SUMIFS(D$6:D$51,A$6:A$51,$A65,B$6:B$51,$B65,H$6:H$51,"2")*2 + SUMIFS(D$6:D$51,A$6:A$51,$A65,B$6:B$51,$B65,H$6:H$51,"1")*1 -> 66 | E65: =IFERROR(C65/D65,"") -> 0.22727273
... A68: THREMOLIA | B68: S3 | C68: =SUMIFS(E$6:E$51,A$6:A$51,$A68,B$6:B$51,$B68,H$6:H$51,"3")*3 + SUMIFS(E$6:E$51,A$6:A$51,$A68,B$6:B$51,$B68,H$6:H$51,"2")*2 + SUMIFS(E$6:E$51,A$6:A$51,$A68,B$6:B$51,$B68,H$6:H$51,"1")*1 -> 40 | D68: =SUMIFS(D$6:D$51,A$6:A$51,$A68,B$6:B$51,$B68,H$6:H$51,"3")*3 + SUMIFS(D$6:D$51,A$6:A$51,$A68,B$6:B$51,$B68,H$6:H$51,"2")*2 + SUMIFS(D$6:D$51,A$6:A$51,$A68,B$6:B$51,$B68,H$6:H$51,"1")*1 -> 66 | E68: =IFERROR(C68/D68,"") -> 0.60606061
A70: Note: severity-weighted recall = (3*TP_Critical + 2*TP_High + 1*TP_Medium) / (3*Ref_Critical + 2*Ref_High + 1*Ref_Medium). Weights are fixed a priori.

Sheet 11_LLM_ANALYSIS
A1: LLM-specific vs Non-LLM reference coverage
A2: LLM-specific classification taken from the expert reference baseline (column Q of 02_REFERENCE), never inferred from generated findings.
A4: Approach | B4: Scenario | C4: LLM-specific reference threats | D4: LLM-specific TP | E4: LLM-specific FN | F4: LLM-specific Recall | G4: Non-LLM reference threats | H4: Non-LLM TP | I4: Non-LLM FN | J4: Non-LLM Recall
A5: OWASP | B5: S1 | C5: =COUNTIFS('02_REFERENCE'!$B$2:$B$99,$B5,'02_REFERENCE'!$Q$2:$Q$99,"Yes",'02_REFERENCE'!$S$2:$S$99,"YES") -> 13 | D5: =COUNTIFS('04_MATCHING'!$B$2:$B$1026,$A5,'04_MATCHING'!$C$2:$C$1026,$B5,'04_MATCHING'!$H$2:$H$1026,"Primary TP",'04_MATCHING'!$F$2:$F$1026,"Yes") -> 2 | E5: =C5-D5 -> 11 | F5: =IFERROR(D5/C5,"") -> 0.15384615 | G5: =COUNTIFS('02_REFERENCE'!$B$2:$B$99,$B5,'02_REFERENCE'!$Q$2:$Q$99,"No",'02_REFERENCE'!$S$2:$S$99,"YES") -> 19 | H5: =COUNTIFS('04_MATCHING'!$B$2:$B$1026,$A5,'04_MATCHING'!$C$2:$C$1026,$B5,'04_MATCHING'!$H$2:$H$1026,"Primary TP",'04_MATCHING'!$F$2:$F$1026,"No") -> 4 | I5: =G5-H5 -> 15 | J5: =IFERROR(H5/G5,"") -> 0.21052632
A6: OWASP | B6: S2 | C6: =COUNTIFS('02_REFERENCE'!$B$2:$B$99,$B6,'02_REFERENCE'!$Q$2:$Q$99,"Yes",'02_REFERENCE'!$S$2:$S$99,"YES") -> 13 | D6: =COUNTIFS('04_MATCHING'!$B$2:$B$1026,$A6,'04_MATCHING'!$C$2:$C$1026,$B6,'04_MATCHING'!$H$2:$H$1026,"Primary TP",'04_MATCHING'!$F$2:$F$1026,"Yes") -> 1 | E6: =C6-D6 -> 12 | F6: =IFERROR(D6/C6,"") -> 0.076923077 | G6: =COUNTIFS('02_REFERENCE'!$B$2:$B$99,$B6,'02_REFERENCE'!$Q$2:$Q$99,"No",'02_REFERENCE'!$S$2:$S$99,"YES") -> 20 | H6: =COUNTIFS('04_MATCHING'!$B$2:$B$1026,$A6,'04_MATCHING'!$C$2:$C$1026,$B6,'04_MATCHING'!$H$2:$H$1026,"Primary TP",'04_MATCHING'!$F$2:$F$1026,"No") -> 5 | I6: =G6-H6 -> 15 | J6: =IFERROR(H6/G6,"") -> 0.25
A7: OWASP | B7: S3 | C7: =COUNTIFS('02_REFERENCE'!$B$2:$B$99,$B7,'02_REFERENCE'!$Q$2:$Q$99,"Yes",'02_REFERENCE'!$S$2:$S$99,"YES") -> 12 | D7: =COUNTIFS('04_MATCHING'!$B$2:$B$1026,$A7,'04_MATCHING'!$C$2:$C$1026,$B7,'04_MATCHING'!$H$2:$H$1026,"Primary TP",'04_MATCHING'!$F$2:$F$1026,"Yes") -> 1 | E7: =C7-D7 -> 11 | F7: =IFERROR(D7/C7,"") -> 0.083333333 | G7: =COUNTIFS('02_REFERENCE'!$B$2:$B$99,$B7,'02_REFERENCE'!$Q$2:$Q$99,"No",'02_REFERENCE'!$S$2:$S$99,"YES") -> 21 | H7: =COUNTIFS('04_MATCHING'!$B$2:$B$1026,$A7,'04_MATCHING'!$C$2:$C$1026,$B7,'04_MATCHING'!$H$2:$H$1026,"Primary TP",'04_MATCHING'!$F$2:$F$1026,"No") -> 6 | I7: =G7-H7 -> 15 | J7: =IFERROR(H7/G7,"") -> 0.28571429
A8: TMT | B8: S1 | C8: =COUNTIFS('02_REFERENCE'!$B$2:$B$99,$B8,'02_REFERENCE'!$Q$2:$Q$99,"Yes",'02_REFERENCE'!$S$2:$S$99,"YES") -> 13 | D8: =COUNTIFS('04_MATCHING'!$B$2:$B$1026,$A8,'04_MATCHING'!$C$2:$C$1026,$B8,'04_MATCHING'!$H$2:$H$1026,"Primary TP",'04_MATCHING'!$F$2:$F$1026,"Yes") -> 4 | E8: =C8-D8 -> 9 | F8: =IFERROR(D8/C8,"") -> 0.30769231 | G8: =COUNTIFS('02_REFERENCE'!$B$2:$B$99,$B8,'02_REFERENCE'!$Q$2:$Q$99,"No",'02_REFERENCE'!$S$2:$S$99,"YES") -> 19 | H8: =COUNTIFS('04_MATCHING'!$B$2:$B$1026,$A8,'04_MATCHING'!$C$2:$C$1026,$B8,'04_MATCHING'!$H$2:$H$1026,"Primary TP",'04_MATCHING'!$F$2:$F$1026,"No") -> 5 | I8: =G8-H8 -> 14 | J8: =IFERROR(H8/G8,"") -> 0.26315789
A9: TMT | B9: S2 | C9: =COUNTIFS('02_REFERENCE'!$B$2:$B$99,$B9,'02_REFERENCE'!$Q$2:$Q$99,"Yes",'02_REFERENCE'!$S$2:$S$99,"YES") -> 13 | D9: =COUNTIFS('04_MATCHING'!$B$2:$B$1026,$A9,'04_MATCHING'!$C$2:$C$1026,$B9,'04_MATCHING'!$H$2:$H$1026,"Primary TP",'04_MATCHING'!$F$2:$F$1026,"Yes") -> 4 | E9: =C9-D9 -> 9 | F9: =IFERROR(D9/C9,"") -> 0.30769231 | G9: =COUNTIFS('02_REFERENCE'!$B$2:$B$99,$B9,'02_REFERENCE'!$Q$2:$Q$99,"No",'02_REFERENCE'!$S$2:$S$99,"YES") -> 20 | H9: =COUNTIFS('04_MATCHING'!$B$2:$B$1026,$A9,'04_MATCHING'!$C$2:$C$1026,$B9,'04_MATCHING'!$H$2:$H$1026,"Primary TP",'04_MATCHING'!$F$2:$F$1026,"No") -> 6 | I9: =G9-H9 -> 14 | J9: =IFERROR(H9/G9,"") -> 0.3
A10: TMT | B10: S3 | C10: =COUNTIFS('02_REFERENCE'!$B$2:$B$99,$B10,'02_REFERENCE'!$Q$2:$Q$99,"Yes",'02_REFERENCE'!$S$2:$S$99,"YES") -> 12 | D10: =COUNTIFS('04_MATCHING'!$B$2:$B$1026,$A10,'04_MATCHING'!$C$2:$C$1026,$B10,'04_MATCHING'!$H$2:$H$1026,"Primary TP",'04_MATCHING'!$F$2:$F$1026,"Yes") -> 3 | E10: =C10-D10 -> 9 | F10: =IFERROR(D10/C10,"") -> 0.25 | G10: =COUNTIFS('02_REFERENCE'!$B$2:$B$99,$B10,'02_REFERENCE'!$Q$2:$Q$99,"No",'02_REFERENCE'!$S$2:$S$99,"YES") -> 21 | H10: =COUNTIFS('04_MATCHING'!$B$2:$B$1026,$A10,'04_MATCHING'!$C$2:$C$1026,$B10,'04_MATCHING'!$H$2:$H$1026,"Primary TP",'04_MATCHING'!$F$2:$F$1026,"No") -> 6 | I10: =G10-H10 -> 15 | J10: =IFERROR(H10/G10,"") -> 0.28571429
A11: CHATGPT | B11: S1 | C11: =COUNTIFS('02_REFERENCE'!$B$2:$B$99,$B11,'02_REFERENCE'!$Q$2:$Q$99,"Yes",'02_REFERENCE'!$S$2:$S$99,"YES") -> 13 | D11: =COUNTIFS('04_MATCHING'!$B$2:$B$1026,$A11,'04_MATCHING'!$C$2:$C$1026,$B11,'04_MATCHING'!$H$2:$H$1026,"Primary TP",'04_MATCHING'!$F$2:$F$1026,"Yes") -> 9 | E11: =C11-D11 -> 4 | F11: =IFERROR(D11/C11,"") -> 0.69230769 | G11: =COUNTIFS('02_REFERENCE'!$B$2:$B$99,$B11,'02_REFERENCE'!$Q$2:$Q$99,"No",'02_REFERENCE'!$S$2:$S$99,"YES") -> 19 | H11: =COUNTIFS('04_MATCHING'!$B$2:$B$1026,$A11,'04_MATCHING'!$C$2:$C$1026,$B11,'04_MATCHING'!$H$2:$H$1026,"Primary TP",'04_MATCHING'!$F$2:$F$1026,"No") -> 9 | I11: =G11-H11 -> 10 | J11: =IFERROR(H11/G11,"") -> 0.47368421
A12: CHATGPT | B12: S2 | C12: =COUNTIFS('02_REFERENCE'!$B$2:$B$99,$B12,'02_REFERENCE'!$Q$2:$Q$99,"Yes",'02_REFERENCE'!$S$2:$S$99,"YES") -> 13 | D12: =COUNTIFS('04_MATCHING'!$B$2:$B$1026,$A12,'04_MATCHING'!$C$2:$C$1026,$B12,'04_MATCHING'!$H$2:$H$1026,"Primary TP",'04_MATCHING'!$F$2:$F$1026,"Yes") -> 9 | E12: =C12-D12 -> 4 | F12: =IFERROR(D12/C12,"") -> 0.69230769 | G12: =COUNTIFS('02_REFERENCE'!$B$2:$B$99,$B12,'02_REFERENCE'!$Q$2:$Q$99,"No",'02_REFERENCE'!$S$2:$S$99,"YES") -> 20 | H12: =COUNTIFS('04_MATCHING'!$B$2:$B$1026,$A12,'04_MATCHING'!$C$2:$C$1026,$B12,'04_MATCHING'!$H$2:$H$1026,"Primary TP",'04_MATCHING'!$F$2:$F$1026,"No") -> 9 | I12: =G12-H12 -> 11 | J12: =IFERROR(H12/G12,"") -> 0.45
A13: CHATGPT | B13: S3 | C13: =COUNTIFS('02_REFERENCE'!$B$2:$B$99,$B13,'02_REFERENCE'!$Q$2:$Q$99,"Yes",'02_REFERENCE'!$S$2:$S$99,"YES") -> 12 | D13: =COUNTIFS('04_MATCHING'!$B$2:$B$1026,$A13,'04_MATCHING'!$C$2:$C$1026,$B13,'04_MATCHING'!$H$2:$H$1026,"Primary TP",'04_MATCHING'!$F$2:$F$1026,"Yes") -> 7 | E13: =C13-D13 -> 5 | F13: =IFERROR(D13/C13,"") -> 0.58333333 | G13: =COUNTIFS('02_REFERENCE'!$B$2:$B$99,$B13,'02_REFERENCE'!$Q$2:$Q$99,"No",'02_REFERENCE'!$S$2:$S$99,"YES") -> 21 | H13: =COUNTIFS('04_MATCHING'!$B$2:$B$1026,$A13,'04_MATCHING'!$C$2:$C$1026,$B13,'04_MATCHING'!$H$2:$H$1026,"Primary TP",'04_MATCHING'!$F$2:$F$1026,"No") -> 9 | I13: =G13-H13 -> 12 | J13: =IFERROR(H13/G13,"") -> 0.42857143
A14: OLLAMA | B14: S1 | C14: =COUNTIFS('02_REFERENCE'!$B$2:$B$99,$B14,'02_REFERENCE'!$Q$2:$Q$99,"Yes",'02_REFERENCE'!$S$2:$S$99,"YES") -> 13 | D14: =COUNTIFS('04_MATCHING'!$B$2:$B$1026,$A14,'04_MATCHING'!$C$2:$C$1026,$B14,'04_MATCHING'!$H$2:$H$1026,"Primary TP",'04_MATCHING'!$F$2:$F$1026,"Yes") -> 3 | E14: =C14-D14 -> 10 | F14: =IFERROR(D14/C14,"") -> 0.23076923 | G14: =COUNTIFS('02_REFERENCE'!$B$2:$B$99,$B14,'02_REFERENCE'!$Q$2:$Q$99,"No",'02_REFERENCE'!$S$2:$S$99,"YES") -> 19 | H14: =COUNTIFS('04_MATCHING'!$B$2:$B$1026,$A14,'04_MATCHING'!$C$2:$C$1026,$B14,'04_MATCHING'!$H$2:$H$1026,"Primary TP",'04_MATCHING'!$F$2:$F$1026,"No") -> 3 | I14: =G14-H14 -> 16 | J14: =IFERROR(H14/G14,"") -> 0.15789474
A15: OLLAMA | B15: S2 | C15: =COUNTIFS('02_REFERENCE'!$B$2:$B$99,$B15,'02_REFERENCE'!$Q$2:$Q$99,"Yes",'02_REFERENCE'!$S$2:$S$99,"YES") -> 13 | D15: =COUNTIFS('04_MATCHING'!$B$2:$B$1026,$A15,'04_MATCHING'!$C$2:$C$1026,$B15,'04_MATCHING'!$H$2:$H$1026,"Primary TP",'04_MATCHING'!$F$2:$F$1026,"Yes") -> 3 | E15: =C15-D15 -> 10 | F15: =IFERROR(D15/C15,"") -> 0.23076923 | G15: =COUNTIFS('02_REFERENCE'!$B$2:$B$99,$B15,'02_REFERENCE'!$Q$2:$Q$99,"No",'02_REFERENCE'!$S$2:$S$99,"YES") -> 20 | H15: =COUNTIFS('04_MATCHING'!$B$2:$B$1026,$A15,'04_MATCHING'!$C$2:$C$1026,$B15,'04_MATCHING'!$H$2:$H$1026,"Primary TP",'04_MATCHING'!$F$2:$F$1026,"No") -> 4 | I15: =G15-H15 -> 16 | J15: =IFERROR(H15/G15,"") -> 0.2
A16: OLLAMA | B16: S3 | C16: =COUNTIFS('02_REFERENCE'!$B$2:$B$99,$B16,'02_REFERENCE'!$Q$2:$Q$99,"Yes",'02_REFERENCE'!$S$2:$S$99,"YES") -> 12 | D16: =COUNTIFS('04_MATCHING'!$B$2:$B$1026,$A16,'04_MATCHING'!$C$2:$C$1026,$B16,'04_MATCHING'!$H$2:$H$1026,"Primary TP",'04_MATCHING'!$F$2:$F$1026,"Yes") -> 2 | E16: =C16-D16 -> 10 | F16: =IFERROR(D16/C16,"") -> 0.16666667 | G16: =COUNTIFS('02_REFERENCE'!$B$2:$B$99,$B16,'02_REFERENCE'!$Q$2:$Q$99,"No",'02_REFERENCE'!$S$2:$S$99,"YES") -> 21 | H16: =COUNTIFS('04_MATCHING'!$B$2:$B$1026,$A16,'04_MATCHING'!$C$2:$C$1026,$B16,'04_MATCHING'!$H$2:$H$1026,"Primary TP",'04_MATCHING'!$F$2:$F$1026,"No") -> 5 | I16: =G16-H16 -> 16 | J16: =IFERROR(H16/G16,"") -> 0.23809524
... A19: THREMOLIA | B19: S3 | C19: =COUNTIFS('02_REFERENCE'!$B$2:$B$99,$B19,'02_REFERENCE'!$Q$2:$Q$99,"Yes",'02_REFERENCE'!$S$2:$S$99,"YES") -> 12 | D19: =COUNTIFS('04_MATCHING'!$B$2:$B$1026,$A19,'04_MATCHING'!$C$2:$C$1026,$B19,'04_MATCHING'!$H$2:$H$1026,"Primary TP",'04_MATCHING'!$F$2:$F$1026,"Yes") -> 6 | E19: =C19-D19 -> 6 | F19: =IFERROR(D19/C19,"") -> 0.5 | G19: =COUNTIFS('02_REFERENCE'!$B$2:$B$99,$B19,'02_REFERENCE'!$Q$2:$Q$99,"No",'02_REFERENCE'!$S$2:$S$99,"YES") -> 21 | H19: =COUNTIFS('04_MATCHING'!$B$2:$B$1026,$A19,'04_MATCHING'!$C$2:$C$1026,$B19,'04_MATCHING'!$H$2:$H$1026,"Primary TP",'04_MATCHING'!$F$2:$F$1026,"No") -> 14 | I19: =G19-H19 -> 7 | J19: =IFERROR(H19/G19,"") -> 0.66666667
A20: TOTAL | B20: All | C20: =SUM(C5:C19) -> 190 | D20: =SUM(D5:D19) -> 72 | E20: =SUM(E5:E19) -> 118 | F20: =IFERROR(D20/C20,"") -> 0.37894737 | G20: =SUM(G5:G19) -> 300 | H20: =SUM(H5:H19) -> 116 | I20: =SUM(I5:I19) -> 184 | J20: =IFERROR(H20/G20,"") -> 0.38666667

Sheet 12_FEATURES_MCDM
A1: Feature / Functionality Matrix + MCDM (decision-support synthesis)
A2: Feature matrix requires manual coding from documentation. No documentation was provided, so every cell is "Unknown" (honest default) and Feature Completeness + MCDM composite = N/A - DATA NOT AVAILABLE. MCDM is decision-support synthesis, NOT a statistical metric. No SUS/usability scores (no formal SUS study conducted).
A4: Capability / Feature | B4: OWASP Threat Dragon | C4: Microsoft TMT | D4: ChatGPT | E4: Ollama | F4: ThreMoLIA
A5: Graphical architecture modelling (draw diagram) | B5: Unknown | C5: Unknown | D5: Unknown | E5: Unknown | F5: Unknown
A6: Built-in threat catalogue / rule engine | B6: Unknown | C6: Unknown | D6: Unknown | E6: Unknown | F6: Unknown
A7: Automated threat identification | B7: Unknown | C7: Unknown | D7: Unknown | E7: Unknown | F7: Unknown
A8: STRIDE category assignment | B8: Unknown | C8: Unknown | D8: Unknown | E8: Unknown | F8: Unknown
A9: Data-flow and trust-boundary capture | B9: Unknown | C9: Unknown | D9: Unknown | E9: Unknown | F9: Unknown
A10: Manual threat entry and annotation | B10: Unknown | C10: Unknown | D10: Unknown | E10: Unknown | F10: Unknown
A11: Prompt/LLM-supported generation | B11: Unknown | C11: Unknown | D11: Unknown | E11: Unknown | F11: Unknown
A12: Runs locally (no external LLM) | B12: Unknown | C12: Unknown | D12: Unknown | E12: Unknown | F12: Unknown
A13: Export / shareable results | B13: Unknown | C13: Unknown | D13: Unknown | E13: Unknown | F13: Unknown
A14: Traceability to architectural element | B14: Unknown | C14: Unknown | D14: Unknown | E14: Unknown | F14: Unknown
A15: Documentation reference / guidance | B15: Unknown | C15: Unknown | D15: Unknown | E15: Unknown | F15: Unknown
... A18: Cross-checking / deduplication | B18: Unknown | C18: Unknown | D18: Unknown | E18: Unknown | F18: Unknown
A19: Feature Completeness (% of cells = Native/External) | B19: =IFERROR(COUNTIF(B5:B18,"Native")+COUNTIF(B5:B18,"External/Manual")+COUNTIF(B5:B18,"Prompt-supported"),"N/A") -> 0 | C19: =IFERROR(COUNTIF(C5:C18,"Native")+COUNTIF(C5:C18,"External/Manual")+COUNTIF(C5:C18,"Prompt-supported"),"N/A") -> 0 | D19: =IFERROR(COUNTIF(D5:D18,"Native")+COUNTIF(D5:D18,"External/Manual")+COUNTIF(D5:D18,"Prompt-supported"),"N/A") -> 0 | E19: =IFERROR(COUNTIF(E5:E18,"Native")+COUNTIF(E5:E18,"External/Manual")+COUNTIF(E5:E18,"Prompt-supported"),"N/A") -> 0 | F19: =IFERROR(COUNTIF(F5:F18,"Native")+COUNTIF(F5:F18,"External/Manual")+COUNTIF(F5:F18,"Prompt-supported"),"N/A") -> 0
A21: Feature coding legend
A22: Native | B22: Fully supported natively out-of-the-box
A23: External/Manual | B23: Supported but requires external tool or manual effort
A24: Prompt-supported | B24: Supported via prompt/LLM assistance, not native
A25: Not Supported | B25: Not supported
A26: Unknown | B26: Not verifiable from provided documentation (default for all cells here)
A28: MCDM Ranking (weights fixed a priori)
A29: Approach | B29: Precision (30%) | C29: Recall (30%) | D29: Grounding (20%) | E29: Feature Completeness (20%) | F29: Overall Score (0.30P+0.30R+0.20G+0.20F) | G29: Rank
A30: OWASP | B30: =IFERROR(SUMIFS('05_TP_FP_FN'!$E$5:$E$19,'05_TP_FP_FN'!$A$5:$A$19,$A30)/(SUMIFS('05_TP_FP_FN'!$E$5:$E$19,'05_TP_FP_FN'!$A$5:$A$19,$A30)+SUMIFS('05_TP_FP_FN'!$F$5:$F$19,'05_TP_FP_FN'!$A$5:$A$19,$A30)),"") -> 0.19387755 | C30: =IFERROR(SUMIFS('05_TP_FP_FN'!$E$5:$E$19,'05_TP_FP_FN'!$A$5:$A$19,$A30)/SUMIFS('05_TP_FP_FN'!$D$5:$D$19,'05_TP_FP_FN'!$A$5:$A$19,$A30),"") -> 0.19387755 | D30: N/A - DATA NOT AVAILABLE | E30: N/A - DATA NOT AVAILABLE | F30: =IF(OR(ISNUMBER(D30),ISNUMBER(E30)),0.3*N(B30)+0.3*N(C30)+0.2*N(D30)+0.2*N(E30),"N/A - DATA NOT AVAILABLE") -> N/A - DATA NOT AVAILABLE | G30: N/A
A31: TMT | B31: =IFERROR(SUMIFS('05_TP_FP_FN'!$E$5:$E$19,'05_TP_FP_FN'!$A$5:$A$19,$A31)/(SUMIFS('05_TP_FP_FN'!$E$5:$E$19,'05_TP_FP_FN'!$A$5:$A$19,$A31)+SUMIFS('05_TP_FP_FN'!$F$5:$F$19,'05_TP_FP_FN'!$A$5:$A$19,$A31)),"") -> 0.1124498 | C31: =IFERROR(SUMIFS('05_TP_FP_FN'!$E$5:$E$19,'05_TP_FP_FN'!$A$5:$A$19,$A31)/SUMIFS('05_TP_FP_FN'!$D$5:$D$19,'05_TP_FP_FN'!$A$5:$A$19,$A31),"") -> 0.28571429 | D31: N/A - DATA NOT AVAILABLE | E31: N/A - DATA NOT AVAILABLE | F31: =IF(OR(ISNUMBER(D31),ISNUMBER(E31)),0.3*N(B31)+0.3*N(C31)+0.2*N(D31)+0.2*N(E31),"N/A - DATA NOT AVAILABLE") -> N/A - DATA NOT AVAILABLE | G31: N/A
